Workbook

Sheet crecimientos
A2: 2025 | B2: Global 2025 | C2: Global 2026 | D2: Vta Ecom 2025 | E2: Venta Ecom 2026 | F2: Digital 2025 | G2: Digital 2026 | H2: MKP 2025 | I2: MKP 2026 | J2: 2026 | K2: Venta Meta 2026 | L2: Meta Digital | M2: Meta MKPlace | N2: Web + APP 2025 | O2: Web + APP 2026 | P2: Afiliados 2025 | Q2: Afiliados 2026 | R2: TMK 2025 | S2: TMK 2026 | T2: WA 2025 | U2: WA 2026 | V2: Ent. en Tienda 2025 | W2: Ent. en Tienda 2026 | X2: Meli Drop 2025 | Y2: Meli Drop 2026 | Z2: Meli Full 2025 | AA2: Meli Full 2026 | AB2: Amazon Drop 2025 | AC2: Amazon Drop 2026 | AD2: Amazon Full 2025 | AE2: Amazon Full 2026 | AF2: TikTok 2025 | AG2: TikTok 2026 | AH2: Shein 2025 | AI2: Shein 2026 | AJ2: MELI 2025 | AK2: MELI2026 | AL2: AMZ 2025 | AM2: AMZ 2026 | AN2: 2026 | AO2: Global | AP2: Ecomm | AQ2: Digital | AR2: MKP | AS2: Web + APP | AT2: Afiliados | AU2: TMK | AV2: WA | AW2: Ent. en Tienda | AX2: Meli Drop | AY2: Meli Full | AZ2: MELI | BA2: Amazon Drop | BB2: Amazon Full | BC2: AMAZON | BD2: TikTok | BE2: Shein
A3: 45659 | B3: 35585285 | C3: 1767787 | D3: 3530236.3 | E3: 1767692 | F3: =SUM(N3,P3,R3,T3,V3) -> 2657177.3 | G3: =SUM(O3,Q3,S3,U3,W3) -> 1137078 | H3: =SUM(X3,Z3,AB3,AD3,AF3,AH3) -> 873059 | I3: =SUM(Y3,AA3,AC3,AE3,AG3,AI3) -> 630614 | J3: 46023 | K3: -36578.828 | L3: -91461.011 | M3: 54882.183 | N3: 2533552 | O3: 1117875 | P3: 48254.31 | Q3: 17319 | R3: 21696 | S3: 0 | T3: 5984 | U3: 1884 | V3: 47691 | W3: 0 | X3: 671816 | Y3: 511381 | Z3: 116771 | AA3: 78269 | AB3: 84472 | AC3: 31357 | AD3: 0 | AE3: 7591 | AF3: 0 | AG3: 2016 | AH3: 0 | AI3: 0 | AJ3: =X3+Z3 -> 788587 | AK3: =Y3+AA3 -> 589650 | AL3: =AD3+AB3 -> 84472 | AM3: =AE3+AC3 -> 38948 | AN3: 46023 | AO3: =C3/B3-1 -> -0.95032253 | AP3: =E3/D3-1 -> -0.49927091 | AQ3: =G3/F3-1 -> -0.57207297 | AR3: =I3/H3-1 -> -0.27769601 | AS3: =O3/N3-1 -> -0.55877164 | AT3: =Q3/P3-1 -> -0.64108906 | AU3: =S3/R3-1 -> -1 | AV3: =U3/T3-1 -> -0.68516043 | AW3: =W3/V3-1 -> -1 | AX3: =Y3/X3-1 -> -0.23880795 | AY3: =AA3/Z3-1 -> -0.32972228 | AZ3: =AK3/AJ3-1 -> -0.2522702 | BA3: =AC3/AB3-1 -> -0.62878824 | BB3: =AE3/AD3-1 -> #DIV/0! | BC3: =AM3/AL3-1 -> -0.53892414 | BD3: =AG3/AF3-1 -> #DIV/0! | BE3: =AI3/AH3-1 -> #DIV/0!
A4: 45660 | B4: 45059441 | C4: 37878399 | D4: 2122251.3 | E4: 3057411 | F4: =SUM(N4,P4,R4,T4,V4) -> 1350420.3 | G4: =SUM(O4,Q4,S4,U4,W4) -> 1978374 | H4: =SUM(X4,Z4,AB4,AD4,AF4,AH4) -> 771831 | I4: =SUM(Y4,AA4,AC4,AE4,AG4,AI4) -> 1079037 | J4: 46024 | K4: 4512263.3 | L4: 3388096 | M4: 1124167.3 | N4: 1249824 | O4: 1824628 | P4: 33610.345 | Q4: 32072 | R4: 21922 | S4: 15461 | T4: 4267 | U4: 5339 | V4: 40797 | W4: 100874 | X4: 650641 | Y4: 906403 | Z4: 73651 | AA4: 134485 | AB4: 47539 | AC4: 28403 | AD4: 0 | AE4: 8334 | AF4: 0 | AG4: 1412 | AH4: 0 | AI4: 0 | AJ4: =X4+Z4 -> 724292 | AK4: =Y4+AA4 -> 1040888 | AL4: =AD4+AB4 -> 47539 | AM4: =AE4+AC4 -> 36737 | AN4: 46024 | AO4: =C4/B4-1 -> -0.1593682 | AP4: =E4/D4-1 -> 0.4406451 | AQ4: =G4/F4-1 -> 0.46500607 | AR4: =I4/H4-1 -> 0.39802236 | AS4: =O4/N4-1 -> 0.45990796 | AT4: =Q4/P4-1 -> -0.045769981 | AU4: =S4/R4-1 -> -0.29472676 | AV4: =U4/T4-1 -> 0.25123037 | AW4: =W4/V4-1 -> 1.4725838 | AX4: =Y4/X4-1 -> 0.39309235 | AY4: =AA4/Z4-1 -> 0.82597657 | AZ4: =AK4/AJ4-1 -> 0.437111 | BA4: =AC4/AB4-1 -> -0.40253266 | BB4: =AE4/AD4-1 -> #DIV/0! | BC4: =AM4/AL4-1 -> -0.22722396 | BD4: =AG4/AF4-1 -> #DIV/0! | BE4: =AI4/AH4-1 -> #DIV/0!
A5: 45661 | B5: 52763562 | C5: 45280774 | D5: 1311867 | E5: 2619534 | F5: =SUM(N5,P5,R5,T5,V5) -> 915080.97 | G5: =SUM(O5,Q5,S5,U5,W5) -> 1941567 | H5: =SUM(X5,Z5,AB5,AD5,AF5,AH5) -> 396786 | I5: =SUM(Y5,AA5,AC5,AE5,AG5,AI5) -> 677967 | J5: 46025 | K5: 2715709.2 | L5: 1721885 | M5: 993824.24 | N5: 805491 | O5: 1844500 | P5: 33443.966 | Q5: 30385 | R5: -972 | S5: 4998 | T5: 125 | U5: 903 | V5: 76993 | W5: 60781 | X5: 272764 | Y5: 517553 | Z5: 79911 | AA5: 118746 | AB5: 44111 | AC5: 27889 | AD5: 0 | AE5: 13091 | AF5: 0 | AG5: 688 | AH5: 0 | AI5: 0 | AJ5: =X5+Z5 -> 352675 | AK5: =Y5+AA5 -> 636299 | AL5: =AD5+AB5 -> 44111 | AM5: =AE5+AC5 -> 40980 | AN5: 46025 | AO5: =C5/B5-1 -> -0.14181734 | AP5: =E5/D5-1 -> 0.99679851 | AQ5: =G5/F5-1 -> 1.1217434 | AR5: =I5/H5-1 -> 0.70864647 | AS5: =O5/N5-1 -> 1.2899076 | AT5: =Q5/P5-1 -> -0.091465395 | AU5: =S5/R5-1 -> -6.1419753 | AV5: =U5/T5-1 -> 6.224 | AW5: =W5/V5-1 -> -0.2105646 | AX5: =Y5/X5-1 -> 0.89743881 | AY5: =AA5/Z5-1 -> 0.48597815 | AZ5: =AK5/AJ5-1 -> 0.80420784 | BA5: =AC5/AB5-1 -> -0.36775407 | BB5: =AE5/AD5-1 -> #DIV/0! | BC5: =AM5/AL5-1 -> -0.070980028 | BD5: =AG5/AF5-1 -> #DIV/0! | BE5: =AI5/AH5-1 -> #DIV/0!
A6: 45662 | B6: 49768856 | C6: 49319936 | D6: 1824121.7 | E6: 2295830 | F6: =SUM(N6,P6,R6,T6,V6) -> 1383885.7 | G6: =SUM(O6,Q6,S6,U6,W6) -> 1968323 | H6: =SUM(X6,Z6,AB6,AD6,AF6,AH6) -> 440236 | I6: =SUM(Y6,AA6,AC6,AE6,AG6,AI6) -> 327507 | J6: 46026 | K6: 1677704.5 | L6: 1166795.4 | M6: 510909.18 | N6: 1228466 | O6: 1894237 | P6: 26220.69 | Q6: 35794 | R6: 6650 | S6: 2820 | T6: 4220 | U6: 1256 | V6: 118329 | W6: 34216 | X6: 311434 | Y6: 181111 | Z6: 74826 | AA6: 111132 | AB6: 53976 | AC6: 24171 | AD6: 0 | AE6: 11093 | AF6: 0 | AG6: 0 | AH6: 0 | AI6: 0 | AJ6: =X6+Z6 -> 386260 | AK6: =Y6+AA6 -> 292243 | AL6: =AD6+AB6 -> 53976 | AM6: =AE6+AC6 -> 35264 | AN6: 46026 | AO6: =C6/B6-1 -> -0.0090200988 | AP6: =E6/D6-1 -> 0.25859476 | AQ6: =G6/F6-1 -> 0.42231617 | AR6: =I6/H6-1 -> -0.25606493 | AS6: =O6/N6-1 -> 0.54195314 | AT6: =Q6/P6-1 -> 0.36510521 | AU6: =S6/R6-1 -> -0.57593985 | AV6: =U6/T6-1 -> -0.70236967 | AW6: =W6/V6-1 -> -0.71084012 | AX6: =Y6/X6-1 -> -0.41846105 | AY6: =AA6/Z6-1 -> 0.48520568 | AZ6: =AK6/AJ6-1 -> -0.24340341 | BA6: =AC6/AB6-1 -> -0.55218986 | BB6: =AE6/AD6-1 -> #DIV/0! | BC6: =AM6/AL6-1 -> -0.3466726 | BD6: =AG6/AF6-1 -> #DIV/0! | BE6: =AI6/AH6-1 -> #DIV/0!
A7: 45663 | B7: 22835293 | C7: 42820052 | D7: 3136399 | E7: 3582433 | F7: =SUM(N7,P7,R7,T7,V7) -> 2260858 | G7: =SUM(O7,Q7,S7,U7,W7) -> 2378747 | H7: =SUM(X7,Z7,AB7,AD7,AF7,AH7) -> 875541 | I7: =SUM(Y7,AA7,AC7,AE7,AG7,AI7) -> 1203686 | J7: 46027 | K7: 2331412 | L7: 1764555.8 | M7: 566856.23 | N7: 2147376 | O7: 2243868 | P7: 18700 | Q7: 29134 | R7: 36331 | S7: 10063 | T7: -500 | U7: 4612 | V7: 58951 | W7: 91070 | X7: 714238 | Y7: 1061982 | Z7: 83712 | AA7: 81808 | AB7: 77591 | AC7: 39071 | AD7: 0 | AE7: 9717 | AF7: 0 | AG7: 11108 | AH7: 0 | AI7: 0 | AJ7: =X7+Z7 -> 797950 | AK7: =Y7+AA7 -> 1143790 | AL7: =AD7+AB7 -> 77591 | AM7: =AE7+AC7 -> 48788 | AN7: 46027 | AO7: =C7/B7-1 -> 0.87516981 | AP7: =E7/D7-1 -> 0.14221214 | AQ7: =G7/F7-1 -> 0.052143478 | AR7: =I7/H7-1 -> 0.37479113 | AS7: =O7/N7-1 -> 0.044934841 | AT7: =Q7/P7-1 -> 0.55796791 | AU7: =S7/R7-1 -> -0.72301891 | AV7: =U7/T7-1 -> -10.224 | AW7: =W7/V7-1 -> 0.54484233 | AX7: =Y7/X7-1 -> 0.48687412 | AY7: =AA7/Z7-1 -> -0.022744648 | AZ7: =AK7/AJ7-1 -> 0.43341061 | BA7: =AC7/AB7-1 -> -0.49644933 | BB7: =AE7/AD7-1 -> #DIV/0! | BC7: =AM7/AL7-1 -> -0.37121573 | BD7: =AG7/AF7-1 -> #DIV/0! | BE7: =AI7/AH7-1 -> #DIV/0!
A8: 45664 | B8: 23697613 | C8: 22329279 | D8: 2922246.1 | E8: 3328582 | F8: =SUM(N8,P8,R8,T8,V8) -> 2574526.1 | G8: =SUM(O8,Q8,S8,U8,W8) -> 2530631 | H8: =SUM(X8,Z8,AB8,AD8,AF8,AH8) -> 347720 | I8: =SUM(Y8,AA8,AC8,AE8,AG8,AI8) -> 797951 | J8: 46028 | K8: 4010123 | L8: 2882759.8 | M8: 1127363.2 | N8: 2444768 | O8: 2374462 | P8: 20049.138 | Q8: 21733 | R8: 54064 | S8: 67853 | T8: -344 | U8: -114 | V8: 55989 | W8: 66697 | X8: 209116 | Y8: 650825 | Z8: 80417 | AA8: 87785 | AB8: 58187 | AC8: 32894 | AD8: 0 | AE8: 14047 | AF8: 0 | AG8: 11280 | AH8: 0 | AI8: 1120 | AJ8: =X8+Z8 -> 289533 | AK8: =Y8+AA8 -> 738610 | AL8: =AD8+AB8 -> 58187 | AM8: =AE8+AC8 -> 46941 | AN8: 46028 | AO8: =C8/B8-1 -> -0.057741427 | AP8: =E8/D8-1 -> 0.13904916 | AQ8: =G8/F8-1 -> -0.017049793 | AR8: =I8/H8-1 -> 1.294809 | AS8: =O8/N8-1 -> -0.028757739 | AT8: =Q8/P8-1 -> 0.083986757 | AU8: =S8/R8-1 -> 0.25504957 | AV8: =U8/T8-1 -> -0.66860465 | AW8: =W8/V8-1 -> 0.19125185 | AX8: =Y8/X8-1 -> 2.1122678 | AY8: =AA8/Z8-1 -> 0.091622418 | AZ8: =AK8/AJ8-1 -> 1.5510391 | BA8: =AC8/AB8-1 -> -0.43468472 | BB8: =AE8/AD8-1 -> #DIV/0! | BC8: =AM8/AL8-1 -> -0.19327341 | BD8: =AG8/AF8-1 -> #DIV/0! | BE8: =AI8/AH8-1 -> #DIV/0!
A9: 45665 | B9: 26871838 | C9: 23046004 | D9: 3244805 | E9: 3134032 | F9: =SUM(N9,P9,R9,T9,V9) -> 2599511 | G9: =SUM(O9,Q9,S9,U9,W9) -> 2550948 | H9: =SUM(X9,Z9,AB9,AD9,AF9,AH9) -> 645294 | I9: =SUM(Y9,AA9,AC9,AE9,AG9,AI9) -> 583084 | J9: 46029 | K9: 3730440.5 | L9: 3282709.7 | M9: 447730.87 | N9: 2443314 | O9: 2461726 | P9: 26275 | Q9: 24949 | R9: 56169 | S9: 16759 | T9: 3661 | U9: 5667 | V9: 70092 | W9: 41847 | X9: 538812 | Y9: 438746 | Z9: 68361 | AA9: 113224 | AB9: 38121 | AC9: 5778 | AD9: 0 | AE9: 10555 | AF9: 0 | AG9: 14781 | AH9: 0 | AI9: 0 | AJ9: =X9+Z9 -> 607173 | AK9: =Y9+AA9 -> 551970 | AL9: =AD9+AB9 -> 38121 | AM9: =AE9+AC9 -> 16333 | AN9: 46029 | AO9: =C9/B9-1 -> -0.14237337 | AP9: =E9/D9-1 -> -0.034138569 | AQ9: =G9/F9-1 -> -0.01868159 | AR9: =I9/H9-1 -> -0.096405669 | AS9: =O9/N9-1 -> 0.0075356667 | AT9: =Q9/P9-1 -> -0.050466223 | AU9: =S9/R9-1 -> -0.70163257 | AV9: =U9/T9-1 -> 0.54793772 | AW9: =W9/V9-1 -> -0.40297038 | AX9: =Y9/X9-1 -> -0.18571598 | AY9: =AA9/Z9-1 -> 0.656266 | AZ9: =AK9/AJ9-1 -> -0.090918074 | BA9: =AC9/AB9-1 -> -0.84843 | BB9: =AE9/AD9-1 -> #DIV/0! | BC9: =AM9/AL9-1 -> -0.57154849 | BD9: =AG9/AF9-1 -> #DIV/0! | BE9: =AI9/AH9-1 -> #DIV/0!
A10: 45666 | B10: 28051817 | C10: 26562197 | D10: 2520450.3 | E10: 3334996 | F10: =SUM(N10,P10,R10,T10,V10) -> 2303447.3 | G10: =SUM(O10,Q10,S10,U10,W10) -> 2731509 | H10: =SUM(X10,Z10,AB10,AD10,AF10,AH10) -> 217003 | I10: =SUM(Y10,AA10,AC10,AE10,AG10,AI10) -> 603487 | J10: 46030 | K10: 4145460 | L10: 3314567.2 | M10: 830892.8 | N10: 2184366 | O10: 2651325 | P10: 24654.31 | Q10: 23867 | R10: 59780 | S10: 32696 | T10: 2734 | U10: 1757 | V10: 31913 | W10: 21864 | X10: 73729 | Y10: 443664 | Z10: 68117 | AA10: 108455 | AB10: 75157 | AC10: 25645 | AD10: 0 | AE10: 3530 | AF10: 0 | AG10: 21246 | AH10: 0 | AI10: 947 | AJ10: =X10+Z10 -> 141846 | AK10: =Y10+AA10 -> 552119 | AL10: =AD10+AB10 -> 75157 | AM10: =AE10+AC10 -> 29175 | AN10: 46030 | AO10: =C10/B10-1 -> -0.053102443 | AP10: =E10/D10-1 -> 0.32317467 | AQ10: =G10/F10-1 -> 0.18583524 | AR10: =I10/H10-1 -> 1.7810076 | AS10: =O10/N10-1 -> 0.21377324 | AT10: =Q10/P10-1 -> -0.031933984 | AU10: =S10/R10-1 -> -0.45306122 | AV10: =U10/T10-1 -> -0.35735187 | AW10: =W10/V10-1 -> -0.31488735 | AX10: =Y10/X10-1 -> 5.0174965 | AY10: =AA10/Z10-1 -> 0.59218697 | AZ10: =AK10/AJ10-1 -> 2.8923833 | BA10: =AC10/AB10-1 -> -0.65878095 | BB10: =AE10/AD10-1 -> #DIV/0! | BC10: =AM10/AL10-1 -> -0.61181261 | BD10: =AG10/AF10-1 -> #DIV/0! | BE10: =AI10/AH10-1 -> #DIV/0!
A11: 45667 | B11: 28699623 | C11: 26952477 | D11: 2278857.6 | E11: 2577374 | F11: =SUM(N11,P11,R11,T11,V11) -> 2150898.6 | G11: =SUM(O11,Q11,S11,U11,W11) -> 2081802 | H11: =SUM(X11,Z11,AB11,AD11,AF11,AH11) -> 127959 | I11: =SUM(Y11,AA11,AC11,AE11,AG11,AI11) -> 495572 | J11: 46031 | K11: 3216481.5 | L11: 2937064.3 | M11: 279417.18 | N11: 2007643 | O11: 1967914 | P11: 26027.586 | Q11: 27977 | R11: 69118 | S11: 732 | T11: 2178 | U11: 3382 | V11: 45932 | W11: 81797 | X11: 27229 | Y11: 357183 | Z11: 63746 | AA11: 88348 | AB11: 36984 | AC11: 22372 | AD11: 0 | AE11: 11805 | AF11: 0 | AG11: 15175 | AH11: 0 | AI11: 689 | AJ11: =X11+Z11 -> 90975 | AK11: =Y11+AA11 -> 445531 | AL11: =AD11+AB11 -> 36984 | AM11: =AE11+AC11 -> 34177 | AN11: 46031 | AO11: =C11/B11-1 -> -0.060876967 | AP11: =E11/D11-1 -> 0.13099389 | AQ11: =G11/F11-1 -> -0.032124521 | AR11: =I11/H11-1 -> 2.8728968 | AS11: =O11/N11-1 -> -0.019788877 | AT11: =Q11/P11-1 -> 0.074897986 | AU11: =S11/R11-1 -> -0.98940942 | AV11: =U11/T11-1 -> 0.55280073 | AW11: =W11/V11-1 -> 0.78082818 | AX11: =Y11/X11-1 -> 12.117742 | AY11: =AA11/Z11-1 -> 0.38593794 | AZ11: =AK11/AJ11-1 -> 3.8972905 | BA11: =AC11/AB11-1 -> -0.39508977 | BB11: =AE11/AD11-1 -> #DIV/0! | BC11: =AM11/AL11-1 -> -0.075897685 | BD11: =AG11/AF11-1 -> #DIV/0! | BE11: =AI11/AH11-1 -> #DIV/0!
A12: 45668 | B12: 40105570 | C12: 35436338 | D12: 2287848.8 | E12: 2342887 | F12: =SUM(N12,P12,R12,T12,V12) -> 1735933.8 | G12: =SUM(O12,Q12,S12,U12,W12) -> 1705005 | H12: =SUM(X12,Z12,AB12,AD12,AF12,AH12) -> 551915 | I12: =SUM(Y12,AA12,AC12,AE12,AG12,AI12) -> 637882 | J12: 46032 | K12: 2907315.9 | L12: 2742553.5 | M12: 164762.44 | N12: 1623013 | O12: 1571666 | P12: 27638.793 | Q12: 27994 | R12: 37575 | S12: 71315 | T12: 943 | U12: -96 | V12: 46764 | W12: 34126 | X12: 466722 | Y12: 488987 | Z12: 44669 | AA12: 120073 | AB12: 40524 | AC12: 23228 | AD12: 0 | AE12: 6392 | AF12: 0 | AG12: -1487 | AH12: 0 | AI12: 689 | AJ12: =X12+Z12 -> 511391 | AK12: =Y12+AA12 -> 609060 | AL12: =AD12+AB12 -> 40524 | AM12: =AE12+AC12 -> 29620 | AN12: 46032 | AO12: =C12/B12-1 -> -0.11642353 | AP12: =E12/D12-1 -> 0.02405675 | AQ12: =G12/F12-1 -> -0.017816805 | AR12: =I12/H12-1 -> 0.1557613 | AS12: =O12/N12-1 -> -0.031636838 | AT12: =Q12/P12-1 -> 0.012851751 | AU12: =S12/R12-1 -> 0.89793746 | AV12: =U12/T12-1 -> -1.1018028 | AW12: =W12/V12-1 -> -0.27025062 | AX12: =Y12/X12-1 -> 0.047705058 | AY12: =AA12/Z12-1 -> 1.6880611 | AZ12: =AK12/AJ12-1 -> 0.19098694 | BA12: =AC12/AB12-1 -> -0.4268088 | BB12: =AE12/AD12-1 -> #DIV/0! | BC12: =AM12/AL12-1 -> -0.26907512 | BD12: =AG12/AF12-1 -> #DIV/0! | BE12: =AI12/AH12-1 -> #DIV/0!
A13: 45669 | B13: 41530429 | C13: 37766104 | D13: 2885246.1 | E13: 2278577 | F13: =SUM(N13,P13,R13,T13,V13) -> 2172982.1 | G13: =SUM(O13,Q13,S13,U13,W13) -> 1942100 | H13: =SUM(X13,Z13,AB13,AD13,AF13,AH13) -> 712264 | I13: =SUM(Y13,AA13,AC13,AE13,AG13,AI13) -> 336477 | J13: 46033 | K13: 2924099.1 | L13: 2213442.9 | M13: 710656.22 | N13: 2046304 | O13: 1877762 | P13: 27737.069 | Q13: 29948 | R13: 14675 | S13: -1145 | T13: -1465 | U13: 2935 | V13: 85731 | W13: 32600 | X13: 581035 | Y13: 182133 | Z13: 51721 | AA13: 111049 | AB13: 79508 | AC13: 31695 | AD13: 0 | AE13: 9041 | AF13: 0 | AG13: 1612 | AH13: 0 | AI13: 947 | AJ13: =X13+Z13 -> 632756 | AK13: =Y13+AA13 -> 293182 | AL13: =AD13+AB13 -> 79508 | AM13: =AE13+AC13 -> 40736 | AN13: 46033 | AO13: =C13/B13-1 -> -0.090640167 | AP13: =E13/D13-1 -> -0.21026597 | AQ13: =G13/F13-1 -> -0.10625125 | AR13: =I13/H13-1 -> -0.52759511 | AS13: =O13/N13-1 -> -0.082364106 | AT13: =Q13/P13-1 -> 0.079710334 | AU13: =S13/R13-1 -> -1.0780239 | AV13: =U13/T13-1 -> -3.003413 | AW13: =W13/V13-1 -> -0.61974082 | AX13: =Y13/X13-1 -> -0.68653696 | AY13: =AA13/Z13-1 -> 1.1470776 | AZ13: =AK13/AJ13-1 -> -0.53665868 | BA13: =AC13/AB13-1 -> -0.60136087 | BB13: =AE13/AD13-1 -> #DIV/0! | BC13: =AM13/AL13-1 -> -0.48764904 | BD13: =AG13/AF13-1 -> #DIV/0! | BE13: =AI13/AH13-1 -> #DIV/0!
A14: 45670 | B14: 25137619 | C14: 22002628 | D14: 4228309.2 | E14: 4170572 | F14: =SUM(N14,P14,R14,T14,V14) -> 2947735.2 | G14: =SUM(O14,Q14,S14,U14,W14) -> 2948303 | H14: =SUM(X14,Z14,AB14,AD14,AF14,AH14) -> 1280574 | I14: =SUM(Y14,AA14,AC14,AE14,AG14,AI14) -> 1222269 | J14: 46034 | K14: 3687836.2 | L14: 2770711.5 | M14: 917124.64 | N14: 2797894 | O14: 2815225 | P14: 21892.241 | Q14: 28391 | R14: 62339 | S14: 25098 | T14: 7660 | U14: 689 | V14: 57950 | W14: 78900 | X14: 1124689 | Y14: 1028542 | Z14: 34111 | AA14: 130772 | AB14: 121774 | AC14: 38266 | AD14: 0 | AE14: 9160 | AF14: 0 | AG14: 15529 | AH14: 0 | AI14: 0 | AJ14: =X14+Z14 -> 1158800 | AK14: =Y14+AA14 -> 1159314 | AL14: =AD14+AB14 -> 121774 | AM14: =AE14+AC14 -> 47426 | AN14: 46034 | AO14: =C14/B14-1 -> -0.12471312 | AP14: =E14/D14-1 -> -0.013654924 | AQ14: =G14/F14-1 -> 0.00019260842 | AR14: =I14/H14-1 -> -0.045530364 | AS14: =O14/N14-1 -> 0.0061943019 | AT14: =Q14/P14-1 -> 0.29685214 | AU14: =S14/R14-1 -> -0.59739489 | AV14: =U14/T14-1 -> -0.91005222 | AW14: =W14/V14-1 -> 0.36151855 | AX14: =Y14/X14-1 -> -0.085487633 | AY14: =AA14/Z14-1 -> 2.8337193 | AZ14: =AK14/AJ14-1 -> 0.00044356231 | BA14: =AC14/AB14-1 -> -0.68576215 | BB14: =AE14/AD14-1 -> #DIV/0! | BC14: =AM14/AL14-1 -> -0.61054084 | BD14: =AG14/AF14-1 -> #DIV/0! | BE14: =AI14/AH14-1 -> #DIV/0!
... A153: 45809 | B153: 54033676 | C153: 51664485 | D153: 4327176.6 | E153: 4126779 | F153: =SUM(N153,P153,R153,T153,V153) -> 2869134.6 | G153: =SUM(O153,Q153,S153,U153,W153) -> 2867997 | H153: =SUM(X153,Z153,AB153,AD153,AF153,AH153) -> 1458042 | I153: =SUM(Y153,AA153,AC153,AE153,AG153,AI153) -> 1258782 | J153: 46173 | K153: 5635126.4 | L153: 3688020.2 | M153: 1947106.3 | N153: 2641485 | O153: 2739282 | P153: 39671.552 | Q153: 36548 | R153: -228 | S153: 7405 | T153: 1403 | U153: 4382 | V153: 186803 | W153: 80380 | X153: 1125600 | Y153: 1043225 | Z153: 278166 | AA153: 173161 | AB153: 40863 | AC153: 23659 | AD153: 13413 | AE153: 10923 | AF153: 0 | AG153: 2086 | AH153: 0 | AI153: 5728 | AJ153: =X153+Z153 -> 1403766 | AK153: =Y153+AA153 -> 1216386 | AL153: =AD153+AB153 -> 54276 | AM153: =AE153+AC153 -> 34582 | AN153: 46173 | AO153: =C153/B153-1 -> -0.043846563 | AP153: =E153/D153-1 -> -0.046311388 | AQ153: =G153/F153-1 -> -0.00039647904 | AR153: =I153/H153-1 -> -0.13666273 | AS153: =O153/N153-1 -> 0.037023492 | AT153: =Q153/P153-1 -> -0.078735305 | AU153: =S153/R153-1 -> -33.47807 | AV153: =U153/T153-1 -> 2.1233072 | AW153: =W153/V153-1 -> -0.56970712 | AX153: =Y153/X153-1 -> -0.073183191 | AY153: =AA153/Z153-1 -> -0.37749042 | AZ153: =AK153/AJ153-1 -> -0.13348379 | BA153: =AC153/AB153-1 -> -0.42101657 | BB153: =AE153/AD153-1 -> -0.1856408 | BC153: =AM153/AL153-1 -> -0.36284914 | BD153: =AG153/AF153-1 -> #DIV/0! | BE153: =AI153/AH153-1 -> #DIV/0!
A154: 45810 | B154: 30821255 | C154: 28438618 | D154: 5295147.3 | E154: 5321760 | F154: =SUM(N154,P154,R154,T154,V154) -> 3812724.3 | G154: =SUM(O154,Q154,S154,U154,W154) -> 4223699 | H154: =SUM(X154,Z154,AB154,AD154,AF154,AH154) -> 1482423 | I154: =SUM(Y154,AA154,AC154,AE154,AG154,AI154) -> 1098061 | J154: 46174 | K154: 5628230.5 | L154: 3718237.2 | M154: 1909993.3 | N154: 3591037 | O154: 4064668 | P154: 32404.31 | Q154: 29432 | R154: 47857 | S154: 26689 | T154: 7967 | U154: 10478 | V154: 133459 | W154: 92432 | X154: 1113451 | Y154: 904974 | Z154: 281772 | AA154: 135586 | AB154: 68092 | AC154: 29579 | AD154: 19108 | AE154: 10801 | AF154: 0 | AG154: 8208 | AH154: 0 | AI154: 8913 | AJ154: =X154+Z154 -> 1395223 | AK154: =Y154+AA154 -> 1040560 | AL154: =AD154+AB154 -> 87200 | AM154: =AE154+AC154 -> 40380 | AN154: 46174 | AO154: =C154/B154-1 -> -0.077304996 | AP154: =E154/D154-1 -> 0.0050258639 | AQ154: =G154/F154-1 -> 0.1077903 | AR154: =I154/H154-1 -> -0.25927957 | AS154: =O154/N154-1 -> 0.13189254 | AT154: =Q154/P154-1 -> -0.091725771 | AU154: =S154/R154-1 -> -0.44231774 | AV154: =U154/T154-1 -> 0.3151751 | AW154: =W154/V154-1 -> -0.30741276 | AX154: =Y154/X154-1 -> -0.187235 | AY154: =AA154/Z154-1 -> -0.51880953 | AZ154: =AK154/AJ154-1 -> -0.25419807 | BA154: =AC154/AB154-1 -> -0.56560242 | BB154: =AE154/AD154-1 -> -0.43473938 | BC154: =AM154/AL154-1 -> -0.53692661 | BD154: =IFERROR(AG154/AF154-1,1) -> 1 | BE154: =IFERROR(AI154/AH154-1,1) -> 1
A155: 45811 | B155: 35443743 | C155: 32512385 | D155: 6788915.7 | E155: 5929940 | F155: =SUM(N155,P155,R155,T155,V155) -> 4893991.7 | G155: =SUM(O155,Q155,S155,U155,W155) -> 4767854 | H155: =SUM(X155,Z155,AB155,AD155,AF155,AH155) -> 1894924 | I155: =SUM(Y155,AA155,AC155,AE155,AG155,AI155) -> 1162086 | J155: 46175 | K155: 6910737.6 | L155: 4968805.9 | M155: 1941931.7 | N155: 4671193 | O155: 4572359 | P155: 32920.69 | Q155: 23766 | R155: 51815 | S155: 47963 | T155: 10260 | U155: 15476 | V155: 127803 | W155: 108290 | X155: 1389018 | Y155: 930339 | Z155: 419059 | AA155: 178091 | AB155: 74233 | AC155: 32506 | AD155: 12614 | AE155: 12255 | AF155: 0 | AG155: 4331 | AH155: 0 | AI155: 4564 | AJ155: =X155+Z155 -> 1808077 | AK155: =Y155+AA155 -> 1108430 | AL155: =AD155+AB155 -> 86847 | AM155: =AE155+AC155 -> 44761 | AN155: 46175 | AO155: =C155/B155-1 -> -0.082704527 | AP155: =E155/D155-1 -> -0.1265262 | AQ155: =G155/F155-1 -> -0.025773989 | AR155: =I155/H155-1 -> -0.38673741 | AS155: =O155/N155-1 -> -0.021158192 | AT155: =Q155/P155-1 -> -0.27808317 | AU155: =S155/R155-1 -> -0.074341407 | AV155: =U155/T155-1 -> 0.50838207 | AW155: =W155/V155-1 -> -0.1526803 | AX155: =Y155/X155-1 -> -0.33021818 | AY155: =AA155/Z155-1 -> -0.57502166 | AZ155: =AK155/AJ155-1 -> -0.38695642 | BA155: =AC155/AB155-1 -> -0.5621085 | BB155: =AE155/AD155-1 -> -0.028460441 | BC155: =AM155/AL155-1 -> -0.48459935 | BD155: =IFERROR(AG155/AF155-1,1) -> 1 | BE155: =IFERROR(AI155/AH155-1,1) -> 1
A156: 45812 | B156: 35210999 | C156: 31971655 | D156: 4673886.3 | E156: 4464670 | F156: =SUM(N156,P156,R156,T156,V156) -> 3528636.3 | G156: =SUM(O156,Q156,S156,U156,W156) -> 3739380 | H156: =SUM(X156,Z156,AB156,AD156,AF156,AH156) -> 1145250 | I156: =SUM(Y156,AA156,AC156,AE156,AG156,AI156) -> 725290 | J156: 46176 | K156: 8873325 | L156: 6391028.8 | M156: 2482296.2 | N156: 3304777 | O156: 3552563 | P156: 29785.345 | Q156: 26173 | R156: 42044 | S156: 32530 | T156: 4685 | U156: 6406 | V156: 147345 | W156: 121708 | X156: 792011 | Y156: 539970 | Z156: 301527 | AA156: 136278 | AB156: 38002 | AC156: 35037 | AD156: 13710 | AE156: 7759 | AF156: 0 | AG156: 4912 | AH156: 0 | AI156: 1334 | AJ156: =X156+Z156 -> 1093538 | AK156: =Y156+AA156 -> 676248 | AL156: =AD156+AB156 -> 51712 | AM156: =AE156+AC156 -> 42796 | AN156: 46176 | AO156: =C156/B156-1 -> -0.091998071 | AP156: =E156/D156-1 -> -0.044762822 | AQ156: =G156/F156-1 -> 0.059723824 | AR156: =I156/H156-1 -> -0.36669723 | AS156: =O156/N156-1 -> 0.07497813 | AT156: =Q156/P156-1 -> -0.12127927 | AU156: =S156/R156-1 -> -0.22628675 | AV156: =U156/T156-1 -> 0.36734258 | AW156: =W156/V156-1 -> -0.17399301 | AX156: =Y156/X156-1 -> -0.31822917 | AY156: =AA156/Z156-1 -> -0.54804047 | AZ156: =AK156/AJ156-1 -> -0.38159625 | BA156: =AC156/AB156-1 -> -0.078022209 | BB156: =AE156/AD156-1 -> -0.43406273 | BC156: =AM156/AL156-1 -> -0.17241646 | BD156: =IFERROR(AG156/AF156-1,1) -> 1 | BE156: =IFERROR(AI156/AH156-1,1) -> 1
A157: 45813 | B157: 38609736 | C157: 34179408 | D157: 3575822.2 | E157: 3527523 | F157: =SUM(N157,P157,R157,T157,V157) -> 2639487.2 | G157: =SUM(O157,Q157,S157,U157,W157) -> 2984995 | H157: =SUM(X157,Z157,AB157,AD157,AF157,AH157) -> 936335 | I157: =SUM(Y157,AA157,AC157,AE157,AG157,AI157) -> 542528 | J157: 46177 | K157: 6101558.8 | L157: 4601314 | M157: 1500244.7 | N157: 2405203 | O157: 2797805 | P157: 24530.172 | Q157: 20815 | R157: 28287 | S157: 73509 | T157: 7601 | U157: 4322 | V157: 173866 | W157: 88544 | X157: 649458 | Y157: 330252 | Z157: 251407 | AA157: 176072 | AB157: 22490 | AC157: 20525 | AD157: 12980 | AE157: 5500 | AF157: 0 | AG157: 5098 | AH157: 0 | AI157: 5081 | AJ157: =X157+Z157 -> 900865 | AK157: =Y157+AA157 -> 506324 | AL157: =AD157+AB157 -> 35470 | AM157: =AE157+AC157 -> 26025 | AN157: 46177 | AO157: =C157/B157-1 -> -0.11474639 | AP157: =E157/D157-1 -> -0.013507152 | AQ157: =G157/F157-1 -> 0.1308996 | AR157: =I157/H157-1 -> -0.42058345 | AS157: =O157/N157-1 -> 0.1632303 | AT157: =Q157/P157-1 -> -0.15145317 | AU157: =S157/R157-1 -> 1.5986849 | AV157: =U157/T157-1 -> -0.43139061 | AW157: =W157/V157-1 -> -0.49073424 | AX157: =Y157/X157-1 -> -0.49149599 | AY157: =AA157/Z157-1 -> -0.29965355 | AZ157: =AK157/AJ157-1 -> -0.43795796 | BA157: =AC157/AB157-1 -> -0.087372165 | BB157: =AE157/AD157-1 -> -0.57627119 | BC157: =AM157/AL157-1 -> -0.26628136 | BD157: =IFERROR(AG157/AF157-1,1) -> 1 | BE157: =IFERROR(AI157/AH157-1,1) -> 1
A158: 45814 | B158: 40369746 | C158: 36164915 | D158: 3043546.5 | E158: 2971920 | F158: =SUM(N158,P158,R158,T158,V158) -> 2233464.5 | G158: =SUM(O158,Q158,S158,U158,W158) -> 2416309 | H158: =SUM(X158,Z158,AB158,AD158,AF158,AH158) -> 810082 | I158: =SUM(Y158,AA158,AC158,AE158,AG158,AI158) -> 555611 | J158: 46178 | K158: 4663412.6 | L158: 3436840.6 | M158: 1226572.1 | N158: 2001508 | O158: 2265727 | P158: 24459.483 | Q158: 32888 | R158: 72867 | S158: 13246 | T158: 5878 | U158: 5193 | V158: 128752 | W158: 99255 | X158: 599700 | Y158: 351624 | Z158: 181701 | AA158: 180239 | AB158: 19333 | AC158: 11727 | AD158: 9348 | AE158: 6281 | AF158: 0 | AG158: 4449 | AH158: 0 | AI158: 1291 | AJ158: =X158+Z158 -> 781401 | AK158: =Y158+AA158 -> 531863 | AL158: =AD158+AB158 -> 28681 | AM158: =AE158+AC158 -> 18008 | AN158: 46178 | AO158: =C158/B158-1 -> -0.10415798 | AP158: =E158/D158-1 -> -0.023533888 | AQ158: =G158/F158-1 -> 0.081865872 | AR158: =I158/H158-1 -> -0.31412993 | AS158: =O158/N158-1 -> 0.13200996 | AT158: =Q158/P158-1 -> 0.34459098 | AU158: =S158/R158-1 -> -0.81821675 | AV158: =U158/T158-1 -> -0.11653624 | AW158: =W158/V158-1 -> -0.22909935 | AX158: =Y158/X158-1 -> -0.41366683 | AY158: =AA158/Z158-1 -> -0.0080461858 | AZ158: =AK158/AJ158-1 -> -0.31934692 | BA158: =AC158/AB158-1 -> -0.39342058 | BB158: =AE158/AD158-1 -> -0.32809157 | BC158: =AM158/AL158-1 -> -0.37212789 | BD158: =IFERROR(AG158/AF158-1,1) -> 1 | BE158: =IFERROR(AI158/AH158-1,1) -> 1
A159: 45815 | B159: 50222961 | C159: 47697211 | D159: 2666977.9 | E159: 2870666 | F159: =SUM(N159,P159,R159,T159,V159) -> 2030111.9 | G159: =SUM(O159,Q159,S159,U159,W159) -> 2315852 | H159: =SUM(X159,Z159,AB159,AD159,AF159,AH159) -> 636866 | I159: =SUM(Y159,AA159,AC159,AE159,AG159,AI159) -> 554814 | J159: 46179 | K159: 3963610.1 | L159: 2902425.8 | M159: 1061184.3 | N159: 1812078 | O159: 2159116 | P159: 25031.897 | Q159: 34578 | R159: 25976 | S159: 22387 | T159: 10248 | U159: 1996 | V159: 156778 | W159: 97775 | X159: 495806 | Y159: 344708 | Z159: 116017 | AA159: 188671 | AB159: 17934 | AC159: 9093 | AD159: 7109 | AE159: 3824 | AF159: 0 | AG159: 5418 | AH159: 0 | AI159: 3100 | AJ159: =X159+Z159 -> 611823 | AK159: =Y159+AA159 -> 533379 | AL159: =AD159+AB159 -> 25043 | AM159: =AE159+AC159 -> 12917 | AN159: 46179 | AO159: =C159/B159-1 -> -0.050290743 | AP159: =E159/D159-1 -> 0.076374125 | AQ159: =G159/F159-1 -> 0.14075091 | AR159: =I159/H159-1 -> -0.12883715 | AS159: =O159/N159-1 -> 0.19151383 | AT159: =Q159/P159-1 -> 0.38135758 | AU159: =S159/R159-1 -> -0.138166 | AV159: =U159/T159-1 -> -0.80523029 | AW159: =W159/V159-1 -> -0.37634745 | AX159: =Y159/X159-1 -> -0.30475226 | AY159: =AA159/Z159-1 -> 0.62623581 | AZ159: =AK159/AJ159-1 -> -0.12821355 | BA159: =AC159/AB159-1 -> -0.49297424 | BB159: =AE159/AD159-1 -> -0.46209031 | BC159: =AM159/AL159-1 -> -0.48420716 | BD159: =IFERROR(AG159/AF159-1,1) -> 1 | BE159: =IFERROR(AI159/AH159-1,1) -> 1
A160: 45816 | B160: 49920221 | C160: 50902735 | D160: 3220669.8 | E160: 3708782 | F160: =SUM(N160,P160,R160,T160,V160) -> 2412328.8 | G160: =SUM(O160,Q160,S160,U160,W160) -> 2956420 | H160: =SUM(X160,Z160,AB160,AD160,AF160,AH160) -> 808341 | I160: =SUM(Y160,AA160,AC160,AE160,AG160,AI160) -> 752362 | J160: 46180 | K160: 3472422.4 | L160: 2638146.2 | M160: 834276.25 | N160: 2272542 | O160: 2835754 | P160: 25757.759 | Q160: 33462 | R160: 21715 | S160: 1717 | T160: 6780 | U160: 3121 | V160: 85534 | W160: 82366 | X160: 642846 | Y160: 526670 | Z160: 139716 | AA160: 201401 | AB160: 16575 | AC160: 12585 | AD160: 9204 | AE160: 6574 | AF160: 0 | AG160: 2075 | AH160: 0 | AI160: 3057 | AJ160: =X160+Z160 -> 782562 | AK160: =Y160+AA160 -> 728071 | AL160: =AD160+AB160 -> 25779 | AM160: =AE160+AC160 -> 19159 | AN160: 46180 | AO160: =C160/B160-1 -> 0.019681684 | AP160: =E160/D160-1 -> 0.15155613 | AQ160: =G160/F160-1 -> 0.22554606 | AR160: =I160/H160-1 -> -0.069251714 | AS160: =O160/N160-1 -> 0.24783348 | AT160: =Q160/P160-1 -> 0.29910372 | AU160: =S160/R160-1 -> -0.92093023 | AV160: =U160/T160-1 -> -0.53967552 | AW160: =W160/V160-1 -> -0.037037903 | AX160: =Y160/X160-1 -> -0.18072135 | AY160: =AA160/Z160-1 -> 0.44150276 | AZ160: =AK160/AJ160-1 -> -0.069631544 | BA160: =AC160/AB160-1 -> -0.24072398 | BB160: =AE160/AD160-1 -> -0.28574533 | BC160: =AM160/AL160-1 -> -0.25679817 | BD160: =IFERROR(AG160/AF160-1,1) -> 1 | BE160: =IFERROR(AI160/AH160-1,1) -> 1
A161: 45817 | B161: 28800528 | C161: 28697109 | D161: 4519881.8 | E161: 5173290 | F161: =SUM(N161,P161,R161,T161,V161) -> 3580144.8 | G161: =SUM(O161,Q161,S161,U161,W161) -> 4242387 | H161: =SUM(X161,Z161,AB161,AD161,AF161,AH161) -> 939737 | I161: =SUM(Y161,AA161,AC161,AE161,AG161,AI161) -> 930903 | J161: 46181 | K161: 4193019.5 | L161: 3134115.9 | M161: 1058903.6 | N161: 3416740 | O161: 4038776 | P161: 24238.793 | Q161: 28413 | R161: 51991 | S161: 38880 | T161: 11309 | U161: 7184 | V161: 75866 | W161: 129134 | X161: 757315 | Y161: 693965 | Z161: 142907 | AA161: 192882 | AB161: 32343 | AC161: 27190 | AD161: 7172 | AE161: 4960 | AF161: 0 | AG161: 8849 | AH161: 0 | AI161: 3057 | AJ161: =X161+Z161 -> 900222 | AK161: =Y161+AA161 -> 886847 | AL161: =AD161+AB161 -> 39515 | AM161: =AE161+AC161 -> 32150 | AN161: 46181 | AO161: =C161/B161-1 -> -0.0035908717 | AP161: =E161/D161-1 -> 0.14456312 | AQ161: =G161/F161-1 -> 0.18497638 | AR161: =I161/H161-1 -> -0.0094005025 | AS161: =O161/N161-1 -> 0.18205541 | AT161: =Q161/P161-1 -> 0.17221183 | AU161: =S161/R161-1 -> -0.25217826 | AV161: =U161/T161-1 -> -0.36475374 | AW161: =W161/V161-1 -> 0.70213271 | AX161: =Y161/X161-1 -> -0.083650793 | AY161: =AA161/Z161-1 -> 0.34970295 | AZ161: =AK161/AJ161-1 -> -0.014857446 | BA161: =AC161/AB161-1 -> -0.1593235 | BB161: =AE161/AD161-1 -> -0.30842164 | BC161: =AM161/AL161-1 -> -0.18638492 | BD161: =IFERROR(AG161/AF161-1,1) -> 1 | BE161: =IFERROR(AI161/AH161-1,1) -> 1
A162: 45818 | B162: 33842549 | C162: 32882240 | D162: 4898086.7 | E162: 5209165 | F162: =SUM(N162,P162,R162,T162,V162) -> 3872939.7 | G162: =SUM(O162,Q162,S162,U162,W162) -> 4519578 | H162: =SUM(X162,Z162,AB162,AD162,AF162,AH162) -> 1025147 | I162: =SUM(Y162,AA162,AC162,AE162,AG162,AI162) -> 689587 | J162: 46182 | K162: 5905700.6 | L162: 4674672 | M162: 1231028.6 | N162: 3683319 | O162: 4305103 | P162: 22251.724 | Q162: 32400 | R162: 65685 | S162: 65678 | T162: 13660 | U162: 1844 | V162: 88024 | W162: 114553 | X162: 829750 | Y162: 480602 | Z162: 153054 | AA162: 174897 | AB162: 32493 | AC162: 13800 | AD162: 9850 | AE162: 7381 | AF162: 0 | AG162: 11271 | AH162: 0 | AI162: 1636 | AJ162: =X162+Z162 -> 982804 | AK162: =Y162+AA162 -> 655499 | AL162: =AD162+AB162 -> 42343 | AM162: =AE162+AC162 -> 21181 | AN162: 46182 | AO162: =C162/B162-1 -> -0.028375788 | AP162: =E162/D162-1 -> 0.063510161 | AQ162: =G162/F162-1 -> 0.16696317 | AR162: =I162/H162-1 -> -0.32732867 | AS162: =O162/N162-1 -> 0.16881079 | AT162: =Q162/P162-1 -> 0.45606695 | AU162: =S162/R162-1 -> -0.00010656923 | AV162: =U162/T162-1 -> -0.86500732 | AW162: =W162/V162-1 -> 0.30138371 | AX162: =Y162/X162-1 -> -0.42078698 | AY162: =AA162/Z162-1 -> 0.14271434 | AZ162: =AK162/AJ162-1 -> -0.33303182 | BA162: =AC162/AB162-1 -> -0.57529314 | BB162: =AE162/AD162-1 -> -0.2506599 | BC162: =AM162/AL162-1 -> -0.49977564 | BD162: =IFERROR(AG162/AF162-1,1) -> 1 | BE162: =IFERROR(AI162/AH162-1,1) -> 1
A163: 45819 | B163: 38225481 | C163: 37140797 | D163: 4461529 | E163: 4905225 | F163: =SUM(N163,P163,R163,T163,V163) -> 3335643 | G163: =SUM(O163,Q163,S163,U163,W163) -> 4319205 | H163: =SUM(X163,Z163,AB163,AD163,AF163,AH163) -> 1125886 | I163: =SUM(Y163,AA163,AC163,AE163,AG163,AI163) -> 586020 | J163: 46183 | K163: 6407621.7 | L163: 5064708.5 | M163: 1342913.3 | N163: 3146636 | O163: 4123039 | P163: 19800 | Q163: 28567 | R163: 47481 | S163: 28987 | T163: 1700 | U163: 6055 | V163: 120026 | W163: 132557 | X163: 948224 | Y163: 415988 | Z163: 139153 | AA163: 141262 | AB163: 23874 | AC163: 21700 | AD163: 14635 | AE163: 2811 | AF163: 0 | AG163: 4259 | AH163: 0 | AI163: 0 | AJ163: =X163+Z163 -> 1087377 | AK163: =Y163+AA163 -> 557250 | AL163: =AD163+AB163 -> 38509 | AM163: =AE163+AC163 -> 24511 | AN163: 46183 | AO163: =C163/B163-1 -> -0.028375941 | AP163: =E163/D163-1 -> 0.099449314 | AQ163: =G163/F163-1 -> 0.29486429 | AR163: =I163/H163-1 -> -0.47950325 | AS163: =O163/N163-1 -> 0.31030059 | AT163: =Q163/P163-1 -> 0.44277778 | AU163: =S163/R163-1 -> -0.38950317 | AV163: =U163/T163-1 -> 2.5617647 | AW163: =W163/V163-1 -> 0.10440238 | AX163: =Y163/X163-1 -> -0.56129775 | AY163: =AA163/Z163-1 -> 0.015155979 | AZ163: =AK163/AJ163-1 -> -0.48752824 | BA163: =AC163/AB163-1 -> -0.091061406 | BB163: =AE163/AD163-1 -> -0.8079262 | BC163: =AM163/AL163-1 -> -0.36349944 | BD163: =IFERROR(AG163/AF163-1,1) -> 1 | BE163: =IFERROR(AI163/AH163-1,1) -> 1
A164: 45820 | B164: 44572329 | C164: 35683971 | D164: 3866377.4 | E164: 3824147 | F164: =SUM(N164,P164,R164,T164,V164) -> 2753484.4 | G164: =SUM(O164,Q164,S164,U164,W164) -> 3178208 | H164: =SUM(X164,Z164,AB164,AD164,AF164,AH164) -> 1112893 | I164: =SUM(Y164,AA164,AC164,AE164,AG164,AI164) -> 645939 | J164: 46184 | K164: 5835819.3 | L164: 4360940.9 | M164: 1474878.5 | N164: 2555955 | O164: 2993082 | P164: 25116.379 | Q164: 24347 | R164: 47507 | S164: 18478 | T164: 12578 | U164: 2267 | V164: 112328 | W164: 140034 | X164: 947866 | Y164: 412479 | Z164: 131048 | AA164: 215146 | AB164: 20426 | AC164: 12955 | AD164: 13553 | AE164: 214 | AF164: 0 | AG164: 4069 | AH164: 0 | AI164: 1076 | AJ164: =X164+Z164 -> 1078914 | AK164: =Y164+AA164 -> 627625 | AL164: =AD164+AB164 -> 33979 | AM164: =AE164+AC164 -> 13169 | AN164: 46184 | AO164: =C164/B164-1 -> -0.19941426 | AP164: =E164/D164-1 -> -0.010922467 | AQ164: =G164/F164-1 -> 0.15424951 | AR164: =I164/H164-1 -> -0.41958571 | AS164: =O164/N164-1 -> 0.17102296 | AT164: =Q164/P164-1 -> -0.030632573 | AU164: =S164/R164-1 -> -0.61104679 | AV164: =U164/T164-1 -> -0.81976467 | AW164: =W164/V164-1 -> 0.24665266 | AX164: =Y164/X164-1 -> -0.56483406 | AY164: =AA164/Z164-1 -> 0.64173433 | AZ164: =AK164/AJ164-1 -> -0.41828079 | BA164: =AC164/AB164-1 -> -0.36575933 | BB164: =AE164/AD164-1 -> -0.98421014 | BC164: =AM164/AL164-1 -> -0.61243709 | BD164: =IFERROR(AG164/AF164-1,1) -> 1 | BE164: =IFERROR(AI164/AH164-1,1) -> 1
A165: 45821 | B165: 48087656 | C165: 38806927 | D165: 2794859.4 | E165: 3614931 | F165: =SUM(N165,P165,R165,T165,V165) -> 1862655.4 | G165: =SUM(O165,Q165,S165,U165,W165) -> 2794758 | H165: =SUM(X165,Z165,AB165,AD165,AF165,AH165) -> 932204 | I165: =SUM(Y165,AA165,AC165,AE165,AG165,AI165) -> 820173 | J165: 46185 | K165: 5045229.5 | L165: 3587371.5 | M165: 1457858 | N165: 1667347 | O165: 2651227 | P165: 28341.379 | Q165: 30709 | R165: 42888 | S165: 11629 | T165: 9320 | U165: 3889 | V165: 114759 | W165: 97304 | X165: 766146 | Y165: 566709 | Z165: 144596 | AA165: 221811 | AB165: 10631 | AC165: 20101 | AD165: 10831 | AE165: 2802 | AF165: 0 | AG165: 6123 | AH165: 0 | AI165: 2627 | AJ165: =X165+Z165 -> 910742 | AK165: =Y165+AA165 -> 788520 | AL165: =AD165+AB165 -> 21462 | AM165: =AE165+AC165 -> 22903 | AN165: 46185 | AO165: =C165/B165-1 -> -0.19299608 | AP165: =E165/D165-1 -> 0.29342142 | AQ165: =G165/F165-1 -> 0.50041604 | AR165: =I165/H165-1 -> -0.12017863 | AS165: =O165/N165-1 -> 0.59008713 | AT165: =Q165/P165-1 -> 0.08353936 | AU165: =S165/R165-1 -> -0.72885189 | AV165: =U165/T165-1 -> -0.58272532 | AW165: =W165/V165-1 -> -0.15210136 | AX165: =Y165/X165-1 -> -0.260312 | AY165: =AA165/Z165-1 -> 0.53400509 | AZ165: =AK165/AJ165-1 -> -0.13420047 | BA165: =AC165/AB165-1 -> 0.89079108 | BB165: =AE165/AD165-1 -> -0.74129813 | BC165: =AM165/AL165-1 -> 0.067141925 | BD165: =IFERROR(AG165/AF165-1,1) -> 1 | BE165: =IFERROR(AI165/AH165-1,1) -> 1
... A245: 45901 | B245: 31649055 | C245: 0 | D245: 4990529.1 | E245: 0 | F245: =SUM(N245,P245,R245,T245,V245) -> 4080895.9 | G245: =SUM(O245,Q245,S245,U245,W245) -> 0 | H245: =SUM(X245,Z245,AB245,AD245,AF245,AH245) -> 909633.16 | I245: =SUM(Y245,AA245,AC245,AE245,AG245,AI245) -> 0 | J245: 46265 | K245: 5496657.2 | L245: 3961469.1 | M245: 1535188.1 | N245: 3909270 | O245: 0 | P245: 26356.897 | Q245: 0 | R245: 17828 | S245: 0 | T245: 10082 | U245: 0 | V245: 117359 | W245: 0 | X245: 480576 | Y245: 0 | Z245: 371920 | AA245: 0 | AB245: 38723 | AC245: 0 | AD245: 18027 | AE245: 0 | AF245: 387.15517 | AG245: 0 | AH245: 0 | AI245: 0 | AJ245: =X245+Z245 -> 852496 | AK245: =Y245+AA245 -> 0 | AL245: =AD245+AB245 -> 56750 | AM245: =AE245+AC245 -> 0 | AN245: 46265 | AO245: =C245/B245-1 -> -1 | AP245: =E245/D245-1 -> -1 | AQ245: =G245/F245-1 -> -1 | AR245: =I245/H245-1 -> -1 | AS245: =O245/N245-1 -> -1 | AT245: =Q245/P245-1 -> -1 | AU245: =S245/R245-1 -> -1 | AV245: =U245/T245-1 -> -1 | AW245: =W245/V245-1 -> -1 | AX245: =Y245/X245-1 -> -1 | AY245: =AA245/Z245-1 -> -1 | AZ245: =AK245/AJ245-1 -> -1 | BA245: =AC245/AB245-1 -> -1 | BB245: =AE245/AD245-1 -> -1 | BC245: =AM245/AL245-1 -> -1 | BD245: =IFERROR(AG245/AF245-1,1) -> -1 | BE245: =IFERROR(AI245/AH245-1,1) -> 1

Sheet afil
A3: Etiquetas de fila | B3: Suma de Afiliados 2025 | E3: Etiquetas de columna
A4: ene | B4: 735903.45 | E4: ene | F4: feb | G4: mar | H4: abr | I4: may | J4: jun | K4: jul | L4: ago | M4: sep | N4: Total general
A5: feb | B5: 577281.03 | D5: Suma de Afiliados 2026 | E5: 828398 | F5: 690246 | G5: 781473 | H5: 655793 | I5: 733475 | J5: 933595 | K5: 1134357 | L5: 1006487 | M5: 0 | N5: 6763824
A6: mar | B6: 628597.41
A7: abr | B7: 537415.52
A8: may | B8: 690044.83
A9: jun | B9: 1043100.9
A10: jul | B10: 1288231.9
A11: ago | B11: 1233300
A12: sep | B12: 26356.897
A13: Total general | B13: 6760231.9

Sheet 2025
A3: Etiquetas de fila | B3: Suma de Web + APP 2025 | C3: Suma de TMK 2025 | D3: Suma de WA 2025 | E3: Suma de Ent. en Tienda 2025 | F3: Suma de Meli Drop 2025 | G3: Suma de Meli Full 2025 | H3: Suma de Amazon Drop 2025 | I3: Suma de Amazon Full 2025 | J3: Suma de TikTok 2025 | K3: Suma de Shein 2025 | L3: Suma de Global 2025
A4: ene | B4: 64774122 | C4: 1448010 | D4: 110309 | E4: 1740843 | F4: 12634416 | G4: 2796767 | H4: 1549978 | I4: 337627 | J4: 0 | K4: 0 | L4: 988946355
A5: feb | B5: 62779662 | C5: 1441236 | D5: 110248 | E5: 1727351 | F5: 8028750 | G5: 1592434 | H5: 784689 | I5: 145354 | J5: 0 | K5: 0 | L5: 962218940
A6: mar | B6: 70846957 | C6: 1430022 | D6: 105504 | E6: 1895057 | F6: 12534250 | G6: 3477562 | H6: 516151 | I6: 262286 | J6: 0 | K6: 0 | L6: 1186617098
A7: abr | B7: 64872371 | C7: 1319157 | D7: 228719 | E7: 1991672 | F7: 10402707 | G7: 2880496 | H7: 565896 | I7: 256773 | J7: 0 | K7: 0 | L7: 1035672463
A8: may | B8: 77993633 | C8: 1186894 | D8: 193949 | E8: 2807631 | F8: 17783854 | G8: 4277531 | H8: 740101 | I8: 340898 | J8: 0 | K8: 0 | L8: 1152795410
A9: jun | B9: 81146441 | C9: 1075608 | D9: 224382 | E9: 3214064 | F9: 21666219 | G9: 4885568 | H9: 1068283 | I9: 357640 | J9: 0 | K9: 0 | L9: 1224352130
A10: jul | B10: 85926647 | C10: 993236 | D10: 183021 | E10: 3267791 | F10: 18674810 | G10: 3524088 | H10: 1034594 | I10: 335023 | J10: 0 | K10: 0 | L10: 1257444654
A11: ago | B11: 108478992 | C11: 1181596 | D11: 171602 | E11: 4704001 | F11: 21315555 | G11: 6687463 | H11: 1121624 | I11: 277354 | J11: 14518.138 | K11: 1292.2414 | L11: 1609737016
A12: sep | B12: 87878561 | C12: 968361 | D12: 119486 | E12: 2988851 | F12: 15767135 | G12: 5457540 | H12: 948229 | I12: 215658 | J12: 38105.845 | K12: 5684.4828 | L12: 1126051534
A13: oct | B13: 103771731 | C13: 1262970 | D13: 103398 | E13: 4707733 | F13: 17529528 | G13: 4813818 | H13: 1206578 | I13: 274614 | J13: 159945.12 | K13: 17652.586 | L13: 1287742925
A14: nov | B14: 121922567 | C14: 1422628 | D14: 115811 | E14: 4688825 | F14: 28802133 | G14: 7493286 | H14: 1364853 | I14: 832825 | J14: 236535.45 | K14: 38752.586 | L14: 1645378487
A15: dic | B15: 121938684 | C15: 1363878 | D15: 108517 | E15: 4638343 | F15: 43762583 | G15: 8916467 | H15: 2302519 | I15: 3036049 | J15: 350116.9 | K15: 8956.0345 | L15: 2226063308
A16: Total general | B16: 1052330368 | C16: 15093596 | D16: 1774946 | E16: 38372162 | F16: 228901940 | G16: 56803020 | H16: 13203495 | I16: 6672101 | J16: 799221.45 | K16: 72337.931 | L16: 15703020320
A19: Etiquetas de fila | B19: Suma de Meli Full 2025 | C19: Suma de Meli Drop 2025 | D19: Suma de Meli Drop 2026 | E19: Suma de Meli Full 2026 | G19: MELI 2025 | H19: MELI 2026 | I19: %VAR
A20: ene | B20: 2796767 | C20: 12634416 | D20: 15141562 | E20: 3117450 | F20: ene | G20: =SUM(B20:C20) -> 15431183 | H20: =SUM(D20:E20) -> 18259012 | I20: =H20/G20-1 -> 0.18325419
A21: feb | B21: 1592434 | C21: 8028750 | D21: 11257443 | E21: 1820069 | F21: feb | G21: =SUM(B21:C21) -> 9621184 | H21: =SUM(D21:E21) -> 13077512 | I21: =H21/G21-1 -> 0.35924144
A22: mar | B22: 3477562 | C22: 12534250 | D22: 14502060 | E22: 2278267 | F22: mar | G22: =SUM(B22:C22) -> 16011812 | H22: =SUM(D22:E22) -> 16780327 | I22: =H22/G22-1 -> 0.047996754
A23: abr | B23: 2880496 | C23: 10402707 | D23: 10291831 | E23: 2417828 | F23: abr | G23: =SUM(B23:C23) -> 13283203 | H23: =SUM(D23:E23) -> 12709659 | I23: =H23/G23-1 -> -0.04317814
A24: may | B24: 4277531 | C24: 17783854 | D24: 15146494 | E24: 4400759 | F24: may | G24: =SUM(B24:C24) -> 22061385 | H24: =SUM(D24:E24) -> 19547253 | I24: =H24/G24-1 -> -0.11396075
A25: jun | B25: 4885568 | C25: 21666219 | D25: 16071142 | E25: 5207754 | F25: jun | G25: =SUM(B25:C25) -> 26551787 | H25: =SUM(D25:E25) -> 21278896 | I25: =H25/G25-1 -> -0.19858893 | J25: =E25/B25-1 -> 0.065946477 | K25: =E25/B25-1 -> 0.065946477
A26: jul | B26: 3524088 | C26: 18674810 | D26: 9647154 | E26: 3148801 | F26: jul | G26: =SUM(B26:C26) -> 22198898 | H26: =SUM(D26:E26) -> 12795955 | I26: =H26/G26-1 -> -0.42357702 | J26: =E26/B26-1 -> -0.10649195 | K26: =E26/B26-1 -> -0.10649195
A27: ago | B27: 6687463 | C27: 21315555 | D27: 14363472 | E27: 5950435 | F27: ago | G27: =SUM(B27:C27) -> 28003018 | H27: =SUM(D27:E27) -> 20313907 | I27: =H27/G27-1 -> -0.27458151 | J27: =E27/B27-1 -> -0.1102104 | K27: =E27/B27-1 -> -0.1102104
A28: sep | B28: 5457540 | C28: 15767135 | F28: sep | G28: =SUM(B28:C28) -> 21224675 | H28: =SUM(D28:E28) -> 0
A29: oct | B29: 4813818 | C29: 17529528 | F29: oct | G29: =SUM(B29:C29) -> 22343346 | H29: =SUM(D29:E29) -> 0
A30: nov | B30: 7493286 | C30: 28802133 | F30: nov | G30: =SUM(B30:C30) -> 36295419 | H30: =SUM(D30:E30) -> 0
A31: dic | B31: 8916467 | C31: 43762583 | F31: dic | G31: =SUM(B31:C31) -> 52679050 | H31: =SUM(D31:E31) -> 0
A32: Total general | B32: 56803020 | C32: 228901940 | D32: 106421158 | E32: 28341363 | G32: =SUM(G20:G27) -> 153162470 | H32: =SUM(H20:H31) -> 134762521 | I32: =H32/G32-1 -> -0.12013354

Sheet may-ago
A3: Meses (2026) | B3: Días (2026) | C3: Web + APP 2026 | D3: Afiliados 2026 | E3: TMK 2026 | F3: WA 2026 | G3: Ent. en Tienda 2026 | H3: Meli Drop 2026 | I3: Meli Full 2026 | J3: Amazon Drop 2026 | K3: Amazon Full 2026 | L3: TikTok 2026 | M3: Shein 2026 | N3: Venta Total 2026 | O3: DIGITAL TOTAL | P3: MKP TOTAL
A4: may | B4: 01-may | C4: 2069924 | D4: 31463 | E4: 2522 | F4: 0 | G4: 33966 | H4: 215596 | I4: 89389 | J4: 23623 | K4: 9448 | L4: 2225 | M4: 3134 | N4: 2481290 | O4: =SUM(C4:G4) -> 2137875 | P4: =SUM(H4:M4) -> 343415
B5: 02-may | C5: 1930522 | D5: 20804 | E5: -732 | F5: 1144 | G5: 87762 | H5: 178276 | I5: 69883 | J5: 10926 | K5: 4862 | L5: 447 | M5: 4607 | N5: 2308501 | O5: =SUM(C5:G5) -> 2039500 | P5: =SUM(H5:M5) -> 269001
B6: 03-may | C6: 2628259 | D6: 23026 | E6: 11669 | F6: 740 | G6: 66322 | H6: 227157 | I6: 91628 | J6: 19133 | K6: 8602 | L6: 370 | M6: 5416 | N6: 3082322 | O6: =SUM(C6:G6) -> 2730016 | P6: =SUM(H6:M6) -> 352306
B7: 04-may | C7: 4124173 | D7: 25420 | E7: 28207 | F7: 5623 | G7: 67376 | H7: 521359 | I7: 170941 | J7: 18893 | K7: 10593 | L7: 2031 | M7: 2109 | N7: 4976725 | O7: =SUM(C7:G7) -> 4250799 | P7: =SUM(H7:M7) -> 725926
B8: 05-may | C8: 4494478 | D8: 24526 | E8: 55447 | F8: 6329 | G8: 70316 | H8: 610542 | I8: 206091 | J8: 34471 | K8: 15053 | L8: 4388 | M8: 4047 | N8: 5525688 | O8: =SUM(C8:G8) -> 4651096 | P8: =SUM(H8:M8) -> 874592
B9: 06-may | C9: 4088680 | D9: 22236 | E9: 15858 | F9: 0 | G9: 103050 | H9: 584166 | I9: 168986 | J9: 21276 | K9: 9621 | L9: 4594 | M9: 0 | N9: 5018467 | O9: =SUM(C9:G9) -> 4229824 | P9: =SUM(H9:M9) -> 788643
B10: 07-may | C10: 3214171 | D10: 22409 | E10: 45962 | F10: 0 | G10: 87902 | H10: 433044 | I10: 142471 | J10: 10390 | K10: 7381 | L10: 2879 | M10: 1248 | N10: 3967857 | O10: =SUM(C10:G10) -> 3370444 | P10: =SUM(H10:M10) -> 597413
B11: 08-may | C11: 1615018 | D11: 19192 | E11: 7092 | F11: 1998 | G11: 52205 | H11: 453556 | I11: 262519 | J11: 32442 | K11: 12700 | L11: 3174 | M11: 1464 | N11: 2461360 | O11: =SUM(C11:G11) -> 1695505 | P11: =SUM(H11:M11) -> 765855
B12: 09-may | C12: 1558074 | D12: 23729 | E12: 12190 | F12: 4102 | G12: 87416 | H12: 361074 | I12: 192329 | J12: 9552 | K12: 10260 | L12: 388 | M12: 646 | N12: 2259760 | O12: =SUM(C12:G12) -> 1685511 | P12: =SUM(H12:M12) -> 574249
B13: 10-may | C13: 1920563 | D13: 20514 | E13: -705 | F13: 2209 | G13: 48263 | H13: 395528 | I13: 141929 | J13: 24844 | K13: 7362 | L13: 256 | M13: 0 | N13: 2560763 | O13: =SUM(C13:G13) -> 1990844 | P13: =SUM(H13:M13) -> 569919
B14: 11-may | C14: 2440025 | D14: 21672 | E14: 29073 | F14: 5953 | G14: 60459 | H14: 409424 | I14: 123764 | J14: 11328 | K14: 10655 | L14: 991 | M14: 2109 | N14: 3115453 | O14: =SUM(C14:G14) -> 2557182 | P14: =SUM(H14:M14) -> 558271
B15: 12-may | C15: 2815317 | D15: 21451 | E15: 23262 | F15: 3933 | G15: 54841 | H15: 383123 | I15: 135469 | J15: 16632 | K15: 10371 | L15: 1022 | M15: 4650 | N15: 3470071 | O15: =SUM(C15:G15) -> 2918804 | P15: =SUM(H15:M15) -> 551267
B16: 13-may | C16: 3700459 | D16: 26216 | E16: 28501 | F16: 4829 | G16: 57302 | H16: 381201 | I16: 138856 | J16: 19491 | K16: 6421 | L16: 1247 | M16: 1937 | N16: 4366460 | O16: =SUM(C16:G16) -> 3817307 | P16: =SUM(H16:M16) -> 549153
... B34: 31-may | C34: 2739282 | D34: 36548 | E34: 7405 | F34: 4382 | G34: 80380 | H34: 1043225 | I34: 173161 | J34: 23659 | K34: 10923 | L34: 2086 | M34: 5728 | N34: 4126779 | O34: =SUM(C34:G34) -> 2867997 | P34: =SUM(H34:M34) -> 1258782
A35: Total may | C35: 94288932 | D35: 756439 | E35: 632168 | F35: 86712 | G35: 2472615 | H35: 15146494 | I35: 4400759 | J35: 643572 | K35: 286055 | L35: 78948 | M35: 105171 | N35: 118897865 | O35: =SUM(C35:G35) -> 98236866 | P35: =SUM(H35:M35) -> 20660999
A36: jun | B36: 01-jun | C36: 4064668 | D36: 29432 | E36: 26689 | F36: 10478 | G36: 92432 | H36: 904974 | I36: 135586 | J36: 29579 | K36: 10801 | L36: 8208 | M36: 8913 | N36: 5321760 | O36: =SUM(C36:G36) -> 4223699 | P36: =SUM(H36:M36) -> 1098061
B37: 02-jun | C37: 4572359 | D37: 23766 | E37: 47963 | F37: 15476 | G37: 108290 | H37: 930339 | I37: 178091 | J37: 32506 | K37: 12255 | L37: 4331 | M37: 4564 | N37: 5929940 | O37: =SUM(C37:G37) -> 4767854 | P37: =SUM(H37:M37) -> 1162086
B38: 03-jun | C38: 3552563 | D38: 26173 | E38: 32530 | F38: 6406 | G38: 121708 | H38: 539970 | I38: 136278 | J38: 35037 | K38: 7759 | L38: 4912 | M38: 1334 | N38: 4464670 | O38: =SUM(C38:G38) -> 3739380 | P38: =SUM(H38:M38) -> 725290
B39: 04-jun | C39: 2797805 | D39: 20815 | E39: 73509 | F39: 4322 | G39: 88544 | H39: 330252 | I39: 176072 | J39: 20525 | K39: 5500 | L39: 5098 | M39: 5081 | N39: 3527523 | O39: =SUM(C39:G39) -> 2984995 | P39: =SUM(H39:M39) -> 542528
B40: 05-jun | C40: 2265727 | D40: 32888 | E40: 13246 | F40: 5193 | G40: 99255 | H40: 351624 | I40: 180239 | J40: 11727 | K40: 6281 | L40: 4449 | M40: 1291 | N40: 2971920 | O40: =SUM(C40:G40) -> 2416309 | P40: =SUM(H40:M40) -> 555611
B41: 06-jun | C41: 2159116 | D41: 34578 | E41: 22387 | F41: 1996 | G41: 97775 | H41: 344708 | I41: 188671 | J41: 9093 | K41: 3824 | L41: 5418 | M41: 3100 | N41: 2870666 | O41: =SUM(C41:G41) -> 2315852 | P41: =SUM(H41:M41) -> 554814
B42: 07-jun | C42: 2835754 | D42: 33462 | E42: 1717 | F42: 3121 | G42: 82366 | H42: 526670 | I42: 201401 | J42: 12585 | K42: 6574 | L42: 2075 | M42: 3057 | N42: 3708782 | O42: =SUM(C42:G42) -> 2956420 | P42: =SUM(H42:M42) -> 752362
B43: 08-jun | C43: 4038776 | D43: 28413 | E43: 38880 | F43: 7184 | G43: 129134 | H43: 693965 | I43: 192882 | J43: 27190 | K43: 4960 | L43: 8849 | M43: 3057 | N43: 5173290 | O43: =SUM(C43:G43) -> 4242387 | P43: =SUM(H43:M43) -> 930903
B44: 09-jun | C44: 4305103 | D44: 32400 | E44: 65678 | F44: 1844 | G44: 114553 | H44: 480602 | I44: 174897 | J44: 13800 | K44: 7381 | L44: 11271 | M44: 1636 | N44: 5209165 | O44: =SUM(C44:G44) -> 4519578 | P44: =SUM(H44:M44) -> 689587
B45: 10-jun | C45: 4123039 | D45: 28567 | E45: 28987 | F45: 6055 | G45: 132557 | H45: 415988 | I45: 141262 | J45: 21700 | K45: 2811 | L45: 4259 | M45: 0 | N45: 4905225 | O45: =SUM(C45:G45) -> 4319205 | P45: =SUM(H45:M45) -> 586020
B46: 11-jun | C46: 2993082 | D46: 24347 | E46: 18478 | F46: 2267 | G46: 140034 | H46: 412479 | I46: 215146 | J46: 12955 | K46: 214 | L46: 4069 | M46: 1076 | N46: 3824147 | O46: =SUM(C46:G46) -> 3178208 | P46: =SUM(H46:M46) -> 645939
B47: 12-jun | C47: 2651227 | D47: 30709 | E47: 11629 | F47: 3889 | G47: 97304 | H47: 566709 | I47: 221811 | J47: 20101 | K47: 2802 | L47: 6123 | M47: 2627 | N47: 3614931 | O47: =SUM(C47:G47) -> 2794758 | P47: =SUM(H47:M47) -> 820173
B48: 13-jun | C48: 2172069 | D48: 41533 | E48: 29771 | F48: 2610 | G48: 43950 | H48: 427855 | I48: 215157 | J48: 16395 | K48: 3162 | L48: -34 | M48: 3272 | N48: 2955740 | O48: =SUM(C48:G48) -> 2289933 | P48: =SUM(H48:M48) -> 665807
... B65: 30-jun | C65: 4003008 | D65: 33147 | E65: 7770 | F65: 4521 | G65: 83644 | H65: 771777 | I65: 155445 | J65: 49773 | K65: 13299 | L65: 4538 | M65: 1937 | N65: 5128859 | O65: =SUM(C65:G65) -> 4132090 | P65: =SUM(H65:M65) -> 996769
A66: Total jun | C66: 97249818 | D66: 930194 | E66: 754232 | F66: 104106 | G66: 2740552 | H66: 16071142 | I66: 5207754 | J66: 749766 | K66: 243242 | L66: 196887 | M66: 90033 | N66: 124337726 | O66: =SUM(C66:G66) -> 101778902 | P66: =SUM(H66:M66) -> 22558824
A67: jul | B67: 01-jul | C67: 3854991 | D67: 33555 | E67: 37725 | F67: 3591 | G67: 72458 | H67: 625555 | I67: 147936 | J67: 54054 | K67: 17511 | L67: 6232 | M67: 1455 | N67: 4855063 | O67: =SUM(C67:G67) -> 4002320 | P67: =SUM(H67:M67) -> 852743
B68: 02-jul | C68: 2923874 | D68: 33721 | E68: 11767 | F68: 4184 | G68: 86120 | H68: 529374 | I68: 154761 | J68: 37080 | K68: 17915 | L68: 9869 | M68: 6287 | N68: 3814952 | O68: =SUM(C68:G68) -> 3059666 | P68: =SUM(H68:M68) -> 755286
B69: 03-jul | C69: 2705057 | D69: 43805 | E69: 17931 | F69: 1013 | G69: 84930 | H69: 337385 | I69: 118065 | J69: 42831 | K69: 10140 | L69: 10620 | M69: 1894 | N69: 3373671 | O69: =SUM(C69:G69) -> 2852736 | P69: =SUM(H69:M69) -> 520935
B70: 04-jul | C70: 2175054 | D70: 41461 | E70: 4234 | F70: 345 | G70: 73695 | H70: 476598 | I70: 108307 | J70: 37222 | K70: 7925 | L70: 56771 | M70: 2583 | N70: 2984195 | O70: =SUM(C70:G70) -> 2294789 | P70: =SUM(H70:M70) -> 689406
B71: 05-jul | C71: 2221020 | D71: 34456 | E71: -5691 | F71: 2342 | G71: 40115 | H71: 421919 | I71: 88467 | J71: 39269 | K71: 5114 | L71: 13798 | M71: 3488 | N71: 2864297 | O71: =SUM(C71:G71) -> 2292242 | P71: =SUM(H71:M71) -> 572055
B72: 06-jul | C72: 3592240 | D72: 37084 | E72: 13165 | F72: 3678 | G72: 43263 | H72: 516899 | I72: 122255 | J72: 22297 | K72: 3480 | L72: 17060 | M72: 3660 | N72: 4375081 | O72: =SUM(C72:G72) -> 3689430 | P72: =SUM(H72:M72) -> 685651
B73: 07-jul | C73: 3881350 | D73: 42546 | E73: 27712 | F73: 2534 | G73: 61051 | H73: 691715 | I73: 150430 | J73: 17456 | K73: 2549 | L73: 8033 | M73: 6201 | N73: 4891577 | O73: =SUM(C73:G73) -> 4015193 | P73: =SUM(H73:M73) -> 876384
B74: 08-jul | C74: 3404528 | D74: 36707 | E74: 48817 | F74: 4184 | G74: 89941 | H74: 628785 | I74: 147851 | J74: 25750 | K74: 5197 | L74: 8617 | M74: 1205 | N74: 4401582 | O74: =SUM(C74:G74) -> 3584177 | P74: =SUM(H74:M74) -> 817405
B75: 09-jul | C75: 3166533 | D75: 41275 | E75: 14603 | F75: 4141 | G75: 38529 | H75: 318377 | I75: 87484 | J75: 14199 | K75: 6363 | L75: 6495 | M75: 1248 | N75: 3699247 | O75: =SUM(C75:G75) -> 3265081 | P75: =SUM(H75:M75) -> 434166
B76: 10-jul | C76: 2597860 | D76: 41411 | E76: 28875 | F76: 5451 | G76: 161497 | H76: 363067 | I76: 95870 | J76: 14517 | K76: 6109 | L76: 5021 | M76: 2326 | N76: 3322004 | O76: =SUM(C76:G76) -> 2835094 | P76: =SUM(H76:M76) -> 486910
B77: 11-jul | C77: 1964012 | D77: 40374 | E77: 270 | F77: -18 | G77: 105814 | H77: 233528 | I77: 72542 | J77: 18682 | K77: 9069 | L77: 7197 | M77: 0 | N77: 2451470 | O77: =SUM(C77:G77) -> 2110452 | P77: =SUM(H77:M77) -> 341018
B78: 12-jul | C78: 20069 | D78: 1278 | E78: 0 | F78: 0 | G78: 33609 | H78: 38750 | I78: 6662 | J78: 1861 | K78: 794 | L78: 1636 | M78: 861 | N78: 105520 | O78: =SUM(C78:G78) -> 54956 | P78: =SUM(H78:M78) -> 50564
B79: 13-jul | C79: -4439 | D79: 0 | E79: 0 | F79: 0 | G79: -9316 | H79: 0 | I79: 154243 | J79: 0 | K79: 21040 | L79: 0 | M79: 0 | N79: 161528 | O79: =SUM(C79:G79) -> -13755 | P79: =SUM(H79:M79) -> 175283
... B97: 31-jul | C97: 2903566 | D97: 49697 | E97: 28578 | F97: 11071 | G97: 72428 | H97: 381868 | I97: 115054 | J97: 16287 | K97: 8524 | L97: 12321 | M97: 3617 | N97: 3603011 | O97: =SUM(C97:G97) -> 3065340 | P97: =SUM(H97:M97) -> 537671
A98: Total jul | C98: 83933912 | D98: 1150907 | E98: 395104 | F98: 141802 | G98: 1878801 | H98: 9647154 | I98: 3148801 | J98: 638312 | K98: 236823 | L98: 257607 | M98: 57686 | N98: 101486909 | O98: =SUM(C98:G98) -> 87500526 | P98: =SUM(H98:M98) -> 13986383
A99: ago | B99: 01-ago | C99: 2446126 | D99: 48403 | E99: 6004 | F99: 1786 | G99: 85521 | H99: 329279 | I99: 108433 | J99: 26082 | K99: 12102 | L99: 5795 | M99: 2041 | N99: 3071572 | O99: =SUM(C99:G99) -> 2587840 | P99: =SUM(H99:M99) -> 483732
B100: 02-ago | C100: 2980176 | D100: 54927 | E100: 0 | F100: 2470 | G100: 72324 | H100: 378023 | I100: 109603 | J100: 27620 | K100: 16588 | L100: 6225 | M100: 861 | N100: 3648817 | O100: =SUM(C100:G100) -> 3109897 | P100: =SUM(H100:M100) -> 538920
B101: 03-ago | C101: 4221939 | D101: 46928 | E101: 52670 | F101: 2247 | G101: 65922 | H101: 437544 | I101: 118991 | J101: 35120 | K101: 9760 | L101: 11524 | M101: 1378 | N101: 5004023 | O101: =SUM(C101:G101) -> 4389706 | P101: =SUM(H101:M101) -> 614317
B102: 04-ago | C102: 4338817 | D102: 52837 | E102: 38712 | F102: 7853 | G102: 80292 | H102: 401548 | I102: 100971 | J102: 28918 | K102: 15532 | L102: 6075 | M102: 1809 | N102: 5073364 | O102: =SUM(C102:G102) -> 4518511 | P102: =SUM(H102:M102) -> 554853
B103: 05-ago | C103: 3961812 | D103: 50879 | E103: 36417 | F103: 15109 | G103: 79655 | H103: 395590 | I103: 91725 | J103: 30739 | K103: 8694 | L103: 8108 | M103: 904 | N103: 4679632 | O103: =SUM(C103:G103) -> 4143872 | P103: =SUM(H103:M103) -> 535760
B104: 06-ago | C104: 3534572 | D104: 51525 | E104: 41165 | F104: 14122 | G104: 85303 | H104: 451607 | I104: 155591 | J104: 25766 | K104: 15513 | L104: 6476 | M104: 2153 | N104: 4383793 | O104: =SUM(C104:G104) -> 3726687 | P104: =SUM(H104:M104) -> 657106
B105: 07-ago | C105: 3007032 | D105: 49458 | E105: 15410 | F105: 753 | G105: 96092 | H105: 376897 | I105: 182901 | J105: 15451 | K105: 10998 | L105: 6179 | M105: 4565 | N105: 3765736 | O105: =SUM(C105:G105) -> 3168745 | P105: =SUM(H105:M105) -> 596991
B106: 08-ago | C106: 3117315 | D106: 49755 | E106: -2143 | F106: 16358 | G106: 107597 | H106: 405849 | I106: 220499 | J106: 32535 | K106: 11591 | L106: 10109 | M106: 2067 | N106: 3971532 | O106: =SUM(C106:G106) -> 3288882 | P106: =SUM(H106:M106) -> 682650
B107: 09-ago | C107: 3596880 | D107: 57414 | E107: 14662 | F107: 6852 | G107: 58728 | H107: 433070 | I107: 212540 | J107: 26298 | K107: 11364 | L107: 5631 | M107: 2540 | N107: 4425979 | O107: =SUM(C107:G107) -> 3734536 | P107: =SUM(H107:M107) -> 691443
B108: 10-ago | C108: 4582140 | D108: 47910 | E108: 22732 | F108: 9417 | G108: 120697 | H108: 489155 | I108: 205946 | J108: 44324 | K108: 9798 | L108: 7778 | M108: 1464 | N108: 5541361 | O108: =SUM(C108:G108) -> 4782896 | P108: =SUM(H108:M108) -> 758465
B109: 11-ago | C109: 4741330 | D109: 54809 | E109: 44133 | F109: 4828 | G109: 136695 | H109: 425261 | I109: 184068 | J109: 28255 | K109: 12530 | L109: 14828 | M109: 6805 | N109: 5653542 | O109: =SUM(C109:G109) -> 4981795 | P109: =SUM(H109:M109) -> 671747
B110: 12-ago | C110: 4494722 | D110: 58059 | E110: 50719 | F110: 6868 | G110: 135678 | H110: 452304 | I110: 214357 | J110: 33975 | K110: 9612 | L110: 10923 | M110: 3591 | N110: 5470808 | O110: =SUM(C110:G110) -> 4746046 | P110: =SUM(H110:M110) -> 724762
B111: 13-ago | C111: 3681443 | D111: 51171 | E111: 38856 | F111: 15603 | G111: 100446 | H111: 469013 | I111: 191108 | J111: 37897 | K111: 13748 | L111: 6868 | M111: 2756 | N111: 4608909 | O111: =SUM(C111:G111) -> 3887519 | P111: =SUM(H111:M111) -> 721390
... B129: 31-ago | C129: 3584257 | D129: 46953 | E129: 32425 | F129: 14272 | G129: 94850 | H129: 402779 | I129: 219040 | J129: 49968 | K129: 4422 | L129: 11214 | M129: 17191 | N129: 4477371 | O129: =SUM(C129:G129) -> 3772757 | P129: =SUM(H129:M129) -> 704614
A130: Total ago | C130: 124057121 | D130: 1762594 | E130: 913787 | F130: 251509 | G130: 3812455 | H130: 14766251 | I130: 6169475 | J130: 1133651 | K130: 265651 | L130: 280181 | M130: 125001 | N130: 153537676 | O130: =SUM(C130:G130) -> 130797466 | P130: =SUM(H130:M130) -> 22740210
A131: Total general | C131: 399529783 | D131: 4600134 | E131: 2695291 | F131: 584129 | G131: 10904423 | H131: 55631041 | I131: 18926789 | J131: 3165301 | K131: 1031771 | L131: 813623 | M131: 377891 | N131: 498260176 | O131: =SUM(C131:G131) -> 418313760 | P131: =SUM(H131:M131) -> 79946416

Sheet BD MD
C1: =+SUM(C3:C389) -> 1.4288748e+09 | G1: =+H1-H2 -> -1.0326591e+08 | H1: =+K2+O2+Q2+S2 -> 856993833 | J1: =+SUM(J3:J389) -> 1054900164 | L1: =+SUM(L3:L389) -> 11651867 | N1: =+SUM(N3:N389) -> 15094810 | P1: =+SUM(P3:P389) -> 1776830 | R1: =+SUM(R3:R389) -> 38370811 | T1: =+SUM(T3:T389) -> 229449233 | V1: =+SUM(V3:V389) -> 56838215 | X1: =+SUM(X3:X389) -> 13236238 | Z1: =+SUM(Z3:Z389) -> 6683046 | AB1: =+SUM(AB3:AB389) -> 801237.45 | AD1: =+SUM(AD3:AD389) -> 72337.931 | AE1: =+AD1+AB1+Z1+X1+V1+T1 -> 3.0708031e+08 | AF1: =+AC2+AA2+Y2+W2+U2 -> 165066124 | AP1: =AP2+AQ2 -> 9.3086203e+08 | AR1: =AR2+AS2 -> 1031500327 | AT1: =+AR1/AP1-1 -> 0.10811301 | AV1: =+AW2+AV2 -> 1.204792e+09 | AW1: =+AR1/AV1-1 -> -0.14383533 | BC1: =BC2+BD2 -> -1.7329165e+08 | BE1: =BE2+BF2 -> 1.5537545e+08
B2: =+SUBTOTAL(9,B4:B274) -> 10512401494 | C2: =+SUBTOTAL(9,C4:C274) -> 9.3086203e+08 | E2: =+SUBTOTAL(9,E4:E274) -> 10345159441 | G2: =+SUBTOTAL(9,G4:G274) -> 1.204792e+09 | H2: =+SUBTOTAL(9,H4:H274) -> 9.6025975e+08 | I2: =+SUBTOTAL(9,I4:I274) -> 2.4453223e+08 | J2: =+SUBTOTAL(9,J4:J274) -> 702116637 | K2: =+SUBTOTAL(9,K4:K274) -> 826123931 | L2: =+SUBTOTAL(9,L4:L274) -> 7600937.9 | M2: =+SUBTOTAL(9,M4:M274) -> 8859591 | N2: =+SUBTOTAL(9,N4:N274) -> 11013015 | ... AF2: =+SUBTOTAL(9,AF4:AF274) -> 1031500327 | AG2: =+AF2/G2 -> 0.85616467 | AH2: =+SUBTOTAL(9,AH4:AH274) -> -1.7329165e+08 | AI2: =+AF2/C2-1 -> 0.10811301 | AJ2: =+C2/B2 -> 0.088548942 | AK2: =+AF2/E2 -> 0.0997085 | AL2: =+E2/B2-1 -> -0.015909025 | AP2: =+SUBTOTAL(9,AP4:AP274) -> 7.464155e+08 | AQ2: =+SUBTOTAL(9,AQ4:AQ274) -> 1.8444653e+08 | AR2: =+SUBTOTAL(9,AR4:AR274) -> 865853424 | AS2: =+SUBTOTAL(9,AS4:AS274) -> 165646903 | AV2: =+SUBTOTAL(9,AV4:AV274) -> 9.6025975e+08 | AW2: =+SUBTOTAL(9,AW4:AW274) -> 2.4453223e+08 | BC2: =+SUBTOTAL(9,BC4:BC274) -> -94406323 | BD2: =+SUBTOTAL(9,BD4:BD274) -> -78885326 | BE2: =+SUBTOTAL(9,BE4:BE274) -> 1.3636048e+08 | BF2: =+SUBTOTAL(9,BF4:BF274) -> 19014970
A3: 2025 | B3: Global 2025 | C3: Vta 2025 | D3: Share diario | E3: Global 2026 | F3: 2026 | G3: Venta Meta 2026 | H3: Meta Digital | I3: Meta MKPlace | J3: Web + APP 2025 | K3: Web + APP 2026 | L3: Afiliados 2025 | M3: Afiliados 2026 | N3: TMK 2025 | O3: TMK 2026 | P3: WA 2025 | Q3: WA 2026 | R3: Ent. en Tienda 2025 | S3: Ent. en Tienda 2026 | T3: Meli Drop 2025 | U3: Meli Drop 2026 | V3: Meli Full 2025 | W3: Meli Full 2026 | X3: Amazon Drop 2025 | Y3: Amazon Drop 2026 | Z3: Amazon Full 2025 | AA3: Amazon Full 2026 | AB3: TikTok 2025 | AC3: TikTok 2026 | AD3: Shein 2025 | AE3: Shein 2026 | AF3: Venta Total 2026 | AG3: Alcance vs Meta | AH3: Deuda | AI3: Crecimiento | AJ3: Share vs Global 2025 | AK3: Share vs Global 2026 | AL3: Global YoY | AO3: Fecha | AP3: Digital 2025 | AQ3: MKP 2025 | AR3: Real Digital 2026 | AS3: Real MKP 2026 | AT3: YoY Digital | AU3: YoY Mktp | AV3: Meta Digital | AW3: Meta Mktp | AX3: Cump Digital | AY3: Cump Mktp | AZ3: Cump Total | BA3: Share Mktp | BB3: Share dig | BC3: Deuda Digital | BD3: Deuda Mktp | BE3: Digital vs25 | BF3: MKP vs25
A4: 45659 | B4: 35585285 | C4: =+J4+L4+N4+P4+R4+T4+V4+X4+Z4+AB4+AD4 -> 3530236.3 | D4: =+Tabla22[[#This Row],[Share diario]] -> -0.00033795059 | E4: =+Tabla22[[#This Row],[Global 2026]] -> 1767787 | F4: 46023 | G4: =+H4+I4 -> -36578.828 | H4: -91461.011 | I4: 54882.183 | J4: 2533552 | K4: 1117875 | L4: 48254.31 | M4: 17319 | N4: 21696 | O4: 0 | P4: 5984 | Q4: 1884 | R4: 47691 | S4: 0 | T4: 671816 | U4: 511381 | V4: 116771 | W4: 78269 | X4: 84472 | Y4: 31357 | Z4: 0 | AA4: 7591 | AB4: 0 | AC4: 2016 | AD4: 0 | AE4: 0 | AF4: =+AE4+AC4+AA4+Y4+W4+U4+S4+Q4+O4+M4+K4 -> 1767692 | AG4: =+AF4/G4 -> -48.325551 | AH4: =+AF4-G4 -> 1804270.8 | AI4: =+AF4/C4-1 -> -0.49927091 | AJ4: =+C4/B4 -> 0.099204947 | AK4: =+AF4/E4 -> 0.99994626 | AL4: =+E4/B4-1 -> -0.95032253 | AO4: =+F4 -> 46023 | AP4: =Tabla2[[#This Row],[Web + APP 2025]]+Tabla2[[#This Row],[Afiliados 2025]]+Tabla2[[#This Row],[TMK 2025]]+Tabla2[[#This Row],[WA 2025]]+Tabla2[[#This Row],[Ent. en Tienda 2025]] -> 2657177.3 | AQ4: =Tabla2[[#This Row],[Meli Drop 2025]]+Tabla2[[#This Row],[Meli Full 2025]]+Tabla2[[#This Row],[Amazon Drop 2025]]+Tabla2[[#This Row],[Amazon Full 2025]]+Tabla2[[#This Row],[TikTok 2025]]+Tabla2[[#This Row],[Shein 2025]] -> 873059 | AR4: =Tabla2[[#This Row],[Web + APP 2026]]+Tabla2[[#This Row],[Afiliados 2026]]+Tabla2[[#This Row],[TMK 2026]]+Tabla2[[#This Row],[WA 2026]]+Tabla2[[#This Row],[Ent. en Tienda 2026]] -> 1137078 | AS4: =Tabla2[[#This Row],[Meli Drop 2026]]+Tabla2[[#This Row],[Meli Full 2026]]+Tabla2[[#This Row],[Amazon Drop 2026]]+Tabla2[[#This Row],[Amazon Full 2026]]+Tabla2[[#This Row],[TikTok 2026]]+Tabla2[[#This Row],[Shein 2026]] -> 630614 | AT4: =+AR4/AP4-1 -> -0.57207297 | AU4: =+AS4/AQ4-1 -> -0.27769601 | AV4: =+H4 -> -91461.011 | AW4: =+I4 -> 54882.183 | AX4: =+AR4/AV4 -> -12.432379 | AY4: =+AS4/AW4 -> 11.490323 | AZ4: =+(AR4+AS4)/(AV4+AW4) -> -48.325551 | BA4: 0.0024610845 | BB4: -0.001042448 | BC4: =+AR4-AV4 -> 1228539 | BD4: =+AS4-AW4 -> 575731.82
A5: 45660 | B5: 45059441 | C5: =+J5+L5+N5+P5+R5+T5+V5+X5+Z5+AB5+AD5 -> 2122251.3 | D5: =+Tabla22[[#This Row],[Share diario]] -> 0.040988265 | E5: =+Tabla22[[#This Row],[Global 2026]] -> 37878399 | F5: 46024 | G5: =+H5+I5 -> 4512263.3 | H5: 3388096 | I5: 1124167.3 | J5: 1249824 | K5: 1824628 | L5: 33610.345 | M5: =20000+12072 -> 32072 | N5: 21922 | O5: 15461 | P5: 4267 | Q5: 5339 | R5: 40797 | S5: 100874 | T5: 650641 | U5: 906403 | V5: 73651 | W5: 134485 | X5: 47539 | Y5: 28403 | Z5: 0 | AA5: 8334 | AB5: 0 | AC5: 1412 | AD5: 0 | AE5: 0 | AF5: =+AE5+AC5+AA5+Y5+W5+U5+S5+Q5+O5+M5+K5 -> 3057411 | AG5: =+AF5/G5 -> 0.67757815 | AH5: =+AF5-G5 -> -1454852.3 | AI5: =+AF5/C5-1 -> 0.4406451 | AJ5: =+C5/B5 -> 0.047098927 | AK5: =+AF5/E5 -> 0.080716479 | AL5: =+E5/B5-1 -> -0.1593682 | AO5: =+F5 -> 46024 | AP5: =Tabla2[[#This Row],[Web + APP 2025]]+Tabla2[[#This Row],[Afiliados 2025]]+Tabla2[[#This Row],[TMK 2025]]+Tabla2[[#This Row],[WA 2025]]+Tabla2[[#This Row],[Ent. en Tienda 2025]] -> 1350420.3 | AQ5: =Tabla2[[#This Row],[Meli Drop 2025]]+Tabla2[[#This Row],[Meli Full 2025]]+Tabla2[[#This Row],[Amazon Drop 2025]]+Tabla2[[#This Row],[Amazon Full 2025]]+Tabla2[[#This Row],[TikTok 2025]]+Tabla2[[#This Row],[Shein 2025]] -> 771831 | AR5: =Tabla2[[#This Row],[Web + APP 2026]]+Tabla2[[#This Row],[Afiliados 2026]]+Tabla2[[#This Row],[TMK 2026]]+Tabla2[[#This Row],[WA 2026]]+Tabla2[[#This Row],[Ent. en Tienda 2026]] -> 1978374 | AS5: =Tabla2[[#This Row],[Meli Drop 2026]]+Tabla2[[#This Row],[Meli Full 2026]]+Tabla2[[#This Row],[Amazon Drop 2026]]+Tabla2[[#This Row],[Amazon Full 2026]]+Tabla2[[#This Row],[TikTok 2026]]+Tabla2[[#This Row],[Shein 2026]] -> 1079037 | AT5: =+AR5/AP5-1 -> 0.46500607 | AU5: =+AS5/AQ5-1 -> 0.39802236 | AV5: =+H5 -> 3388096 | AW5: =+I5 -> 1124167.3 | AX5: =+AR5/AV5 -> 0.58391912 | AY5: =+AS5/AW5 -> 0.95985444 | AZ5: =+(AR5+AS5)/(AV5+AW5) -> 0.67757815 | BA5: 0.050411091 | BB5: 0.038616606 | BC5: =+AR5-AV5 -> -1409722 | BD5: =+AS5-AW5 -> -45130.332
A6: 45661 | B6: 52763562 | C6: =+J6+L6+N6+P6+R6+T6+V6+X6+Z6+AB6+AD6 -> 1311867 | D6: =+Tabla22[[#This Row],[Share diario]] -> 0.024640674 | E6: =+Tabla22[[#This Row],[Global 2026]] -> 45280774 | F6: 46025 | G6: =+H6+I6 -> 2715709.2 | H6: 1721885 | I6: 993824.24 | J6: 805491 | K6: 1844500 | L6: 33443.966 | M6: =18860+11525 -> 30385 | N6: -972 | O6: 4998 | P6: 125 | Q6: 903 | R6: 76993 | S6: 60781 | T6: 272764 | U6: 517553 | V6: 79911 | W6: 118746 | X6: 44111 | Y6: 27889 | Z6: 0 | AA6: 13091 | AB6: 0 | AC6: 688 | AD6: 0 | AE6: 0 | AF6: =+AE6+AC6+AA6+Y6+W6+U6+S6+Q6+O6+M6+K6 -> 2619534 | AG6: =+AF6/G6 -> 0.96458559 | AH6: =+AF6-G6 -> -96175.229 | AI6: =+AF6/C6-1 -> 0.99679851 | AJ6: =+C6/B6 -> 0.024863124 | AK6: =+AF6/E6 -> 0.05785091 | AL6: =+E6/B6-1 -> -0.14181734 | AO6: =+F6 -> 46025 | AP6: =Tabla2[[#This Row],[Web + APP 2025]]+Tabla2[[#This Row],[Afiliados 2025]]+Tabla2[[#This Row],[TMK 2025]]+Tabla2[[#This Row],[WA 2025]]+Tabla2[[#This Row],[Ent. en Tienda 2025]] -> 915080.97 | AQ6: =Tabla2[[#This Row],[Meli Drop 2025]]+Tabla2[[#This Row],[Meli Full 2025]]+Tabla2[[#This Row],[Amazon Drop 2025]]+Tabla2[[#This Row],[Amazon Full 2025]]+Tabla2[[#This Row],[TikTok 2025]]+Tabla2[[#This Row],[Shein 2025]] -> 396786 | AR6: =Tabla2[[#This Row],[Web + APP 2026]]+Tabla2[[#This Row],[Afiliados 2026]]+Tabla2[[#This Row],[TMK 2026]]+Tabla2[[#This Row],[WA 2026]]+Tabla2[[#This Row],[Ent. en Tienda 2026]] -> 1941567 | AS6: =Tabla2[[#This Row],[Meli Drop 2026]]+Tabla2[[#This Row],[Meli Full 2026]]+Tabla2[[#This Row],[Amazon Drop 2026]]+Tabla2[[#This Row],[Amazon Full 2026]]+Tabla2[[#This Row],[TikTok 2026]]+Tabla2[[#This Row],[Shein 2026]] -> 677967 | AT6: =+AR6/AP6-1 -> 1.1217434 | AU6: =+AS6/AQ6-1 -> 0.70864647 | AV6: =+H6 -> 1721885 | AW6: =+I6 -> 993824.24 | AX6: =+AR6/AV6 -> 1.1275823 | AY6: =+AS6/AW6 -> 0.68217998 | AZ6: =+(AR6+AS6)/(AV6+AW6) -> 0.96458559 | BA6: 0.044566109 | BB6: 0.019625582 | BC6: =+AR6-AV6 -> 219682.01 | BD6: =+AS6-AW6 -> -315857.24
A7: 45662 | B7: 49768856 | C7: =+J7+L7+N7+P7+R7+T7+V7+X7+Z7+AB7+AD7 -> 1824121.7 | D7: =+Tabla22[[#This Row],[Share diario]] -> 0.015231601 | E7: =+Tabla22[[#This Row],[Global 2026]] -> 49319936 | F7: 46026 | G7: =+H7+I7 -> 1677704.5 | H7: 1166795.4 | I7: 510909.18 | J7: 1228466 | K7: 1894237 | L7: 26220.69 | M7: =20047+15747 -> 35794 | N7: 6650 | O7: 2820 | P7: 4220 | Q7: 1256 | R7: 118329 | S7: 34216 | T7: 311434 | U7: 181111 | V7: 74826 | W7: 111132 | X7: 53976 | Y7: 24171 | Z7: 0 | AA7: 11093 | AB7: 0 | AC7: 0 | AD7: 0 | AE7: 0 | AF7: =+AE7+AC7+AA7+Y7+W7+U7+S7+Q7+O7+M7+K7 -> 2295830 | AG7: =+AF7/G7 -> 1.3684352 | AH7: =+AF7-G7 -> 618125.47 | AI7: =+AF7/C7-1 -> 0.25859476 | AJ7: =+C7/B7 -> 0.036651871 | AK7: =+AF7/E7 -> 0.046549736 | AL7: =+E7/B7-1 -> -0.0090200988 | AO7: =+F7 -> 46026 | AP7: =Tabla2[[#This Row],[Web + APP 2025]]+Tabla2[[#This Row],[Afiliados 2025]]+Tabla2[[#This Row],[TMK 2025]]+Tabla2[[#This Row],[WA 2025]]+Tabla2[[#This Row],[Ent. en Tienda 2025]] -> 1383885.7 | AQ7: =Tabla2[[#This Row],[Meli Drop 2025]]+Tabla2[[#This Row],[Meli Full 2025]]+Tabla2[[#This Row],[Amazon Drop 2025]]+Tabla2[[#This Row],[Amazon Full 2025]]+Tabla2[[#This Row],[TikTok 2025]]+Tabla2[[#This Row],[Shein 2025]] -> 440236 | AR7: =Tabla2[[#This Row],[Web + APP 2026]]+Tabla2[[#This Row],[Afiliados 2026]]+Tabla2[[#This Row],[TMK 2026]]+Tabla2[[#This Row],[WA 2026]]+Tabla2[[#This Row],[Ent. en Tienda 2026]] -> 1968323 | AS7: =Tabla2[[#This Row],[Meli Drop 2026]]+Tabla2[[#This Row],[Meli Full 2026]]+Tabla2[[#This Row],[Amazon Drop 2026]]+Tabla2[[#This Row],[Amazon Full 2026]]+Tabla2[[#This Row],[TikTok 2026]]+Tabla2[[#This Row],[Shein 2026]] -> 327507 | AT7: =+AR7/AP7-1 -> 0.42231617 | AU7: =+AS7/AQ7-1 -> -0.25606493 | AV7: =+H7 -> 1166795.4 | AW7: =+I7 -> 510909.18 | AX7: =+AR7/AV7 -> 1.6869479 | AY7: =+AS7/AW7 -> 0.64102782 | AZ7: =+(AR7+AS7)/(AV7+AW7) -> 1.3684352 | BA7: 0.022910726 | BB7: 0.01329882 | BC7: =+AR7-AV7 -> 801527.65 | BD7: =+AS7-AW7 -> -183402.18
A8: 45663 | B8: 22835293 | C8: =+J8+L8+N8+P8+R8+T8+V8+X8+Z8+AB8+AD8 -> 3136399 | D8: =+Tabla22[[#This Row],[Share diario]] -> 0.021179201 | E8: =+Tabla22[[#This Row],[Global 2026]] -> 42820052 | F8: 46027 | G8: =+H8+I8 -> 2331412 | H8: 1764555.8 | I8: 566856.23 | J8: 2147376 | K8: 2243868 | L8: 18700 | M8: =16759+12375 -> 29134 | N8: 36331 | O8: 10063 | P8: -500 | Q8: 4612 | R8: 58951 | S8: 91070 | T8: 714238 | U8: 1061982 | V8: 83712 | W8: 81808 | X8: 77591 | Y8: 39071 | Z8: 0 | AA8: 9717 | AB8: 0 | AC8: 11108 | AD8: 0 | AE8: 0 | AF8: =+AE8+AC8+AA8+Y8+W8+U8+S8+Q8+O8+M8+K8 -> 3582433 | AG8: =+AF8/G8 -> 1.5365937 | AH8: =+AF8-G8 -> 1251021 | AI8: =+AF8/C8-1 -> 0.14221214 | AJ8: =+C8/B8 -> 0.13734875 | AK8: =+AF8/E8 -> 0.083662509 | AL8: =+E8/B8-1 -> 0.87516981 | AO8: =+F8 -> 46027 | AP8: =Tabla2[[#This Row],[Web + APP 2025]]+Tabla2[[#This Row],[Afiliados 2025]]+Tabla2[[#This Row],[TMK 2025]]+Tabla2[[#This Row],[WA 2025]]+Tabla2[[#This Row],[Ent. en Tienda 2025]] -> 2260858 | AQ8: =Tabla2[[#This Row],[Meli Drop 2025]]+Tabla2[[#This Row],[Meli Full 2025]]+Tabla2[[#This Row],[Amazon Drop 2025]]+Tabla2[[#This Row],[Amazon Full 2025]]+Tabla2[[#This Row],[TikTok 2025]]+Tabla2[[#This Row],[Shein 2025]] -> 875541 | AR8: =Tabla2[[#This Row],[Web + APP 2026]]+Tabla2[[#This Row],[Afiliados 2026]]+Tabla2[[#This Row],[TMK 2026]]+Tabla2[[#This Row],[WA 2026]]+Tabla2[[#This Row],[Ent. en Tienda 2026]] -> 2378747 | AS8: =Tabla2[[#This Row],[Meli Drop 2026]]+Tabla2[[#This Row],[Meli Full 2026]]+Tabla2[[#This Row],[Amazon Drop 2026]]+Tabla2[[#This Row],[Amazon Full 2026]]+Tabla2[[#This Row],[TikTok 2026]]+Tabla2[[#This Row],[Shein 2026]] -> 1203686 | AT8: =+AR8/AP8-1 -> 0.052143478 | AU8: =+AS8/AQ8-1 -> 0.37479113 | AV8: =+H8 -> 1764555.8 | AW8: =+I8 -> 566856.23 | AX8: =+AR8/AV8 -> 1.3480713 | AY8: =+AS8/AW8 -> 2.1234414 | AZ8: =+(AR8+AS8)/(AV8+AW8) -> 1.5365937 | BA8: 0.025419562 | BB8: 0.020111932 | BC8: =+AR8-AV8 -> 614191.24 | BD8: =+AS8-AW8 -> 636829.77
A9: 45664 | B9: 23697613 | C9: =+J9+L9+N9+P9+R9+T9+V9+X9+Z9+AB9+AD9 -> 2922246.1 | D9: =+Tabla22[[#This Row],[Share diario]] -> 0.036415566 | E9: =+Tabla22[[#This Row],[Global 2026]] -> 22329279 | F9: 46028 | G9: =+H9+I9 -> 4010123 | H9: 2882759.8 | I9: 1127363.2 | J9: 2444768 | K9: 2374462 | L9: 20049.138 | M9: =12777+8956 -> 21733 | N9: 54064 | O9: 67853 | P9: -344 | Q9: -114 | R9: 55989 | S9: 66697 | T9: 209116 | U9: 650825 | V9: 80417 | W9: 87785 | X9: 58187 | Y9: 32894 | Z9: 0 | AA9: 14047 | AB9: 0 | AC9: 11280 | AD9: 0 | AE9: 1120 | AF9: =+AE9+AC9+AA9+Y9+W9+U9+S9+Q9+O9+M9+K9 -> 3328582 | AG9: =+AF9/G9 -> 0.83004487 | AH9: =+AF9-G9 -> -681540.98 | AI9: =+AF9/C9-1 -> 0.13904916 | AJ9: =+C9/B9 -> 0.12331394 | AK9: =+AF9/E9 -> 0.14906805 | AL9: =+E9/B9-1 -> -0.057741427 | AO9: =+F9 -> 46028 | AP9: =Tabla2[[#This Row],[Web + APP 2025]]+Tabla2[[#This Row],[Afiliados 2025]]+Tabla2[[#This Row],[TMK 2025]]+Tabla2[[#This Row],[WA 2025]]+Tabla2[[#This Row],[Ent. en Tienda 2025]] -> 2574526.1 | AQ9: =Tabla2[[#This Row],[Meli Drop 2025]]+Tabla2[[#This Row],[Meli Full 2025]]+Tabla2[[#This Row],[Amazon Drop 2025]]+Tabla2[[#This Row],[Amazon Full 2025]]+Tabla2[[#This Row],[TikTok 2025]]+Tabla2[[#This Row],[Shein 2025]] -> 347720 | AR9: =Tabla2[[#This Row],[Web + APP 2026]]+Tabla2[[#This Row],[Afiliados 2026]]+Tabla2[[#This Row],[TMK 2026]]+Tabla2[[#This Row],[WA 2026]]+Tabla2[[#This Row],[Ent. en Tienda 2026]] -> 2530631 | AS9: =Tabla2[[#This Row],[Meli Drop 2026]]+Tabla2[[#This Row],[Meli Full 2026]]+Tabla2[[#This Row],[Amazon Drop 2026]]+Tabla2[[#This Row],[Amazon Full 2026]]+Tabla2[[#This Row],[TikTok 2026]]+Tabla2[[#This Row],[Shein 2026]] -> 797951 | AT9: =+AR9/AP9-1 -> -0.017049793 | AU9: =+AS9/AQ9-1 -> 1.294809 | AV9: =+H9 -> 2882759.8 | AW9: =+I9 -> 1127363.2 | AX9: =+AR9/AV9 -> 0.87785011 | AY9: =+AS9/AW9 -> 0.70780295 | AZ9: =+(AR9+AS9)/(AV9+AW9) -> 0.83004487 | BA9: 0.050554404 | BB9: 0.03285692 | BC9: =+AR9-AV9 -> -352128.78 | BD9: =+AS9-AW9 -> -329412.2
A10: 45665 | B10: 26871838 | C10: =+J10+L10+N10+P10+R10+T10+V10+X10+Z10+AB10+AD10 -> 3244805 | D10: =+Tabla22[[#This Row],[Share diario]] -> 0.033929117 | E10: =+Tabla22[[#This Row],[Global 2026]] -> 23046004 | F10: 46029 | G10: =+H10+I10 -> 3730440.5 | H10: 3282709.7 | I10: 447730.87 | J10: 2443314 | K10: 2461726 | L10: 26275 | M10: =14222+10727 -> 24949 | N10: 56169 | O10: 16759 | P10: 3661 | Q10: 5667 | R10: 70092 | S10: 41847 | T10: 538812 | U10: 438746 | V10: 68361 | W10: 113224 | X10: 38121 | Y10: 5778 | Z10: 0 | AA10: 10555 | AB10: 0 | AC10: 14781 | AD10: 0 | AE10: 0 | AF10: =+AE10+AC10+AA10+Y10+W10+U10+S10+Q10+O10+M10+K10 -> 3134032 | AG10: =+AF10/G10 -> 0.84012383 | AH10: =+AF10-G10 -> -596408.53 | AI10: =+AF10/C10-1 -> -0.034138569 | AJ10: =+C10/B10 -> 0.12075114 | AK10: =+AF10/E10 -> 0.13599026 | AL10: =+E10/B10-1 -> -0.14237337 | AO10: =+F10 -> 46029 | AP10: =Tabla2[[#This Row],[Web + APP 2025]]+Tabla2[[#This Row],[Afiliados 2025]]+Tabla2[[#This Row],[TMK 2025]]+Tabla2[[#This Row],[WA 2025]]+Tabla2[[#This Row],[Ent. en Tienda 2025]] -> 2599511 | AQ10: =Tabla2[[#This Row],[Meli Drop 2025]]+Tabla2[[#This Row],[Meli Full 2025]]+Tabla2[[#This Row],[Amazon Drop 2025]]+Tabla2[[#This Row],[Amazon Full 2025]]+Tabla2[[#This Row],[TikTok 2025]]+Tabla2[[#This Row],[Shein 2025]] -> 645294 | AR10: =Tabla2[[#This Row],[Web + APP 2026]]+Tabla2[[#This Row],[Afiliados 2026]]+Tabla2[[#This Row],[TMK 2026]]+Tabla2[[#This Row],[WA 2026]]+Tabla2[[#This Row],[Ent. en Tienda 2026]] -> 2550948 | AS10: =Tabla2[[#This Row],[Meli Drop 2026]]+Tabla2[[#This Row],[Meli Full 2026]]+Tabla2[[#This Row],[Amazon Drop 2026]]+Tabla2[[#This Row],[Amazon Full 2026]]+Tabla2[[#This Row],[TikTok 2026]]+Tabla2[[#This Row],[Shein 2026]] -> 583084 | AT10: =+AR10/AP10-1 -> -0.01868159 | AU10: =+AS10/AQ10-1 -> -0.096405669 | AV10: =+H10 -> 3282709.7 | AW10: =+I10 -> 447730.87 | AX10: =+AR10/AV10 -> 0.77708609 | AY10: =+AS10/AW10 -> 1.3023091 | AZ10: =+(AR10+AS10)/(AV10+AW10) -> 0.84012383 | BA10: 0.020077617 | BB10: 0.037415442 | BC10: =+AR10-AV10 -> -731761.66 | BD10: =+AS10-AW10 -> 135353.13
A11: 45666 | B11: 28051817 | C11: =+J11+L11+N11+P11+R11+T11+V11+X11+Z11+AB11+AD11 -> 2520450.3 | D11: =+Tabla22[[#This Row],[Share diario]] -> 0.037674228 | E11: =+Tabla22[[#This Row],[Global 2026]] -> 26562197 | F11: 46030 | G11: =+H11+I11 -> 4145460 | H11: 3314567.2 | I11: 830892.8 | J11: 2184366 | K11: 2651325 | L11: 24654.31 | M11: =16483+7384 -> 23867 | N11: 59780 | O11: 32696 | P11: 2734 | Q11: 1757 | R11: 31913 | S11: 21864 | T11: 73729 | U11: 443664 | V11: 68117 | W11: 108455 | X11: 75157 | Y11: 25645 | Z11: 0 | AA11: 3530 | AB11: 0 | AC11: 21246 | AD11: 0 | AE11: 947 | AF11: =+AE11+AC11+AA11+Y11+W11+U11+S11+Q11+O11+M11+K11 -> 3334996 | AG11: =+AF11/G11 -> 0.80449359 | AH11: =+AF11-G11 -> -810463.99 | AI11: =+AF11/C11-1 -> 0.32317467 | AJ11: =+C11/B11 -> 0.089849806 | AK11: =+AF11/E11 -> 0.12555422 | AL11: =+E11/B11-1 -> -0.053102443 | AO11: =+F11 -> 46030 | AP11: =Tabla2[[#This Row],[Web + APP 2025]]+Tabla2[[#This Row],[Afiliados 2025]]+Tabla2[[#This Row],[TMK 2025]]+Tabla2[[#This Row],[WA 2025]]+Tabla2[[#This Row],[Ent. en Tienda 2025]] -> 2303447.3 | AQ11: =Tabla2[[#This Row],[Meli Drop 2025]]+Tabla2[[#This Row],[Meli Full 2025]]+Tabla2[[#This Row],[Amazon Drop 2025]]+Tabla2[[#This Row],[Amazon Full 2025]]+Tabla2[[#This Row],[TikTok 2025]]+Tabla2[[#This Row],[Shein 2025]] -> 217003 | AR11: =Tabla2[[#This Row],[Web + APP 2026]]+Tabla2[[#This Row],[Afiliados 2026]]+Tabla2[[#This Row],[TMK 2026]]+Tabla2[[#This Row],[WA 2026]]+Tabla2[[#This Row],[Ent. en Tienda 2026]] -> 2731509 | AS11: =Tabla2[[#This Row],[Meli Drop 2026]]+Tabla2[[#This Row],[Meli Full 2026]]+Tabla2[[#This Row],[Amazon Drop 2026]]+Tabla2[[#This Row],[Amazon Full 2026]]+Tabla2[[#This Row],[TikTok 2026]]+Tabla2[[#This Row],[Shein 2026]] -> 603487 | AT11: =+AR11/AP11-1 -> 0.18583524 | AU11: =+AS11/AQ11-1 -> 1.7810076 | AV11: =+H11 -> 3314567.2 | AW11: =+I11 -> 830892.8 | AX11: =+AR11/AV11 -> 0.82409221 | AY11: =+AS11/AW11 -> 0.72631151 | AZ11: =+(AR11+AS11)/(AV11+AW11) -> 0.80449359 | BA11: 0.037259767 | BB11: 0.037778545 | BC11: =+AR11-AV11 -> -583058.19 | BD11: =+AS11-AW11 -> -227405.8
A12: 45667 | B12: 28699623 | C12: =+J12+L12+N12+P12+R12+T12+V12+X12+Z12+AB12+AD12 -> 2278857.6 | D12: =+Tabla22[[#This Row],[Share diario]] -> 0.029264014 | E12: =+Tabla22[[#This Row],[Global 2026]] -> 26952477 | F12: 46031 | G12: =+H12+I12 -> 3216481.5 | H12: 2937064.3 | I12: 279417.18 | J12: 2007643 | K12: 1967914 | L12: 26027.586 | M12: =14542+13435 -> 27977 | N12: 69118 | O12: 732 | P12: 2178 | Q12: 3382 | R12: 45932 | S12: 81797 | T12: 27229 | U12: 357183 | V12: 63746 | W12: 88348 | X12: 36984 | Y12: 22372 | Z12: 0 | AA12: 11805 | AB12: 0 | AC12: 15175 | AD12: 0 | AE12: 689 | AF12: =+AE12+AC12+AA12+Y12+W12+U12+S12+Q12+O12+M12+K12 -> 2577374 | AG12: =+AF12/G12 -> 0.8013023 | AH12: =+AF12-G12 -> -639107.45 | AI12: =+AF12/C12-1 -> 0.13099389 | AJ12: =+C12/B12 -> 0.079403746 | AK12: =+AF12/E12 -> 0.09562661 | AL12: =+E12/B12-1 -> -0.060876967 | AO12: =+F12 -> 46031 | AP12: =Tabla2[[#This Row],[Web + APP 2025]]+Tabla2[[#This Row],[Afiliados 2025]]+Tabla2[[#This Row],[TMK 2025]]+Tabla2[[#This Row],[WA 2025]]+Tabla2[[#This Row],[Ent. en Tienda 2025]] -> 2150898.6 | AQ12: =Tabla2[[#This Row],[Meli Drop 2025]]+Tabla2[[#This Row],[Meli Full 2025]]+Tabla2[[#This Row],[Amazon Drop 2025]]+Tabla2[[#This Row],[Amazon Full 2025]]+Tabla2[[#This Row],[TikTok 2025]]+Tabla2[[#This Row],[Shein 2025]] -> 127959 | AR12: =Tabla2[[#This Row],[Web + APP 2026]]+Tabla2[[#This Row],[Afiliados 2026]]+Tabla2[[#This Row],[TMK 2026]]+Tabla2[[#This Row],[WA 2026]]+Tabla2[[#This Row],[Ent. en Tienda 2026]] -> 2081802 | AS12: =Tabla2[[#This Row],[Meli Drop 2026]]+Tabla2[[#This Row],[Meli Full 2026]]+Tabla2[[#This Row],[Amazon Drop 2026]]+Tabla2[[#This Row],[Amazon Full 2026]]+Tabla2[[#This Row],[TikTok 2026]]+Tabla2[[#This Row],[Shein 2026]] -> 495572 | AT12: =+AR12/AP12-1 -> -0.032124521 | AU12: =+AS12/AQ12-1 -> 2.8728968 | AV12: =+H12 -> 2937064.3 | AW12: =+I12 -> 279417.18 | AX12: =+AR12/AV12 -> 0.70880369 | AY12: =+AS12/AW12 -> 1.7735917 | AZ12: =+(AR12+AS12)/(AV12+AW12) -> 0.8013023 | BA12: 0.012529918 | BB12: 0.033475868 | BC12: =+AR12-AV12 -> -855262.27 | BD12: =+AS12-AW12 -> 216154.82
A13: 45668 | B13: 40105570 | C13: =+J13+L13+N13+P13+R13+T13+V13+X13+Z13+AB13+AD13 -> 2287848.8 | D13: =+Tabla22[[#This Row],[Share diario]] -> 0.026458971 | E13: =+Tabla22[[#This Row],[Global 2026]] -> 35436338 | F13: 46032 | G13: =+H13+I13 -> 2907315.9 | H13: 2742553.5 | I13: 164762.44 | J13: 1623013 | K13: 1571666 | L13: 27638.793 | M13: =14575+13419 -> 27994 | N13: 37575 | O13: 71315 | P13: 943 | Q13: -96 | R13: 46764 | S13: 34126 | T13: 466722 | U13: 488987 | V13: 44669 | W13: 120073 | X13: 40524 | Y13: 23228 | Z13: 0 | AA13: 6392 | AB13: 0 | AC13: -1487 | AD13: 0 | AE13: 689 | AF13: =+AE13+AC13+AA13+Y13+W13+U13+S13+Q13+O13+M13+K13 -> 2342887 | AG13: =+AF13/G13 -> 0.80585911 | AH13: =+AF13-G13 -> -564428.9 | AI13: =+AF13/C13-1 -> 0.02405675 | AJ13: =+C13/B13 -> 0.057045662 | AK13: =+AF13/E13 -> 0.066115381 | AL13: =+E13/B13-1 -> -0.11642353 | AO13: =+F13 -> 46032 | AP13: =Tabla2[[#This Row],[Web + APP 2025]]+Tabla2[[#This Row],[Afiliados 2025]]+Tabla2[[#This Row],[TMK 2025]]+Tabla2[[#This Row],[WA 2025]]+Tabla2[[#This Row],[Ent. en Tienda 2025]] -> 1735933.8 | AQ13: =Tabla2[[#This Row],[Meli Drop 2025]]+Tabla2[[#This Row],[Meli Full 2025]]+Tabla2[[#This Row],[Amazon Drop 2025]]+Tabla2[[#This Row],[Amazon Full 2025]]+Tabla2[[#This Row],[TikTok 2025]]+Tabla2[[#This Row],[Shein 2025]] -> 551915 | AR13: =Tabla2[[#This Row],[Web + APP 2026]]+Tabla2[[#This Row],[Afiliados 2026]]+Tabla2[[#This Row],[TMK 2026]]+Tabla2[[#This Row],[WA 2026]]+Tabla2[[#This Row],[Ent. en Tienda 2026]] -> 1705005 | AS13: =Tabla2[[#This Row],[Meli Drop 2026]]+Tabla2[[#This Row],[Meli Full 2026]]+Tabla2[[#This Row],[Amazon Drop 2026]]+Tabla2[[#This Row],[Amazon Full 2026]]+Tabla2[[#This Row],[TikTok 2026]]+Tabla2[[#This Row],[Shein 2026]] -> 637882 | AT13: =+AR13/AP13-1 -> -0.017816805 | AU13: =+AS13/AQ13-1 -> 0.1557613 | AV13: =+H13 -> 2742553.5 | AW13: =+I13 -> 164762.44 | AX13: =+AR13/AV13 -> 0.62168524 | AY13: =+AS13/AW13 -> 3.8715257 | AZ13: =+(AR13+AS13)/(AV13+AW13) -> 0.80585911 | BA13: 0.00738845 | BB13: 0.031258887 | BC13: =+AR13-AV13 -> -1037548.5 | BD13: =+AS13-AW13 -> 473119.56
A14: 45669 | B14: 41530429 | C14: =+J14+L14+N14+P14+R14+T14+V14+X14+Z14+AB14+AD14 -> 2885246.1 | D14: =+Tabla22[[#This Row],[Share diario]] -> 0.026563364 | E14: =+Tabla22[[#This Row],[Global 2026]] -> 37766104 | F14: 46033 | G14: =+H14+I14 -> 2924099.1 | H14: 2213442.9 | I14: 710656.22 | J14: 2046304 | K14: 1877762 | L14: 27737.069 | M14: =16709+13239 -> 29948 | N14: 14675 | O14: -1145 | P14: -1465 | Q14: 2935 | R14: 85731 | S14: 32600 | T14: 581035 | U14: 182133 | V14: 51721 | W14: 111049 | X14: 79508 | Y14: 31695 | Z14: 0 | AA14: 9041 | AB14: 0 | AC14: 1612 | AD14: 0 | AE14: 947 | AF14: =+AE14+AC14+AA14+Y14+W14+U14+S14+Q14+O14+M14+K14 -> 2278577 | AG14: =+AF14/G14 -> 0.77924068 | AH14: =+AF14-G14 -> -645522.14 | AI14: =+AF14/C14-1 -> -0.21026597 | AJ14: =+C14/B14 -> 0.069473062 | AK14: =+AF14/E14 -> 0.060333917 | AL14: =+E14/B14-1 -> -0.090640167 | AO14: =+F14 -> 46033 | AP14: =Tabla2[[#This Row],[Web + APP 2025]]+Tabla2[[#This Row],[Afiliados 2025]]+Tabla2[[#This Row],[TMK 2025]]+Tabla2[[#This Row],[WA 2025]]+Tabla2[[#This Row],[Ent. en Tienda 2025]] -> 2172982.1 | AQ14: =Tabla2[[#This Row],[Meli Drop 2025]]+Tabla2[[#This Row],[Meli Full 2025]]+Tabla2[[#This Row],[Amazon Drop 2025]]+Tabla2[[#This Row],[Amazon Full 2025]]+Tabla2[[#This Row],[TikTok 2025]]+Tabla2[[#This Row],[Shein 2025]] -> 712264 | AR14: =Tabla2[[#This Row],[Web + APP 2026]]+Tabla2[[#This Row],[Afiliados 2026]]+Tabla2[[#This Row],[TMK 2026]]+Tabla2[[#This Row],[WA 2026]]+Tabla2[[#This Row],[Ent. en Tienda 2026]] -> 1942100 | AS14: =Tabla2[[#This Row],[Meli Drop 2026]]+Tabla2[[#This Row],[Meli Full 2026]]+Tabla2[[#This Row],[Amazon Drop 2026]]+Tabla2[[#This Row],[Amazon Full 2026]]+Tabla2[[#This Row],[TikTok 2026]]+Tabla2[[#This Row],[Shein 2026]] -> 336477 | AT14: =+AR14/AP14-1 -> -0.10625125 | AU14: =+AS14/AQ14-1 -> -0.52759511 | AV14: =+H14 -> 2213442.9 | AW14: =+I14 -> 710656.22 | AX14: =+AR14/AV14 -> 0.87741138 | AY14: =+AS14/AW14 -> 0.47347365 | AZ14: =+(AR14+AS14)/(AV14+AW14) -> 0.77924068 | BA14: 0.031867992 | BB14: 0.025228227 | BC14: =+AR14-AV14 -> -271342.91 | BD14: =+AS14-AW14 -> -374179.22
A15: 45670 | B15: 25137619 | C15: =+J15+L15+N15+P15+R15+T15+V15+X15+Z15+AB15+AD15 -> 4228309.2 | D15: =+Tabla22[[#This Row],[Share diario]] -> 0.033499523 | E15: =+Tabla22[[#This Row],[Global 2026]] -> 22002628 | F15: 46034 | G15: =+H15+I15 -> 3687836.2 | H15: 2770711.5 | I15: 917124.64 | J15: 2797894 | K15: 2815225 | L15: 21892.241 | M15: =15551+12840 -> 28391 | N15: 62339 | O15: 25098 | P15: 7660 | Q15: 689 | R15: 57950 | S15: 78900 | T15: 1124689 | U15: 1028542 | V15: 34111 | W15: 130772 | X15: 121774 | Y15: 38266 | Z15: 0 | AA15: 9160 | AB15: 0 | AC15: 15529 | AD15: 0 | AE15: 0 | AF15: =+AE15+AC15+AA15+Y15+W15+U15+S15+Q15+O15+M15+K15 -> 4170572 | AG15: =+AF15/G15 -> 1.1308995 | AH15: =+AF15-G15 -> 482735.84 | AI15: =+AF15/C15-1 -> -0.013654924 | AJ15: =+C15/B15 -> 0.16820643 | AK15: =+AF15/E15 -> 0.18954881 | AL15: =+E15/B15-1 -> -0.12471312 | AO15: =+F15 -> 46034 | AP15: =Tabla2[[#This Row],[Web + APP 2025]]+Tabla2[[#This Row],[Afiliados 2025]]+Tabla2[[#This Row],[TMK 2025]]+Tabla2[[#This Row],[WA 2025]]+Tabla2[[#This Row],[Ent. en Tienda 2025]] -> 2947735.2 | AQ15: =Tabla2[[#This Row],[Meli Drop 2025]]+Tabla2[[#This Row],[Meli Full 2025]]+Tabla2[[#This Row],[Amazon Drop 2025]]+Tabla2[[#This Row],[Amazon Full 2025]]+Tabla2[[#This Row],[TikTok 2025]]+Tabla2[[#This Row],[Shein 2025]] -> 1280574 | AR15: =Tabla2[[#This Row],[Web + APP 2026]]+Tabla2[[#This Row],[Afiliados 2026]]+Tabla2[[#This Row],[TMK 2026]]+Tabla2[[#This Row],[WA 2026]]+Tabla2[[#This Row],[Ent. en Tienda 2026]] -> 2948303 | AS15: =Tabla2[[#This Row],[Meli Drop 2026]]+Tabla2[[#This Row],[Meli Full 2026]]+Tabla2[[#This Row],[Amazon Drop 2026]]+Tabla2[[#This Row],[Amazon Full 2026]]+Tabla2[[#This Row],[TikTok 2026]]+Tabla2[[#This Row],[Shein 2026]] -> 1222269 | AT15: =+AR15/AP15-1 -> 0.00019260842 | AU15: =+AS15/AQ15-1 -> -0.045530364 | AV15: =+H15 -> 2770711.5 | AW15: =+I15 -> 917124.64 | AX15: =+AR15/AV15 -> 1.064096 | AY15: =+AS15/AW15 -> 1.3327185 | AZ15: =+(AR15+AS15)/(AV15+AW15) -> 1.1308995 | BA15: 0.041126665 | BB15: 0.031579825 | BC15: =+AR15-AV15 -> 177591.48 | BD15: =+AS15-AW15 -> 305144.36
A16: 45671 | B16: 26929672 | C16: =+J16+L16+N16+P16+R16+T16+V16+X16+Z16+AB16+AD16 -> 4051721.8 | D16: =+Tabla22[[#This Row],[Share diario]] -> 0.049093331 | E16: =+Tabla22[[#This Row],[Global 2026]] -> 24135120 | F16: 46035 | G16: =+H16+I16 -> 5407470 | H16: 3758578.6 | I16: 1648891.4 | J16: 3014987 | K16: 3308864 | L16: 25132.759 | M16: =16835+12441 -> 29276 | N16: 88823 | O16: 24647 | P16: 264 | Q16: 3108 | R16: 76057 | S16: 43565 | T16: 657218 | U16: 536006 | V16: 100302 | W16: 110255 | X16: 88938 | Y16: 39605 | Z16: 0 | AA16: 8501 | AB16: 0 | AC16: 11906 | AD16: 0 | AE16: 0 | AF16: =+AE16+AC16+AA16+Y16+W16+U16+S16+Q16+O16+M16+K16 -> 4115733 | AG16: =+AF16/G16 -> 0.76111989 | AH16: =+AF16-G16 -> -1291737 | AI16: =+AF16/C16-1 -> 0.015798528 | AJ16: =+C16/B16 -> 0.15045567 | AK16: =+AF16/E16 -> 0.1705288 | AL16: =+E16/B16-1 -> -0.10377223 | AO16: =+F16 -> 46035 | AP16: =Tabla2[[#This Row],[Web + APP 2025]]+Tabla2[[#This Row],[Afiliados 2025]]+Tabla2[[#This Row],[TMK 2025]]+Tabla2[[#This Row],[WA 2025]]+Tabla2[[#This Row],[Ent. en Tienda 2025]] -> 3205263.8 | AQ16: =Tabla2[[#This Row],[Meli Drop 2025]]+Tabla2[[#This Row],[Meli Full 2025]]+Tabla2[[#This Row],[Amazon Drop 2025]]+Tabla2[[#This Row],[Amazon Full 2025]]+Tabla2[[#This Row],[TikTok 2025]]+Tabla2[[#This Row],[Shein 2025]] -> 846458 | AR16: =Tabla2[[#This Row],[Web + APP 2026]]+Tabla2[[#This Row],[Afiliados 2026]]+Tabla2[[#This Row],[TMK 2026]]+Tabla2[[#This Row],[WA 2026]]+Tabla2[[#This Row],[Ent. en Tienda 2026]] -> 3409460 | AS16: =Tabla2[[#This Row],[Meli Drop 2026]]+Tabla2[[#This Row],[Meli Full 2026]]+Tabla2[[#This Row],[Amazon Drop 2026]]+Tabla2[[#This Row],[Amazon Full 2026]]+Tabla2[[#This Row],[TikTok 2026]]+Tabla2[[#This Row],[Shein 2026]] -> 706273 | AT16: =+AR16/AP16-1 -> 0.063706533 | AU16: =+AS16/AQ16-1 -> -0.16561365 | AV16: =+H16 -> 3758578.6 | AW16: =+I16 -> 1648891.4 | AX16: =+AR16/AV16 -> 0.90711418 | AY16: =+AS16/AW16 -> 0.42833204 | AZ16: =+(AR16+AS16)/(AV16+AW16) -> 0.76111989 | BA16: 0.073941317 | BB16: 0.042839268 | BC16: =+AR16-AV16 -> -349118.64 | BD16: =+AS16-AW16 -> -942618.38
A17: 45672 | B17: 30377124 | C17: =+J17+L17+N17+P17+R17+T17+V17+X17+Z17+AB17+AD17 -> 4027205.9 | D17: =+Tabla22[[#This Row],[Share diario]] -> 0.04704304 | E17: =+Tabla22[[#This Row],[Global 2026]] -> 26317522 | F17: 46036 | G17: =+H17+I17 -> 5176861.8 | H17: 4086946.4 | I17: 1089915.4 | J17: 3145541 | K17: 3212173 | L17: 28275.862 | M17: =15827+12102 -> 27929 | N17: 68859 | O17: 49002 | P17: 5179 | Q17: 2343 | R17: 64024 | S17: 31865 | T17: 635340 | U17: 514044 | V17: 1022 | W17: 119118 | X17: 78965 | Y17: 41245 | Z17: 0 | AA17: 5948 | AB17: 0 | AC17: 15693 | AD17: 0 | AE17: 0 | AF17: =+AE17+AC17+AA17+Y17+W17+U17+S17+Q17+O17+M17+K17 -> 4019360 | AG17: =+AF17/G17 -> 0.7764086 | AH17: =+AF17-G17 -> -1157501.8 | AI17: =+AF17/C17-1 -> -0.0019482148 | AJ17: =+C17/B17 -> 0.13257364 | AK17: =+AF17/E17 -> 0.15272563 | AL17: =+E17/B17-1 -> -0.1336401 | AO17: =+F17 -> 46036 | AP17: =Tabla2[[#This Row],[Web + APP 2025]]+Tabla2[[#This Row],[Afiliados 2025]]+Tabla2[[#This Row],[TMK 2025]]+Tabla2[[#This Row],[WA 2025]]+Tabla2[[#This Row],[Ent. en Tienda 2025]] -> 3311878.9 | AQ17: =Tabla2[[#This Row],[Meli Drop 2025]]+Tabla2[[#This Row],[Meli Full 2025]]+Tabla2[[#This Row],[Amazon Drop 2025]]+Tabla2[[#This Row],[Amazon Full 2025]]+Tabla2[[#This Row],[TikTok 2025]]+Tabla2[[#This Row],[Shein 2025]] -> 715327 | AR17: =Tabla2[[#This Row],[Web + APP 2026]]+Tabla2[[#This Row],[Afiliados 2026]]+Tabla2[[#This Row],[TMK 2026]]+Tabla2[[#This Row],[WA 2026]]+Tabla2[[#This Row],[Ent. en Tienda 2026]] -> 3323312 | AS17: =Tabla2[[#This Row],[Meli Drop 2026]]+Tabla2[[#This Row],[Meli Full 2026]]+Tabla2[[#This Row],[Amazon Drop 2026]]+Tabla2[[#This Row],[Amazon Full 2026]]+Tabla2[[#This Row],[TikTok 2026]]+Tabla2[[#This Row],[Shein 2026]] -> 696048 | AT17: =+AR17/AP17-1 -> 0.0034521607 | AU17: =+AS17/AQ17-1 -> -0.02695131 | AV17: =+H17 -> 4086946.4 | AW17: =+I17 -> 1089915.4 | AX17: =+AR17/AV17 -> 0.81315282 | AY17: =+AS17/AW17 -> 0.63862573 | AZ17: =+(AR17+AS17)/(AV17+AW17) -> 0.7764086 | BA17: 0.048875129 | BB17: 0.046581916 | BC17: =+AR17-AV17 -> -763634.39 | BD17: =+AS17-AW17 -> -393867.38
A18: 45673 | B18: 34401698 | C18: =+J18+L18+N18+P18+R18+T18+V18+X18+Z18+AB18+AD18 -> 3965940.8 | D18: =+Tabla22[[#This Row],[Share diario]] -> 0.046758395 | E18: =+Tabla22[[#This Row],[Global 2026]] -> 30903967 | F18: 46037 | G18: =+H18+I18 -> 5143957.1 | H18: 4222888.5 | I18: 921068.62 | J18: 2652789 | K18: 2833552 | L18: 24219.828 | M18: =21233+15198 -> 36431 | N18: 86898 | O18: 39316 | P18: 9752 | Q18: 1033 | R18: 63370 | S18: 49218 | T18: 467016 | U18: 512619 | V18: 578857 | W18: 120851 | X18: 83039 | Y18: 38749 | Z18: 0 | AA18: 11568 | AB18: 0 | AC18: 6953 | AD18: 0 | AE18: 947 | AF18: =+AE18+AC18+AA18+Y18+W18+U18+S18+Q18+O18+M18+K18 -> 3651237 | AG18: =+AF18/G18 -> 0.70981094 | AH18: =+AF18-G18 -> -1492720.1 | AI18: =+AF18/C18-1 -> -0.07935162 | AJ18: =+C18/B18 -> 0.11528329 | AK18: =+AF18/E18 -> 0.11814784 | AL18: =+E18/B18-1 -> -0.10167321 | AO18: =+F18 -> 46037 | AP18: =Tabla2[[#This Row],[Web + APP 2025]]+Tabla2[[#This Row],[Afiliados 2025]]+Tabla2[[#This Row],[TMK 2025]]+Tabla2[[#This Row],[WA 2025]]+Tabla2[[#This Row],[Ent. en Tienda 2025]] -> 2837028.8 | AQ18: =Tabla2[[#This Row],[Meli Drop 2025]]+Tabla2[[#This Row],[Meli Full 2025]]+Tabla2[[#This Row],[Amazon Drop 2025]]+Tabla2[[#This Row],[Amazon Full 2025]]+Tabla2[[#This Row],[TikTok 2025]]+Tabla2[[#This Row],[Shein 2025]] -> 1128912 | AR18: =Tabla2[[#This Row],[Web + APP 2026]]+Tabla2[[#This Row],[Afiliados 2026]]+Tabla2[[#This Row],[TMK 2026]]+Tabla2[[#This Row],[WA 2026]]+Tabla2[[#This Row],[Ent. en Tienda 2026]] -> 2959550 | AS18: =Tabla2[[#This Row],[Meli Drop 2026]]+Tabla2[[#This Row],[Meli Full 2026]]+Tabla2[[#This Row],[Amazon Drop 2026]]+Tabla2[[#This Row],[Amazon Full 2026]]+Tabla2[[#This Row],[TikTok 2026]]+Tabla2[[#This Row],[Shein 2026]] -> 691687 | AT18: =+AR18/AP18-1 -> 0.043186439 | AU18: =+AS18/AQ18-1 -> -0.38729768 | AV18: =+H18 -> 4222888.5 | AW18: =+I18 -> 921068.62 | AX18: =+AR18/AV18 -> 0.70083546 | AY18: =+AS18/AW18 -> 0.75096142 | AZ18: =+(AR18+AS18)/(AV18+AW18) -> 0.70981094 | BA18: 0.041303525 | BB18: 0.048131347 | BC18: =+AR18-AV18 -> -1263338.5 | BD18: =+AS18-AW18 -> -229381.62
A19: 45674 | B19: 33022574 | C19: =+J19+L19+N19+P19+R19+T19+V19+X19+Z19+AB19+AD19 -> 2433095.3 | D19: =+Tabla22[[#This Row],[Share diario]] -> 0.046047069 | E19: =+Tabla22[[#This Row],[Global 2026]] -> 32703579 | F19: 46038 | G19: =+H19+I19 -> 5071028.4 | H19: 3617419.8 | I19: 1453608.5 | J19: 1736223 | K19: 2640237 | L19: 19429.31 | M19: =19101+16772 -> 35873 | N19: 37364 | O19: -6459 | P19: 4728 | Q19: 3002 | R19: 83214 | S19: 52074 | T19: 307736 | U19: 435351 | V19: 197102 | W19: 150561 | X19: 47299 | Y19: 53754 | Z19: 0 | AA19: 6324 | AB19: 0 | AC19: 8858 | AD19: 0 | AE19: 947 | AF19: =+AE19+AC19+AA19+Y19+W19+U19+S19+Q19+O19+M19+K19 -> 3380522 | AG19: =+AF19/G19 -> 0.66663441 | AH19: =+AF19-G19 -> -1690506.4 | AI19: =+AF19/C19-1 -> 0.38939152 | AJ19: =+C19/B19 -> 0.073679759 | AK19: =+AF19/E19 -> 0.10336856 | AL19: =+E19/B19-1 -> -0.0096599072 | AO19: =+F19 -> 46038 | AP19: =Tabla2[[#This Row],[Web + APP 2025]]+Tabla2[[#This Row],[Afiliados 2025]]+Tabla2[[#This Row],[TMK 2025]]+Tabla2[[#This Row],[WA 2025]]+Tabla2[[#This Row],[Ent. en Tienda 2025]] -> 1880958.3 | AQ19: =Tabla2[[#This Row],[Meli Drop 2025]]+Tabla2[[#This Row],[Meli Full 2025]]+Tabla2[[#This Row],[Amazon Drop 2025]]+Tabla2[[#This Row],[Amazon Full 2025]]+Tabla2[[#This Row],[TikTok 2025]]+Tabla2[[#This Row],[Shein 2025]] -> 552137 | AR19: =Tabla2[[#This Row],[Web + APP 2026]]+Tabla2[[#This Row],[Afiliados 2026]]+Tabla2[[#This Row],[TMK 2026]]+Tabla2[[#This Row],[WA 2026]]+Tabla2[[#This Row],[Ent. en Tienda 2026]] -> 2724727 | AS19: =Tabla2[[#This Row],[Meli Drop 2026]]+Tabla2[[#This Row],[Meli Full 2026]]+Tabla2[[#This Row],[Amazon Drop 2026]]+Tabla2[[#This Row],[Amazon Full 2026]]+Tabla2[[#This Row],[TikTok 2026]]+Tabla2[[#This Row],[Shein 2026]] -> 655795 | AT19: =+AR19/AP19-1 -> 0.44858447 | AU19: =+AS19/AQ19-1 -> 0.18773964 | AV19: =+H19 -> 3617419.8 | AW19: =+I19 -> 1453608.5 | AX19: =+AR19/AV19 -> 0.75322388 | AY19: =+AS19/AW19 -> 0.45114967 | AZ19: =+(AR19+AS19)/(AV19+AW19) -> 0.66663441 | BA19: 0.065184238 | BB19: 0.041230378 | BC19: =+AR19-AV19 -> -892692.85 | BD19: =+AS19-AW19 -> -797813.51
A20: 45675 | B20: 45210881 | C20: =+J20+L20+N20+P20+R20+T20+V20+X20+Z20+AB20+AD20 -> 3363106 | D20: =+Tabla22[[#This Row],[Share diario]] -> 0.028249768 | E20: =+Tabla22[[#This Row],[Global 2026]] -> 45086574 | F20: 46039 | G20: =+H20+I20 -> 3109301.9 | H20: 2398359.8 | I20: 710942.08 | J20: 2580220 | K20: 2128824 | L20: 28300 | M20: =23452+18396 -> 41848 | N20: 17517 | O20: 39673 | P20: 6155 | Q20: 3597 | R20: 63991 | S20: 57603 | T20: 488099 | U20: 457229 | V20: 140441 | W20: 118233 | X20: 38383 | Y20: 37402 | Z20: 0 | AA20: 6671 | AB20: 0 | AC20: 930 | AD20: 0 | AE20: 0 | AF20: =+AE20+AC20+AA20+Y20+W20+U20+S20+Q20+O20+M20+K20 -> 2892010 | AG20: =+AF20/G20 -> 0.93011554 | AH20: =+AF20-G20 -> -217291.89 | AI20: =+AF20/C20-1 -> -0.14007765 | AJ20: =+C20/B20 -> 0.074387093 | AK20: =+AF20/E20 -> 0.064143485 | AL20: =+E20/B20-1 -> -0.002749493 | AO20: =+F20 -> 46039 | AP20: =Tabla2[[#This Row],[Web + APP 2025]]+Tabla2[[#This Row],[Afiliados 2025]]+Tabla2[[#This Row],[TMK 2025]]+Tabla2[[#This Row],[WA 2025]]+Tabla2[[#This Row],[Ent. en Tienda 2025]] -> 2696183 | AQ20: =Tabla2[[#This Row],[Meli Drop 2025]]+Tabla2[[#This Row],[Meli Full 2025]]+Tabla2[[#This Row],[Amazon Drop 2025]]+Tabla2[[#This Row],[Amazon Full 2025]]+Tabla2[[#This Row],[TikTok 2025]]+Tabla2[[#This Row],[Shein 2025]] -> 666923 | AR20: =Tabla2[[#This Row],[Web + APP 2026]]+Tabla2[[#This Row],[Afiliados 2026]]+Tabla2[[#This Row],[TMK 2026]]+Tabla2[[#This Row],[WA 2026]]+Tabla2[[#This Row],[Ent. en Tienda 2026]] -> 2271545 | AS20: =Tabla2[[#This Row],[Meli Drop 2026]]+Tabla2[[#This Row],[Meli Full 2026]]+Tabla2[[#This Row],[Amazon Drop 2026]]+Tabla2[[#This Row],[Amazon Full 2026]]+Tabla2[[#This Row],[TikTok 2026]]+Tabla2[[#This Row],[Shein 2026]] -> 620465 | AT20: =+AR20/AP20-1 -> -0.15749599 | AU20: =+AS20/AQ20-1 -> -0.069660216 | AV20: =+H20 -> 2398359.8 | AW20: =+I20 -> 710942.08 | AX20: =+AR20/AV20 -> 0.94712436 | AY20: =+AS20/AW20 -> 0.87273636 | AZ20: =+(AR20+AS20)/(AV20+AW20) -> 0.93011554 | BA20: 0.031880811 | BB20: 0.02733586 | BC20: =+AR20-AV20 -> -126814.81 | BD20: =+AS20-AW20 -> -90477.076
A21: 45676 | B21: 42397530 | C21: =+J21+L21+N21+P21+R21+T21+V21+X21+Z21+AB21+AD21 -> 2564263.8 | D21: =+Tabla22[[#This Row],[Share diario]] -> 0.039047777 | E21: =+Tabla22[[#This Row],[Global 2026]] -> 44463837 | F21: 46040 | G21: =+H21+I21 -> 4296573.8 | H21: 3437831.1 | I21: 858742.71 | J21: 2028149 | K21: 2552466 | L21: 25069.828 | M21: =20869+16163 -> 37032 | N21: 22533 | O21: -1059 | P21: 9941 | Q21: 2557 | R21: 65234 | S21: 43820 | T21: 193047 | U21: 167676 | V21: 170098 | W21: 113618 | X21: 50192 | Y21: 53156 | Z21: 0 | AA21: 3354 | AB21: 0 | AC21: 586 | AD21: 0 | AE21: 0 | AF21: =+AE21+AC21+AA21+Y21+W21+U21+S21+Q21+O21+M21+K21 -> 2973206 | AG21: =+AF21/G21 -> 0.69199463 | AH21: =+AF21-G21 -> -1323367.8 | AI21: =+AF21/C21-1 -> 0.15947742 | AJ21: =+C21/B21 -> 0.060481444 | AK21: =+AF21/E21 -> 0.066867958 | AL21: =+E21/B21-1 -> 0.048736495 | AO21: =+F21 -> 46040 | AP21: =Tabla2[[#This Row],[Web + APP 2025]]+Tabla2[[#This Row],[Afiliados 2025]]+Tabla2[[#This Row],[TMK 2025]]+Tabla2[[#This Row],[WA 2025]]+Tabla2[[#This Row],[Ent. en Tienda 2025]] -> 2150926.8 | AQ21: =Tabla2[[#This Row],[Meli Drop 2025]]+Tabla2[[#This Row],[Meli Full 2025]]+Tabla2[[#This Row],[Amazon Drop 2025]]+Tabla2[[#This Row],[Amazon Full 2025]]+Tabla2[[#This Row],[TikTok 2025]]+Tabla2[[#This Row],[Shein 2025]] -> 413337 | AR21: =Tabla2[[#This Row],[Web + APP 2026]]+Tabla2[[#This Row],[Afiliados 2026]]+Tabla2[[#This Row],[TMK 2026]]+Tabla2[[#This Row],[WA 2026]]+Tabla2[[#This Row],[Ent. en Tienda 2026]] -> 2634816 | AS21: =Tabla2[[#This Row],[Meli Drop 2026]]+Tabla2[[#This Row],[Meli Full 2026]]+Tabla2[[#This Row],[Amazon Drop 2026]]+Tabla2[[#This Row],[Amazon Full 2026]]+Tabla2[[#This Row],[TikTok 2026]]+Tabla2[[#This Row],[Shein 2026]] -> 338390 | AT21: =+AR21/AP21-1 -> 0.22496775 | AU21: =+AS21/AQ21-1 -> -0.18132178 | AV21: =+H21 -> 3437831.1 | AW21: =+I21 -> 858742.71 | AX21: =+AR21/AV21 -> 0.76641811 | AY21: =+AS21/AW21 -> 0.39405284 | AZ21: =+(AR21+AS21)/(AV21+AW21) -> 0.69199463 | BA21: 0.038508642 | BB21: 0.039183474 | BC21: =+AR21-AV21 -> -803015.08 | BD21: =+AS21-AW21 -> -520352.71
A22: 45677 | B22: 24310022 | C22: =+J22+L22+N22+P22+R22+T22+V22+X22+Z22+AB22+AD22 -> 3939989.7 | D22: =+Tabla22[[#This Row],[Share diario]] -> 0.029772717 | E22: =+Tabla22[[#This Row],[Global 2026]] -> 25877600 | F22: 46041 | G22: =+H22+I22 -> 3274810 | H22: 2742589.5 | I22: 532220.56 | J22: 3051836 | K22: 3650682 | L22: 24870.69 | M22: =16838+12441 -> 29279 | N22: 62489 | O22: 39416 | P22: 2112 | Q22: 1876 | R22: 23575 | S22: 66465 | T22: 601975 | U22: 827888 | V22: 119622 | W22: 129619 | X22: 47661 | Y22: 40872 | Z22: 5849 | AA22: 7344 | AB22: 0 | AC22: 6161 | AD22: 0 | AE22: 861 | AF22: =+AE22+AC22+AA22+Y22+W22+U22+S22+Q22+O22+M22+K22 -> 4800463 | AG22: =+AF22/G22 -> 1.4658753 | AH22: =+AF22-G22 -> 1525653 | AI22: =+AF22/C22-1 -> 0.21839481 | AJ22: =+C22/B22 -> 0.16207265 | AK22: =+AF22/E22 -> 0.1855065 | AL22: =+E22/B22-1 -> 0.064482788 | AO22: =+F22 -> 46041 | AP22: =Tabla2[[#This Row],[Web + APP 2025]]+Tabla2[[#This Row],[Afiliados 2025]]+Tabla2[[#This Row],[TMK 2025]]+Tabla2[[#This Row],[WA 2025]]+Tabla2[[#This Row],[Ent. en Tienda 2025]] -> 3164882.7 | AQ22: =Tabla2[[#This Row],[Meli Drop 2025]]+Tabla2[[#This Row],[Meli Full 2025]]+Tabla2[[#This Row],[Amazon Drop 2025]]+Tabla2[[#This Row],[Amazon Full 2025]]+Tabla2[[#This Row],[TikTok 2025]]+Tabla2[[#This Row],[Shein 2025]] -> 775107 | AR22: =Tabla2[[#This Row],[Web + APP 2026]]+Tabla2[[#This Row],[Afiliados 2026]]+Tabla2[[#This Row],[TMK 2026]]+Tabla2[[#This Row],[WA 2026]]+Tabla2[[#This Row],[Ent. en Tienda 2026]] -> 3787718 | AS22: =Tabla2[[#This Row],[Meli Drop 2026]]+Tabla2[[#This Row],[Meli Full 2026]]+Tabla2[[#This Row],[Amazon Drop 2026]]+Tabla2[[#This Row],[Amazon Full 2026]]+Tabla2[[#This Row],[TikTok 2026]]+Tabla2[[#This Row],[Shein 2026]] -> 1012745 | AT22: =+AR22/AP22-1 -> 0.1967957 | AU22: =+AS22/AQ22-1 -> 0.30658735 | AV22: =+H22 -> 2742589.5 | AW22: =+I22 -> 532220.56 | AX22: =+AR22/AV22 -> 1.3810736 | AY22: =+AS22/AW22 -> 1.9028671 | AZ22: =+(AR22+AS22)/(AV22+AW22) -> 1.4658753 | BA22: 0.023866393 | BB22: 0.031259297 | BC22: =+AR22-AV22 -> 1045128.5 | BD22: =+AS22-AW22 -> 480524.44
A23: 45678 | B23: 25280575 | C23: =+J23+L23+N23+P23+R23+T23+V23+X23+Z23+AB23+AD23 -> 4126281 | D23: =+Tabla22[[#This Row],[Share diario]] -> 0.04574576 | E23: =+Tabla22[[#This Row],[Global 2026]] -> 26671750 | F23: 46042 | G23: =+H23+I23 -> 5033500 | H23: 4035457.6 | I23: 998042.48 | J23: 2969811 | K23: 3539014 | L23: 20875 | M23: =16964+18297 -> 35261 | N23: 56684 | O23: 50393 | P23: 6612 | Q23: 1403 | R23: 40784 | S23: 82775 | T23: 884541 | U23: 541048 | V23: 85285 | W23: 103829 | X23: 44091 | Y23: 59350 | Z23: 17598 | AA23: 5233 | AB23: 0 | AC23: 8443 | AD23: 0 | AE23: 0 | AF23: =+AE23+AC23+AA23+Y23+W23+U23+S23+Q23+O23+M23+K23 -> 4426749 | AG23: =+AF23/G23 -> 0.87945743 | AH23: =+AF23-G23 -> -606751.05 | AI23: =+AF23/C23-1 -> 0.072818114 | AJ23: =+C23/B23 -> 0.16321943 | AK23: =+AF23/E23 -> 0.16597145 | AL23: =+E23/B23-1 -> 0.055029405 | AO23: =+F23 -> 46042 | AP23: =Tabla2[[#This Row],[Web + APP 2025]]+Tabla2[[#This Row],[Afiliados 2025]]+Tabla2[[#This Row],[TMK 2025]]+Tabla2[[#This Row],[WA 2025]]+Tabla2[[#This Row],[Ent. en Tienda 2025]] -> 3094766 | AQ23: =Tabla2[[#This Row],[Meli Drop 2025]]+Tabla2[[#This Row],[Meli Full 2025]]+Tabla2[[#This Row],[Amazon Drop 2025]]+Tabla2[[#This Row],[Amazon Full 2025]]+Tabla2[[#This Row],[TikTok 2025]]+Tabla2[[#This Row],[Shein 2025]] -> 1031515 | AR23: =Tabla2[[#This Row],[Web + APP 2026]]+Tabla2[[#This Row],[Afiliados 2026]]+Tabla2[[#This Row],[TMK 2026]]+Tabla2[[#This Row],[WA 2026]]+Tabla2[[#This Row],[Ent. en Tienda 2026]] -> 3708846 | AS23: =Tabla2[[#This Row],[Meli Drop 2026]]+Tabla2[[#This Row],[Meli Full 2026]]+Tabla2[[#This Row],[Amazon Drop 2026]]+Tabla2[[#This Row],[Amazon Full 2026]]+Tabla2[[#This Row],[TikTok 2026]]+Tabla2[[#This Row],[Shein 2026]] -> 717903 | AT23: =+AR23/AP23-1 -> 0.19842534 | AU23: =+AS23/AQ23-1 -> -0.30403048 | AV23: =+H23 -> 4035457.6 | AW23: =+I23 -> 998042.48 | AX23: =+AR23/AV23 -> 0.91906455 | AY23: =+AS23/AW23 -> 0.71931107 | AZ23: =+(AR23+AS23)/(AV23+AW23) -> 0.87945743 | BA23: 0.044755268 | BB23: 0.04599506 | BC23: =+AR23-AV23 -> -326611.57 | BD23: =+AS23-AW23 -> -280139.48
A24: 45679 | B24: 27320349 | C24: =+J24+L24+N24+P24+R24+T24+V24+X24+Z24+AB24+AD24 -> 3467828.1 | D24: =+Tabla22[[#This Row],[Share diario]] -> 0.047908719 | E24: =+Tabla22[[#This Row],[Global 2026]] -> 28758026 | F24: 46043 | G24: =+H24+I24 -> 5274251.9 | H24: 3946053.6 | I24: 1328198.3 | J24: 2805417 | K24: 3499850 | L24: 19287.069 | M24: =13419+17382 -> 30801 | N24: 90551 | O24: 35803 | P24: 1592 | Q24: 5841 | R24: 36254 | S24: 48687 | T24: 374553 | U24: 482866 | V24: 69855 | W24: 118197 | X24: 52088 | Y24: 45226 | Z24: 18231 | AA24: 2767 | AB24: 0 | AC24: 9702 | AD24: 0 | AE24: 0 | AF24: =+AE24+AC24+AA24+Y24+W24+U24+S24+Q24+O24+M24+K24 -> 4279740 | AG24: =+AF24/G24 -> 0.81144019 | AH24: =+AF24-G24 -> -994511.93 | AI24: =+AF24/C24-1 -> 0.23412693 | AJ24: =+C24/B24 -> 0.12693206 | AK24: =+AF24/E24 -> 0.14881898 | AL24: =+E24/B24-1 -> 0.052622937 | AO24: =+F24 -> 46043 | AP24: =Tabla2[[#This Row],[Web + APP 2025]]+Tabla2[[#This Row],[Afiliados 2025]]+Tabla2[[#This Row],[TMK 2025]]+Tabla2[[#This Row],[WA 2025]]+Tabla2[[#This Row],[Ent. en Tienda 2025]] -> 2953101.1 | AQ24: =Tabla2[[#This Row],[Meli Drop 2025]]+Tabla2[[#This Row],[Meli Full 2025]]+Tabla2[[#This Row],[Amazon Drop 2025]]+Tabla2[[#This Row],[Amazon Full 2025]]+Tabla2[[#This Row],[TikTok 2025]]+Tabla2[[#This Row],[Shein 2025]] -> 514727 | AR24: =Tabla2[[#This Row],[Web + APP 2026]]+Tabla2[[#This Row],[Afiliados 2026]]+Tabla2[[#This Row],[TMK 2026]]+Tabla2[[#This Row],[WA 2026]]+Tabla2[[#This Row],[Ent. en Tienda 2026]] -> 3620982 | AS24: =Tabla2[[#This Row],[Meli Drop 2026]]+Tabla2[[#This Row],[Meli Full 2026]]+Tabla2[[#This Row],[Amazon Drop 2026]]+Tabla2[[#This Row],[Amazon Full 2026]]+Tabla2[[#This Row],[TikTok 2026]]+Tabla2[[#This Row],[Shein 2026]] -> 658758 | AT24: =+AR24/AP24-1 -> 0.22616257 | AU24: =+AS24/AQ24-1 -> 0.27982018 | AV24: =+H24 -> 3946053.6 | AW24: =+I24 -> 1328198.3 | AX24: =+AR24/AV24 -> 0.91762108 | AY24: =+AS24/AW24 -> 0.49597866 | AZ24: =+(AR24+AS24)/(AV24+AW24) -> 0.81144019 | BA24: 0.059560461 | BB24: 0.044976058 | BC24: =+AR24-AV24 -> -325071.64 | BD24: =+AS24-AW24 -> -669440.28
A25: 45680 | B25: 28863545 | C25: =+J25+L25+N25+P25+R25+T25+V25+X25+Z25+AB25+AD25 -> 2314941.4 | D25: =+Tabla22[[#This Row],[Share diario]] -> 0.040263666 | E25: =+Tabla22[[#This Row],[Global 2026]] -> 30590251 | F25: 46044 | G25: =+H25+I25 -> 4428192.7 | H25: 3765420.5 | I25: 662772.25 | J25: 1788443 | K25: 2626517 | L25: 22197.414 | M25: =13884+15409 -> 29293 | N25: 61174 | O25: 89330 | P25: 1316 | Q25: 878 | R25: 49423 | S25: 73394 | T25: 276672 | U25: 421869 | V25: 49661 | W25: 87416 | X25: 52812 | Y25: 44135 | Z25: 13243 | AA25: 5521 | AB25: 0 | AC25: 12903 | AD25: 0 | AE25: 0 | AF25: =+AE25+AC25+AA25+Y25+W25+U25+S25+Q25+O25+M25+K25 -> 3391256 | AG25: =+AF25/G25 -> 0.76583297 | AH25: =+AF25-G25 -> -1036936.7 | AI25: =+AF25/C25-1 -> 0.46494247 | AJ25: =+C25/B25 -> 0.080202949 | AK25: =+AF25/E25 -> 0.11086068 | AL25: =+E25/B25-1 -> 0.059823074 | AO25: =+F25 -> 46044 | AP25: =Tabla2[[#This Row],[Web + APP 2025]]+Tabla2[[#This Row],[Afiliados 2025]]+Tabla2[[#This Row],[TMK 2025]]+Tabla2[[#This Row],[WA 2025]]+Tabla2[[#This Row],[Ent. en Tienda 2025]] -> 1922553.4 | AQ25: =Tabla2[[#This Row],[Meli Drop 2025]]+Tabla2[[#This Row],[Meli Full 2025]]+Tabla2[[#This Row],[Amazon Drop 2025]]+Tabla2[[#This Row],[Amazon Full 2025]]+Tabla2[[#This Row],[TikTok 2025]]+Tabla2[[#This Row],[Shein 2025]] -> 392388 | AR25: =Tabla2[[#This Row],[Web + APP 2026]]+Tabla2[[#This Row],[Afiliados 2026]]+Tabla2[[#This Row],[TMK 2026]]+Tabla2[[#This Row],[WA 2026]]+Tabla2[[#This Row],[Ent. en Tienda 2026]] -> 2819412 | AS25: =Tabla2[[#This Row],[Meli Drop 2026]]+Tabla2[[#This Row],[Meli Full 2026]]+Tabla2[[#This Row],[Amazon Drop 2026]]+Tabla2[[#This Row],[Amazon Full 2026]]+Tabla2[[#This Row],[TikTok 2026]]+Tabla2[[#This Row],[Shein 2026]] -> 571844 | AT25: =+AR25/AP25-1 -> 0.46649346 | AU25: =+AS25/AQ25-1 -> 0.45734324 | AV25: =+H25 -> 3765420.5 | AW25: =+I25 -> 662772.25 | AX25: =+AR25/AV25 -> 0.74876419 | AY25: =+AS25/AW25 -> 0.86280619 | AZ25: =+(AR25+AS25)/(AV25+AW25) -> 0.76583297 | BA25: 0.029720729 | BB25: 0.04291725 | BC25: =+AR25-AV25 -> -946008.47 | BD25: =+AS25-AW25 -> -90928.251
A26: 45681 | B26: 31893984 | C26: =+J26+L26+N26+P26+R26+T26+V26+X26+Z26+AB26+AD26 -> 1982979.2 | D26: =+Tabla22[[#This Row],[Share diario]] -> 0.026877927 | E26: =+Tabla22[[#This Row],[Global 2026]] -> 31338795 | F26: 46045 | G26: =+H26+I26 -> 2956642.9 | H26: 2451396.6 | I26: 505246.23 | J26: 1462778 | K26: 2207677 | L26: 19311.207 | M26: =14447+12553 -> 27000 | N26: 70610 | O26: 50125 | P26: 2246 | Q26: 1962 | R26: 52560 | S26: 62478 | T26: 296224 | U26: 395456 | V26: 49215 | W26: 87113 | X26: 15576 | Y26: 29785 | Z26: 14459 | AA26: 3177 | AB26: 0 | AC26: 1034 | AD26: 0 | AE26: 947 | AF26: =+AE26+AC26+AA26+Y26+W26+U26+S26+Q26+O26+M26+K26 -> 2866754 | AG26: =+AF26/G26 -> 0.96959766 | AH26: =+AF26-G26 -> -89888.851 | AI26: =+AF26/C26-1 -> 0.44568031 | AJ26: =+C26/B26 -> 0.062174083 | AK26: =+AF26/E26 -> 0.091476204 | AL26: =+E26/B26-1 -> -0.017407327 | AO26: =+F26 -> 46045 | AP26: =Tabla2[[#This Row],[Web + APP 2025]]+Tabla2[[#This Row],[Afiliados 2025]]+Tabla2[[#This Row],[TMK 2025]]+Tabla2[[#This Row],[WA 2025]]+Tabla2[[#This Row],[Ent. en Tienda 2025]] -> 1607505.2 | AQ26: =Tabla2[[#This Row],[Meli Drop 2025]]+Tabla2[[#This Row],[Meli Full 2025]]+Tabla2[[#This Row],[Amazon Drop 2025]]+Tabla2[[#This Row],[Amazon Full 2025]]+Tabla2[[#This Row],[TikTok 2025]]+Tabla2[[#This Row],[Shein 2025]] -> 375474 | AR26: =Tabla2[[#This Row],[Web + APP 2026]]+Tabla2[[#This Row],[Afiliados 2026]]+Tabla2[[#This Row],[TMK 2026]]+Tabla2[[#This Row],[WA 2026]]+Tabla2[[#This Row],[Ent. en Tienda 2026]] -> 2349242 | AS26: =Tabla2[[#This Row],[Meli Drop 2026]]+Tabla2[[#This Row],[Meli Full 2026]]+Tabla2[[#This Row],[Amazon Drop 2026]]+Tabla2[[#This Row],[Amazon Full 2026]]+Tabla2[[#This Row],[TikTok 2026]]+Tabla2[[#This Row],[Shein 2026]] -> 517512 | AT26: =+AR26/AP26-1 -> 0.46142108 | AU26: =+AS26/AQ26-1 -> 0.37828984 | AV26: =+H26 -> 2451396.6 | AW26: =+I26 -> 505246.23 | AX26: =+AR26/AV26 -> 0.95832799 | AY26: =+AS26/AW26 -> 1.0242768 | AZ26: =+(AR26+AS26)/(AV26+AW26) -> 0.96959766 | BA26: 0.022656782 | BB26: 0.027940359 | BC26: =+AR26-AV26 -> -102154.62 | BD26: =+AS26-AW26 -> 12265.767
A27: 45682 | B27: 39679161 | C27: =+J27+L27+N27+P27+R27+T27+V27+X27+Z27+AB27+AD27 -> 1581235.5 | D27: =+Tabla22[[#This Row],[Share diario]] -> 0.023023637 | E27: =+Tabla22[[#This Row],[Global 2026]] -> 40446079 | F27: 46046 | G27: =+H27+I27 -> 2533154.5 | H27: 2049687 | I27: 483467.45 | J27: 1103959 | K27: 1954073 | L27: 21284.483 | M27: =17029+13804 -> 30833 | N27: 11116 | O27: 29064 | P27: 430 | Q27: 1720 | R27: 56626 | S27: 60413 | T27: 295266 | U27: 400858 | V27: 41484 | W27: 71989 | X27: 39494 | Y27: 36844 | Z27: 11576 | AA27: 3208 | AB27: 0 | AC27: 0 | AD27: 0 | AE27: 0 | AF27: =+AE27+AC27+AA27+Y27+W27+U27+S27+Q27+O27+M27+K27 -> 2589002 | AG27: =+AF27/G27 -> 1.0220466 | AH27: =+AF27-G27 -> 55847.508 | AI27: =+AF27/C27-1 -> 0.63732855 | AJ27: =+C27/B27 -> 0.039850527 | AK27: =+AF27/E27 -> 0.064011199 | AL27: =+E27/B27-1 -> 0.019327979 | AO27: =+F27 -> 46046 | AP27: =Tabla2[[#This Row],[Web + APP 2025]]+Tabla2[[#This Row],[Afiliados 2025]]+Tabla2[[#This Row],[TMK 2025]]+Tabla2[[#This Row],[WA 2025]]+Tabla2[[#This Row],[Ent. en Tienda 2025]] -> 1193415.5 | AQ27: =Tabla2[[#This Row],[Meli Drop 2025]]+Tabla2[[#This Row],[Meli Full 2025]]+Tabla2[[#This Row],[Amazon Drop 2025]]+Tabla2[[#This Row],[Amazon Full 2025]]+Tabla2[[#This Row],[TikTok 2025]]+Tabla2[[#This Row],[Shein 2025]] -> 387820 | AR27: =Tabla2[[#This Row],[Web + APP 2026]]+Tabla2[[#This Row],[Afiliados 2026]]+Tabla2[[#This Row],[TMK 2026]]+Tabla2[[#This Row],[WA 2026]]+Tabla2[[#This Row],[Ent. en Tienda 2026]] -> 2076103 | AS27: =Tabla2[[#This Row],[Meli Drop 2026]]+Tabla2[[#This Row],[Meli Full 2026]]+Tabla2[[#This Row],[Amazon Drop 2026]]+Tabla2[[#This Row],[Amazon Full 2026]]+Tabla2[[#This Row],[TikTok 2026]]+Tabla2[[#This Row],[Shein 2026]] -> 512899 | AT27: =+AR27/AP27-1 -> 0.73963136 | AU27: =+AS27/AQ27-1 -> 0.32251818 | AV27: =+H27 -> 2049687 | AW27: =+I27 -> 483467.45 | AX27: =+AR27/AV27 -> 1.0128878 | AY27: =+AS27/AW27 -> 1.060876 | AZ27: =+(AR27+AS27)/(AV27+AW27) -> 1.0220466 | BA27: 0.021680155 | BB27: 0.023361782 | BC27: =+AR27-AV27 -> 26415.954 | BD27: =+AS27-AW27 -> 29431.554
A28: 45683 | B28: 37710035 | C28: =+J28+L28+N28+P28+R28+T28+V28+X28+Z28+AB28+AD28 -> 1989044.2 | D28: =+Tabla22[[#This Row],[Share diario]] -> 0.018359139 | E28: =+Tabla22[[#This Row],[Global 2026]] -> 40762958 | F28: 46047 | G28: =+H28+I28 -> 2021056.7 | H28: 1521692.3 | I28: 499364.39 | J28: 1640079 | K28: 2194390 | L28: 18636.207 | M28: =16696+14416 -> 31112 | N28: 20959 | O28: 5527 | P28: 6107 | Q28: 1670 | R28: 42996 | S28: 80142 | T28: 181222 | U28: 329347 | V28: 38455 | W28: 91250 | X28: 33258 | Y28: 31562 | Z28: 7332 | AA28: 3487 | AB28: 0 | AC28: 1118 | AD28: 0 | AE28: 0 | AF28: =+AE28+AC28+AA28+Y28+W28+U28+S28+Q28+O28+M28+K28 -> 2769605 | AG28: =+AF28/G28 -> 1.3703747 | AH28: =+AF28-G28 -> 748548.34 | AI28: =+AF28/C28-1 -> 0.39243009 | AJ28: =+C28/B28 -> 0.052745753 | AK28: =+AF28/E28 -> 0.067944161 | AL28: =+E28/B28-1 -> 0.080957841 | AO28: =+F28 -> 46047 | AP28: =Tabla2[[#This Row],[Web + APP 2025]]+Tabla2[[#This Row],[Afiliados 2025]]+Tabla2[[#This Row],[TMK 2025]]+Tabla2[[#This Row],[WA 2025]]+Tabla2[[#This Row],[Ent. en Tienda 2025]] -> 1728777.2 | AQ28: =Tabla2[[#This Row],[Meli Drop 2025]]+Tabla2[[#This Row],[Meli Full 2025]]+Tabla2[[#This Row],[Amazon Drop 2025]]+Tabla2[[#This Row],[Amazon Full 2025]]+Tabla2[[#This Row],[TikTok 2025]]+Tabla2[[#This Row],[Shein 2025]] -> 260267 | AR28: =Tabla2[[#This Row],[Web + APP 2026]]+Tabla2[[#This Row],[Afiliados 2026]]+Tabla2[[#This Row],[TMK 2026]]+Tabla2[[#This Row],[WA 2026]]+Tabla2[[#This Row],[Ent. en Tienda 2026]] -> 2312841 | AS28: =Tabla2[[#This Row],[Meli Drop 2026]]+Tabla2[[#This Row],[Meli Full 2026]]+Tabla2[[#This Row],[Amazon Drop 2026]]+Tabla2[[#This Row],[Amazon Full 2026]]+Tabla2[[#This Row],[TikTok 2026]]+Tabla2[[#This Row],[Shein 2026]] -> 456764 | AT28: =+AR28/AP28-1 -> 0.33784793 | AU28: =+AS28/AQ28-1 -> 0.75498238 | AV28: =+H28 -> 1521692.3 | AW28: =+I28 -> 499364.39 | AX28: =+AR28/AV28 -> 1.5199137 | AY28: =+AS28/AW28 -> 0.91469077 | AZ28: =+(AR28+AS28)/(AV28+AW28) -> 1.3703747 | BA28: 0.022393022 | BB28: 0.017343839 | BC28: =+AR28-AV28 -> 791148.73 | BD28: =+AS28-AW28 -> -42600.39
A29: 45684 | B29: 22777244 | C29: =+J29+L29+N29+P29+R29+T29+V29+X29+Z29+AB29+AD29 -> 3133160.6 | D29: =+Tabla22[[#This Row],[Share diario]] -> 0.023094055 | E29: =+Tabla22[[#This Row],[Global 2026]] -> 22718693 | F29: 46048 | G29: =+H29+I29 -> 2539442.5 | H29: 2204317.7 | I29: 335124.73 | J29: 2287434 | K29: 3117837 | L29: 20571.552 | M29: =12809+10481 -> 23290 | N29: 48184 | O29: 4291 | P29: 6325 | Q29: 1531 | R29: 38707 | S29: 43342 | T29: 428538 | U29: 517922 | V29: 34661 | W29: 78533 | X29: 41258 | Y29: 42966 | Z29: 227482 | AA29: 8314 | AB29: 0 | AC29: 10462 | AD29: 0 | AE29: 1378 | AF29: =+AE29+AC29+AA29+Y29+W29+U29+S29+Q29+O29+M29+K29 -> 3849866 | AG29: =+AF29/G29 -> 1.516028 | AH29: =+AF29-G29 -> 1310423.5 | AI29: =+AF29/C29-1 -> 0.2287484 | AJ29: =+C29/B29 -> 0.13755661 | AK29: =+AF29/E29 -> 0.16945808 | AL29: =+E29/B29-1 -> -0.0025705919 | AO29: =+F29 -> 46048 | AP29: =Tabla2[[#This Row],[Web + APP 2025]]+Tabla2[[#This Row],[Afiliados 2025]]+Tabla2[[#This Row],[TMK 2025]]+Tabla2[[#This Row],[WA 2025]]+Tabla2[[#This Row],[Ent. en Tienda 2025]] -> 2401221.6 | AQ29: =Tabla2[[#This Row],[Meli Drop 2025]]+Tabla2[[#This Row],[Meli Full 2025]]+Tabla2[[#This Row],[Amazon Drop 2025]]+Tabla2[[#This Row],[Amazon Full 2025]]+Tabla2[[#This Row],[TikTok 2025]]+Tabla2[[#This Row],[Shein 2025]] -> 731939 | AR29: =Tabla2[[#This Row],[Web + APP 2026]]+Tabla2[[#This Row],[Afiliados 2026]]+Tabla2[[#This Row],[TMK 2026]]+Tabla2[[#This Row],[WA 2026]]+Tabla2[[#This Row],[Ent. en Tienda 2026]] -> 3190291 | AS29: =Tabla2[[#This Row],[Meli Drop 2026]]+Tabla2[[#This Row],[Meli Full 2026]]+Tabla2[[#This Row],[Amazon Drop 2026]]+Tabla2[[#This Row],[Amazon Full 2026]]+Tabla2[[#This Row],[TikTok 2026]]+Tabla2[[#This Row],[Shein 2026]] -> 659575 | AT29: =+AR29/AP29-1 -> 0.32861168 | AU29: =+AS29/AQ29-1 -> -0.098866162 | AV29: =+H29 -> 2204317.7 | AW29: =+I29 -> 335124.73 | AX29: =+AR29/AV29 -> 1.4472918 | AY29: =+AS29/AW29 -> 1.9681478 | AZ29: =+(AR29+AS29)/(AV29+AW29) -> 1.516028 | BA29: 0.015028015 | BB29: 0.025124221 | BC29: =+AR29-AV29 -> 985973.26 | BD29: =+AS29-AW29 -> 324450.27
A30: 45685 | B30: 24302957 | C30: =+J30+L30+N30+P30+R30+T30+V30+X30+Z30+AB30+AD30 -> 3137849.9 | D30: =+Tabla22[[#This Row],[Share diario]] -> 0.036377966 | E30: =+Tabla22[[#This Row],[Global 2026]] -> 24708209 | F30: 46049 | G30: =+H30+I30 -> 4004192.1 | H30: 3061733.6 | I30: 942458.54 | J30: 2625912 | K30: 3426615 | L30: 24700.862 | M30: =16341+11476 -> 27817 | N30: 92321 | O30: 57382 | P30: 6877 | Q30: 5403 | R30: 49308 | S30: 52302 | T30: 276028 | U30: 411232 | V30: 43571 | W30: 82440 | X30: 14912 | Y30: 37763 | Z30: 4220 | AA30: 5270 | AB30: 0 | AC30: 1490 | AD30: 0 | AE30: 0 | AF30: =+AE30+AC30+AA30+Y30+W30+U30+S30+Q30+O30+M30+K30 -> 4107714 | AG30: =+AF30/G30 -> 1.0258534 | AH30: =+AF30-G30 -> 103521.85 | AI30: =+AF30/C30-1 -> 0.30908558 | AJ30: =+C30/B30 -> 0.12911391 | AK30: =+AF30/E30 -> 0.16624896 | AL30: =+E30/B30-1 -> 0.016675008 | AO30: =+F30 -> 46049 | AP30: =Tabla2[[#This Row],[Web + APP 2025]]+Tabla2[[#This Row],[Afiliados 2025]]+Tabla2[[#This Row],[TMK 2025]]+Tabla2[[#This Row],[WA 2025]]+Tabla2[[#This Row],[Ent. en Tienda 2025]] -> 2799118.9 | AQ30: =Tabla2[[#This Row],[Meli Drop 2025]]+Tabla2[[#This Row],[Meli Full 2025]]+Tabla2[[#This Row],[Amazon Drop 2025]]+Tabla2[[#This Row],[Amazon Full 2025]]+Tabla2[[#This Row],[TikTok 2025]]+Tabla2[[#This Row],[Shein 2025]] -> 338731 | AR30: =Tabla2[[#This Row],[Web + APP 2026]]+Tabla2[[#This Row],[Afiliados 2026]]+Tabla2[[#This Row],[TMK 2026]]+Tabla2[[#This Row],[WA 2026]]+Tabla2[[#This Row],[Ent. en Tienda 2026]] -> 3569519 | AS30: =Tabla2[[#This Row],[Meli Drop 2026]]+Tabla2[[#This Row],[Meli Full 2026]]+Tabla2[[#This Row],[Amazon Drop 2026]]+Tabla2[[#This Row],[Amazon Full 2026]]+Tabla2[[#This Row],[TikTok 2026]]+Tabla2[[#This Row],[Shein 2026]] -> 538195 | AT30: =+AR30/AP30-1 -> 0.27522952 | AU30: =+AS30/AQ30-1 -> 0.58885664 | AV30: =+H30 -> 3061733.6 | AW30: =+I30 -> 942458.54 | AX30: =+AR30/AV30 -> 1.165849 | AY30: =+AS30/AW30 -> 0.5710543 | AZ30: =+(AR30+AS30)/(AV30+AW30) -> 1.0258534 | BA30: 0.042262715 | BB30: 0.034896816 | BC30: =+AR30-AV30 -> 507785.4 | BD30: =+AS30-AW30 -> -404263.54
A31: 45686 | B31: 26923427 | C31: =+J31+L31+N31+P31+R31+T31+V31+X31+Z31+AB31+AD31 -> 2877999.6 | D31: =+Tabla22[[#This Row],[Share diario]] -> 0.036432412 | E31: =+Tabla22[[#This Row],[Global 2026]] -> 25710859 | F31: 46050 | G31: =+H31+I31 -> 4005238.3 | H31: 3569081.9 | I31: 436156.46 | J31: 2418581 | K31: 2794957 | L31: 20333.621 | M31: =128+1268 -> 1396 | N31: 55131 | O31: 24203 | P31: 6277 | Q31: 1791 | R31: 82493 | S31: 86934 | T31: 224454 | U31: 411456 | V31: 43095 | W31: 58025 | X31: 21531 | Y31: 39072 | Z31: 6104 | AA31: 4163 | AB31: 0 | AC31: 4865 | AD31: 0 | AE31: 0 | AF31: =+AE31+AC31+AA31+Y31+W31+U31+S31+Q31+O31+M31+K31 -> 3426862 | AG31: =+AF31/G31 -> 0.85559503 | AH31: =+AF31-G31 -> -578376.32 | AI31: =+AF31/C31-1 -> 0.19070968 | AJ31: =+C31/B31 -> 0.10689574 | AK31: =+AF31/E31 -> 0.13328462 | AL31: =+E31/B31-1 -> -0.045037654 | AO31: =+F31 -> 46050 | AP31: =Tabla2[[#This Row],[Web + APP 2025]]+Tabla2[[#This Row],[Afiliados 2025]]+Tabla2[[#This Row],[TMK 2025]]+Tabla2[[#This Row],[WA 2025]]+Tabla2[[#This Row],[Ent. en Tienda 2025]] -> 2582815.6 | AQ31: =Tabla2[[#This Row],[Meli Drop 2025]]+Tabla2[[#This Row],[Meli Full 2025]]+Tabla2[[#This Row],[Amazon Drop 2025]]+Tabla2[[#This Row],[Amazon Full 2025]]+Tabla2[[#This Row],[TikTok 2025]]+Tabla2[[#This Row],[Shein 2025]] -> 295184 | AR31: =Tabla2[[#This Row],[Web + APP 2026]]+Tabla2[[#This Row],[Afiliados 2026]]+Tabla2[[#This Row],[TMK 2026]]+Tabla2[[#This Row],[WA 2026]]+Tabla2[[#This Row],[Ent. en Tienda 2026]] -> 2909281 | AS31: =Tabla2[[#This Row],[Meli Drop 2026]]+Tabla2[[#This Row],[Meli Full 2026]]+Tabla2[[#This Row],[Amazon Drop 2026]]+Tabla2[[#This Row],[Amazon Full 2026]]+Tabla2[[#This Row],[TikTok 2026]]+Tabla2[[#This Row],[Shein 2026]] -> 517581 | AT31: =+AR31/AP31-1 -> 0.12639903 | AU31: =+AS31/AQ31-1 -> 0.75341821 | AV31: =+H31 -> 3569081.9 | AW31: =+I31 -> 436156.46 | AX31: =+AR31/AV31 -> 0.81513429 | AY31: =+AS31/AW31 -> 1.1866865 | AZ31: =+(AR31+AS31)/(AV31+AW31) -> 0.85559503 | BA31: 0.019558586 | BB31: 0.040679435 | BC31: =+AR31-AV31 -> -659800.86 | BD31: =+AS31-AW31 -> 81424.538
A32: 45687 | B32: 30741390 | C32: =+J32+L32+N32+P32+R32+T32+V32+X32+Z32+AB32+AD32 -> 2556179.1 | D32: =+Tabla22[[#This Row],[Share diario]] -> 0.033415387 | E32: =+Tabla22[[#This Row],[Global 2026]] -> 28535339 | F32: 46051 | G32: =+H32+I32 -> 3673363.9 | H32: 3293279.4 | I32: 380084.52 | J32: 2124088 | K32: 2450518 | L32: 20593.103 | M32: =369+128 -> 497 | N32: 61017 | O32: 6335 | P32: 4303 | Q32: 6576 | R32: 68703 | S32: 61831 | T32: 188379 | U32: 318201 | V32: 64182 | W32: 69719 | X32: 18890 | Y32: 44859 | Z32: 6024 | AA32: 6441 | AB32: 0 | AC32: 10362 | AD32: 0 | AE32: 0 | AF32: =+AE32+AC32+AA32+Y32+W32+U32+S32+Q32+O32+M32+K32 -> 2975339 | AG32: =+AF32/G32 -> 0.80997666 | AH32: =+AF32-G32 -> -698024.88 | AI32: =+AF32/C32-1 -> 0.16397908 | AJ32: =+C32/B32 -> 0.083151058 | AK32: =+AF32/E32 -> 0.10426857 | AL32: =+E32/B32-1 -> -0.071761589 | AO32: =+F32 -> 46051 | AP32: =Tabla2[[#This Row],[Web + APP 2025]]+Tabla2[[#This Row],[Afiliados 2025]]+Tabla2[[#This Row],[TMK 2025]]+Tabla2[[#This Row],[WA 2025]]+Tabla2[[#This Row],[Ent. en Tienda 2025]] -> 2278704.1 | AQ32: =Tabla2[[#This Row],[Meli Drop 2025]]+Tabla2[[#This Row],[Meli Full 2025]]+Tabla2[[#This Row],[Amazon Drop 2025]]+Tabla2[[#This Row],[Amazon Full 2025]]+Tabla2[[#This Row],[TikTok 2025]]+Tabla2[[#This Row],[Shein 2025]] -> 277475 | AR32: =Tabla2[[#This Row],[Web + APP 2026]]+Tabla2[[#This Row],[Afiliados 2026]]+Tabla2[[#This Row],[TMK 2026]]+Tabla2[[#This Row],[WA 2026]]+Tabla2[[#This Row],[Ent. en Tienda 2026]] -> 2525757 | AS32: =Tabla2[[#This Row],[Meli Drop 2026]]+Tabla2[[#This Row],[Meli Full 2026]]+Tabla2[[#This Row],[Amazon Drop 2026]]+Tabla2[[#This Row],[Amazon Full 2026]]+Tabla2[[#This Row],[TikTok 2026]]+Tabla2[[#This Row],[Shein 2026]] -> 449582 | AT32: =+AR32/AP32-1 -> 0.10841816 | AU32: =+AS32/AQ32-1 -> 0.62026128 | AV32: =+H32 -> 3293279.4 | AW32: =+I32 -> 380084.52 | AX32: =+AR32/AV32 -> 0.76694283 | AY32: =+AS32/AW32 -> 1.1828474 | AZ32: =+(AR32+AS32)/(AV32+AW32) -> 0.80997666 | BA32: 0.017044149 | BB32: 0.037535912 | BC32: =+AR32-AV32 -> -767522.36 | BD32: =+AS32-AW32 -> 69497.481
A33: 45688 | B33: 36726305 | C33: =+J33+L33+N33+P33+R33+T33+V33+X33+Z33+AB33+AD33 -> 2351622.2 | D33: =+Tabla22[[#This Row],[Share diario]] -> 0.029678848 | E33: =+Tabla22[[#This Row],[Global 2026]] -> 32375122 | F33: 46052 | G33: =+H33+I33 -> 3262796.9 | H33: 2905514.9 | I33: 357282.07 | J33: 1896380 | K33: 1981506 | L33: 18311.207 | M33: =13851+10016 -> 23867 | N33: 57647 | O33: 19840 | P33: 630 | Q33: 1512 | R33: 46392 | S33: 79127 | T33: 251795 | U33: 341849 | V33: 49925 | W33: 52697 | X33: 25033 | Y33: 28869 | Z33: 5509 | AA33: 3232 | AB33: 0 | AC33: 4079 | AD33: 0 | AE33: 0 | AF33: =+AE33+AC33+AA33+Y33+W33+U33+S33+Q33+O33+M33+K33 -> 2536578 | AG33: =+AF33/G33 -> 0.77742441 | AH33: =+AF33-G33 -> -726218.94 | AI33: =+AF33/C33-1 -> 0.0786503 | AJ33: =+C33/B33 -> 0.064031005 | AK33: =+AF33/E33 -> 0.078349604 | AL33: =+E33/B33-1 -> -0.11847593 | AO33: =+F33 -> 46052 | AP33: =Tabla2[[#This Row],[Web + APP 2025]]+Tabla2[[#This Row],[Afiliados 2025]]+Tabla2[[#This Row],[TMK 2025]]+Tabla2[[#This Row],[WA 2025]]+Tabla2[[#This Row],[Ent. en Tienda 2025]] -> 2019360.2 | AQ33: =Tabla2[[#This Row],[Meli Drop 2025]]+Tabla2[[#This Row],[Meli Full 2025]]+Tabla2[[#This Row],[Amazon Drop 2025]]+Tabla2[[#This Row],[Amazon Full 2025]]+Tabla2[[#This Row],[TikTok 2025]]+Tabla2[[#This Row],[Shein 2025]] -> 332262 | AR33: =Tabla2[[#This Row],[Web + APP 2026]]+Tabla2[[#This Row],[Afiliados 2026]]+Tabla2[[#This Row],[TMK 2026]]+Tabla2[[#This Row],[WA 2026]]+Tabla2[[#This Row],[Ent. en Tienda 2026]] -> 2105852 | AS33: =Tabla2[[#This Row],[Meli Drop 2026]]+Tabla2[[#This Row],[Meli Full 2026]]+Tabla2[[#This Row],[Amazon Drop 2026]]+Tabla2[[#This Row],[Amazon Full 2026]]+Tabla2[[#This Row],[TikTok 2026]]+Tabla2[[#This Row],[Shein 2026]] -> 430726 | AT33: =+AR33/AP33-1 -> 0.042831285 | AU33: =+AS33/AQ33-1 -> 0.29634445 | AV33: =+H33 -> 2905514.9 | AW33: =+I33 -> 357282.07 | AX33: =+AR33/AV33 -> 0.72477757 | AY33: =+AS33/AW33 -> 1.2055629 | AZ33: =+(AR33+AS33)/(AV33+AW33) -> 0.77742441 | BA33: 0.016021618 | BB33: 0.033116277 | BC33: =+AR33-AV33 -> -799662.87 | BD33: =+AS33-AW33 -> 73443.926
A34: 45689 | B34: 37793760 | C34: =+J34+L34+N34+P34+R34+T34+V34+X34+Z34+AB34+AD34 -> 1774200.1 | D34: =+Tabla22[[#This Row],[Share diario]] -> 0.027303814 | E34: =+Tabla22[[#This Row],[Global 2026]] -> 38921712 | F34: 46053 | G34: =+H34+I34 -> 3002659.2 | H34: 2574832.4 | I34: 427826.85 | J34: 1345714 | K34: 1742488 | L34: 19268.103 | M34: =18139+12919 -> 31058 | N34: 24746 | O34: 21274 | P34: 1652 | Q34: 662 | R34: 52485 | S34: 34276 | T34: 259164 | U34: 350135 | V34: 40620 | W34: 69841 | X34: 24306 | Y34: 46260 | Z34: 6245 | AA34: 4173 | AB34: 0 | AC34: 418 | AD34: 0 | AE34: 0 | AF34: =+AE34+AC34+AA34+Y34+W34+U34+S34+Q34+O34+M34+K34 -> 2300585 | AG34: =+AF34/G34 -> 0.76618251 | AH34: =+AF34-G34 -> -702074.23 | AI34: =+AF34/C34-1 -> 0.29668857 | AJ34: =+C34/B34 -> 0.04694426 | AK34: =+AF34/E34 -> 0.059108011 | AL34: =+E34/B34-1 -> 0.029844927 | AO34: =+F34 -> 46053 | AP34: =Tabla2[[#This Row],[Web + APP 2025]]+Tabla2[[#This Row],[Afiliados 2025]]+Tabla2[[#This Row],[TMK 2025]]+Tabla2[[#This Row],[WA 2025]]+Tabla2[[#This Row],[Ent. en Tienda 2025]] -> 1443865.1 | AQ34: =Tabla2[[#This Row],[Meli Drop 2025]]+Tabla2[[#This Row],[Meli Full 2025]]+Tabla2[[#This Row],[Amazon Drop 2025]]+Tabla2[[#This Row],[Amazon Full 2025]]+Tabla2[[#This Row],[TikTok 2025]]+Tabla2[[#This Row],[Shein 2025]] -> 330335 | AR34: =Tabla2[[#This Row],[Web + APP 2026]]+Tabla2[[#This Row],[Afiliados 2026]]+Tabla2[[#This Row],[TMK 2026]]+Tabla2[[#This Row],[WA 2026]]+Tabla2[[#This Row],[Ent. en Tienda 2026]] -> 1829758 | AS34: =Tabla2[[#This Row],[Meli Drop 2026]]+Tabla2[[#This Row],[Meli Full 2026]]+Tabla2[[#This Row],[Amazon Drop 2026]]+Tabla2[[#This Row],[Amazon Full 2026]]+Tabla2[[#This Row],[TikTok 2026]]+Tabla2[[#This Row],[Shein 2026]] -> 470827 | AT34: =+AR34/AP34-1 -> 0.26726382 | AU34: =+AS34/AQ34-1 -> 0.42530159 | AV34: =+H34 -> 2574832.4 | AW34: =+I34 -> 427826.85 | AX34: =+AR34/AV34 -> 0.71063189 | AY34: =+AS34/AW34 -> 1.1005083 | AZ34: =+(AR34+AS34)/(AV34+AW34) -> 0.76618251 | BA34: 0.019185061 | BB34: 0.029347247 | BC34: =+AR34-AV34 -> -745074.38 | BD34: =+AS34-AW34 -> 43000.145
A35: 45690 | B35: 31352601 | C35: =+J35+L35+N35+P35+R35+T35+V35+X35+Z35+AB35+AD35 -> 1727235.8 | D35: =+Tabla22[[#This Row],[Share diario]] -> 0.022985736 | E35: =+Tabla22[[#This Row],[Global 2026]] -> 37738958 | F35: 46054 | G35: =+H35+I35 -> 2165003.4 | H35: 1726695.1 | I35: 438308.27 | J35: 1308491 | K35: 2180837 | L35: 20338.793 | M35: =18122+13547 -> 31669 | N35: 36076 | O35: -2281 | P35: 6773 | Q35: 715 | R35: 66898 | S35: 55760 | T35: 214500 | U35: 327974 | V35: 45990 | W35: 76980 | X35: 25758 | Y35: 25893 | Z35: 2411 | AA35: 4383 | AB35: 0 | AC35: 774 | AD35: 0 | AE35: 0 | AF35: =+AE35+AC35+AA35+Y35+W35+U35+S35+Q35+O35+M35+K35 -> 2702704 | AG35: =+AF35/G35 -> 1.2483602 | AH35: =+AF35-G35 -> 537700.62 | AI35: =+AF35/C35-1 -> 0.56475683 | AJ35: =+C35/B35 -> 0.05509067 | AK35: =+AF35/E35 -> 0.071615756 | AL35: =+E35/B35-1 -> 0.20369465 | AO35: =+F35 -> 46054 | AP35: =Tabla2[[#This Row],[Web + APP 2025]]+Tabla2[[#This Row],[Afiliados 2025]]+Tabla2[[#This Row],[TMK 2025]]+Tabla2[[#This Row],[WA 2025]]+Tabla2[[#This Row],[Ent. en Tienda 2025]] -> 1438576.8 | AQ35: =Tabla2[[#This Row],[Meli Drop 2025]]+Tabla2[[#This Row],[Meli Full 2025]]+Tabla2[[#This Row],[Amazon Drop 2025]]+Tabla2[[#This Row],[Amazon Full 2025]]+Tabla2[[#This Row],[TikTok 2025]]+Tabla2[[#This Row],[Shein 2025]] -> 288659 | AR35: =Tabla2[[#This Row],[Web + APP 2026]]+Tabla2[[#This Row],[Afiliados 2026]]+Tabla2[[#This Row],[TMK 2026]]+Tabla2[[#This Row],[WA 2026]]+Tabla2[[#This Row],[Ent. en Tienda 2026]] -> 2266700 | AS35: =Tabla2[[#This Row],[Meli Drop 2026]]+Tabla2[[#This Row],[Meli Full 2026]]+Tabla2[[#This Row],[Amazon Drop 2026]]+Tabla2[[#This Row],[Amazon Full 2026]]+Tabla2[[#This Row],[TikTok 2026]]+Tabla2[[#This Row],[Shein 2026]] -> 436004 | AT35: =+AR35/AP35-1 -> 0.5756545 | AU35: =+AS35/AQ35-1 -> 0.51044658 | AV35: =+H35 -> 1726695.1 | AW35: =+I35 -> 438308.27 | AX35: =+AR35/AV35 -> 1.312739 | AY35: =+AS35/AW35 -> 0.99474282 | AZ35: =+(AR35+AS35)/(AV35+AW35) -> 1.2483602 | BA35: 0.031307733 | BB35: 0.021668016 | BC35: =+AR35-AV35 -> 540004.88 | BD35: =+AS35-AW35 -> -2304.265
A36: 45691 | B36: 36434352 | C36: =+J36+L36+N36+P36+R36+T36+V36+X36+Z36+AB36+AD36 -> 2412188.8 | D36: =+Tabla22[[#This Row],[Share diario]] -> 0.022377287 | E36: =+Tabla22[[#This Row],[Global 2026]] -> 33698919 | F36: 46055 | G36: =+H36+I36 -> 2103381 | H36: 1720370.9 | I36: 383010.05 | J36: 2010759 | K36: 2671764 | L36: 23738.793 | M36: =17032+13323 -> 30355 | N36: 37153 | O36: 15499 | P36: 756 | Q36: 3214 | R36: 54921 | S36: 64407 | T36: 213227 | U36: 374619 | V36: 32459 | W36: 115869 | X36: 34007 | Y36: 34782 | Z36: 5168 | AA36: 5635 | AB36: 0 | AC36: -148 | AD36: 0 | AE36: 0 | AF36: =+AE36+AC36+AA36+Y36+W36+U36+S36+Q36+O36+M36+K36 -> 3315996 | AG36: =+AF36/G36 -> 1.5765076 | AH36: =+AF36-G36 -> 1212615 | AI36: =+AF36/C36-1 -> 0.37468344 | AJ36: =+C36/B36 -> 0.066206441 | AK36: =+AF36/E36 -> 0.098400664 | AL36: =+E36/B36-1 -> -0.075078404 | AO36: =+F36 -> 46055 | AP36: =Tabla2[[#This Row],[Web + APP 2025]]+Tabla2[[#This Row],[Afiliados 2025]]+Tabla2[[#This Row],[TMK 2025]]+Tabla2[[#This Row],[WA 2025]]+Tabla2[[#This Row],[Ent. en Tienda 2025]] -> 2127327.8 | AQ36: =Tabla2[[#This Row],[Meli Drop 2025]]+Tabla2[[#This Row],[Meli Full 2025]]+Tabla2[[#This Row],[Amazon Drop 2025]]+Tabla2[[#This Row],[Amazon Full 2025]]+Tabla2[[#This Row],[TikTok 2025]]+Tabla2[[#This Row],[Shein 2025]] -> 284861 | AR36: =Tabla2[[#This Row],[Web + APP 2026]]+Tabla2[[#This Row],[Afiliados 2026]]+Tabla2[[#This Row],[TMK 2026]]+Tabla2[[#This Row],[WA 2026]]+Tabla2[[#This Row],[Ent. en Tienda 2026]] -> 2785239 | AS36: =Tabla2[[#This Row],[Meli Drop 2026]]+Tabla2[[#This Row],[Meli Full 2026]]+Tabla2[[#This Row],[Amazon Drop 2026]]+Tabla2[[#This Row],[Amazon Full 2026]]+Tabla2[[#This Row],[TikTok 2026]]+Tabla2[[#This Row],[Shein 2026]] -> 530757 | AT36: =+AR36/AP36-1 -> 0.30926649 | AU36: =+AS36/AQ36-1 -> 0.86321399 | AV36: =+H36 -> 1720370.9 | AW36: =+I36 -> 383010.05 | AX36: =+AR36/AV36 -> 1.6189759 | AY36: =+AS36/AW36 -> 1.3857521 | AZ36: =+(AR36+AS36)/(AV36+AW36) -> 1.5765076 | BA36: 0.027357861 | BB36: 0.021588655 | BC36: =+AR36-AV36 -> 1064868.1 | BD36: =+AS36-AW36 -> 147746.95
A37: 45692 | B37: 22395022 | C37: =+J37+L37+N37+P37+R37+T37+V37+X37+Z37+AB37+AD37 -> 2754754.9 | D37: =+Tabla22[[#This Row],[Share diario]] -> 0.031251229 | E37: =+Tabla22[[#This Row],[Global 2026]] -> 22551540 | F37: 46056 | G37: =+H37+I37 -> 2922007.8 | H37: 2544037.2 | I37: 377970.64 | J37: 2354728 | K37: 3181814 | L37: 23787.931 | M37: =13064+9710 -> 22774 | N37: 132035 | O37: 13358 | P37: 2563 | Q37: 6483 | R37: 50149 | S37: 67690 | T37: 79913 | U37: 395638 | V37: 56003 | W37: 87196 | X37: 51486 | Y37: 25879 | Z37: 4090 | AA37: 4357 | AB37: 0 | AC37: 4453 | AD37: 0 | AE37: 0 | AF37: =+AE37+AC37+AA37+Y37+W37+U37+S37+Q37+O37+M37+K37 -> 3809642 | AG37: =+AF37/G37 -> 1.3037754 | AH37: =+AF37-G37 -> 887634.18 | AI37: =+AF37/C37-1 -> 0.38293318 | AJ37: =+C37/B37 -> 0.12300747 | AK37: =+AF37/E37 -> 0.16893046 | AL37: =+E37/B37-1 -> 0.0069889639 | AO37: =+F37 -> 46056 | AP37: =Tabla2[[#This Row],[Web + APP 2025]]+Tabla2[[#This Row],[Afiliados 2025]]+Tabla2[[#This Row],[TMK 2025]]+Tabla2[[#This Row],[WA 2025]]+Tabla2[[#This Row],[Ent. en Tienda 2025]] -> 2563262.9 | AQ37: =Tabla2[[#This Row],[Meli Drop 2025]]+Tabla2[[#This Row],[Meli Full 2025]]+Tabla2[[#This Row],[Amazon Drop 2025]]+Tabla2[[#This Row],[Amazon Full 2025]]+Tabla2[[#This Row],[TikTok 2025]]+Tabla2[[#This Row],[Shein 2025]] -> 191492 | AR37: =Tabla2[[#This Row],[Web + APP 2026]]+Tabla2[[#This Row],[Afiliados 2026]]+Tabla2[[#This Row],[TMK 2026]]+Tabla2[[#This Row],[WA 2026]]+Tabla2[[#This Row],[Ent. en Tienda 2026]] -> 3292119 | AS37: =Tabla2[[#This Row],[Meli Drop 2026]]+Tabla2[[#This Row],[Meli Full 2026]]+Tabla2[[#This Row],[Amazon Drop 2026]]+Tabla2[[#This Row],[Amazon Full 2026]]+Tabla2[[#This Row],[TikTok 2026]]+Tabla2[[#This Row],[Shein 2026]] -> 517523 | AT37: =+AR37/AP37-1 -> 0.28434698 | AU37: =+AS37/AQ37-1 -> 1.7025829 | AV37: =+H37 -> 2544037.2 | AW37: =+I37 -> 377970.64 | AX37: =+AR37/AV37 -> 1.294053 | AY37: =+AS37/AW37 -> 1.3692148 | AZ37: =+(AR37+AS37)/(AV37+AW37) -> 1.3037754 | BA37: 0.026997903 | BB37: 0.031924709 | BC37: =+AR37-AV37 -> 748081.82 | BD37: =+AS37-AW37 -> 139552.36
A38: 45693 | B38: 25539612 | C38: =+J38+L38+N38+P38+R38+T38+V38+X38+Z38+AB38+AD38 -> 2807800.6 | D38: =+Tabla22[[#This Row],[Share diario]] -> 0.035689362 | E38: =+Tabla22[[#This Row],[Global 2026]] -> 25170911 | F38: 46057 | G38: =+H38+I38 -> 3319448.1 | H38: 3065365 | I38: 254083.06 | J38: 2362602 | K38: 3050065 | L38: 24452.586 | M38: =11845+11364 -> 23209 | N38: 110188 | O38: 39499 | P38: -697 | Q38: 6199 | R38: 48254 | S38: 60063 | T38: 151535 | U38: 318098 | V38: 57305 | W38: 80270 | X38: 46066 | Y38: 22916 | Z38: 8095 | AA38: 4100 | AB38: 0 | AC38: 2376 | AD38: 0 | AE38: 0 | AF38: =+AE38+AC38+AA38+Y38+W38+U38+S38+Q38+O38+M38+K38 -> 3606795 | AG38: =+AF38/G38 -> 1.0865647 | AH38: =+AF38-G38 -> 287346.92 | AI38: =+AF38/C38-1 -> 0.28456238 | AJ38: =+C38/B38 -> 0.10993905 | AK38: =+AF38/E38 -> 0.14329219 | AL38: =+E38/B38-1 -> -0.014436437 | AO38: =+F38 -> 46057 | AP38: =Tabla2[[#This Row],[Web + APP 2025]]+Tabla2[[#This Row],[Afiliados 2025]]+Tabla2[[#This Row],[TMK 2025]]+Tabla2[[#This Row],[WA 2025]]+Tabla2[[#This Row],[Ent. en Tienda 2025]] -> 2544799.6 | AQ38: =Tabla2[[#This Row],[Meli Drop 2025]]+Tabla2[[#This Row],[Meli Full 2025]]+Tabla2[[#This Row],[Amazon Drop 2025]]+Tabla2[[#This Row],[Amazon Full 2025]]+Tabla2[[#This Row],[TikTok 2025]]+Tabla2[[#This Row],[Shein 2025]] -> 263001 | AR38: =Tabla2[[#This Row],[Web + APP 2026]]+Tabla2[[#This Row],[Afiliados 2026]]+Tabla2[[#This Row],[TMK 2026]]+Tabla2[[#This Row],[WA 2026]]+Tabla2[[#This Row],[Ent. en Tienda 2026]] -> 3179035 | AS38: =Tabla2[[#This Row],[Meli Drop 2026]]+Tabla2[[#This Row],[Meli Full 2026]]+Tabla2[[#This Row],[Amazon Drop 2026]]+Tabla2[[#This Row],[Amazon Full 2026]]+Tabla2[[#This Row],[TikTok 2026]]+Tabla2[[#This Row],[Shein 2026]] -> 427760 | AT38: =+AR38/AP38-1 -> 0.24922804 | AU38: =+AS38/AQ38-1 -> 0.62645769 | AV38: =+H38 -> 3065365 | AW38: =+I38 -> 254083.06 | AX38: =+AR38/AV38 -> 1.037082 | AY38: =+AS38/AW38 -> 1.683544 | AZ38: =+(AR38+AS38)/(AV38+AW38) -> 1.0865647 | BA38: 0.01814879 | BB38: 0.038466767 | BC38: =+AR38-AV38 -> 113669.98 | BD38: =+AS38-AW38 -> 173676.94
A39: 45694 | B39: 29401665 | C39: =+J39+L39+N39+P39+R39+T39+V39+X39+Z39+AB39+AD39 -> 2311807.3 | D39: =+Tabla22[[#This Row],[Share diario]] -> 0.036376597 | E39: =+Tabla22[[#This Row],[Global 2026]] -> 29563607 | F39: 46058 | G39: =+H39+I39 -> 3392250.5 | H39: 3043285 | I39: 348965.48 | J39: 1988730 | K39: 2711541 | L39: 22460.345 | M39: =13034+9391 -> 22425 | N39: 52855 | O39: 48724 | P39: 2503 | Q39: 4521 | R39: 40300 | S39: 63963 | T39: 119932 | U39: 334593 | V39: 56342 | W39: 91963 | X39: 22237 | Y39: 28657 | Z39: 6448 | AA39: 3153 | AB39: 0 | AC39: 5982 | AD39: 0 | AE39: 0 | AF39: =+AE39+AC39+AA39+Y39+W39+U39+S39+Q39+O39+M39+K39 -> 3315522 | AG39: =+AF39/G39 -> 0.97738124 | AH39: =+AF39-G39 -> -76728.483 | AI39: =+AF39/C39-1 -> 0.43416881 | AJ39: =+C39/B39 -> 0.07862845 | AK39: =+AF39/E39 -> 0.11214876 | AL39: =+E39/B39-1 -> 0.0055079194 | AO39: =+F39 -> 46058 | AP39: =Tabla2[[#This Row],[Web + APP 2025]]+Tabla2[[#This Row],[Afiliados 2025]]+Tabla2[[#This Row],[TMK 2025]]+Tabla2[[#This Row],[WA 2025]]+Tabla2[[#This Row],[Ent. en Tienda 2025]] -> 2106848.3 | AQ39: =Tabla2[[#This Row],[Meli Drop 2025]]+Tabla2[[#This Row],[Meli Full 2025]]+Tabla2[[#This Row],[Amazon Drop 2025]]+Tabla2[[#This Row],[Amazon Full 2025]]+Tabla2[[#This Row],[TikTok 2025]]+Tabla2[[#This Row],[Shein 2025]] -> 204959 | AR39: =Tabla2[[#This Row],[Web + APP 2026]]+Tabla2[[#This Row],[Afiliados 2026]]+Tabla2[[#This Row],[TMK 2026]]+Tabla2[[#This Row],[WA 2026]]+Tabla2[[#This Row],[Ent. en Tienda 2026]] -> 2851174 | AS39: =Tabla2[[#This Row],[Meli Drop 2026]]+Tabla2[[#This Row],[Meli Full 2026]]+Tabla2[[#This Row],[Amazon Drop 2026]]+Tabla2[[#This Row],[Amazon Full 2026]]+Tabla2[[#This Row],[TikTok 2026]]+Tabla2[[#This Row],[Shein 2026]] -> 464348 | AT39: =+AR39/AP39-1 -> 0.35328867 | AU39: =+AS39/AQ39-1 -> 1.2655653 | AV39: =+H39 -> 3043285 | AW39: =+I39 -> 348965.48 | AX39: =+AR39/AV39 -> 0.93687381 | AY39: =+AS39/AW39 -> 1.3306416 | AZ39: =+(AR39+AS39)/(AV39+AW39) -> 0.97738124 | BA39: 0.024926106 | BB39: 0.038189688 | BC39: =+AR39-AV39 -> -192111 | BD39: =+AS39-AW39 -> 115382.52
A40: 45695 | B40: 32016485 | C40: =+J40+L40+N40+P40+R40+T40+V40+X40+Z40+AB40+AD40 -> 2129533.8 | D40: =+Tabla22[[#This Row],[Share diario]] -> 0.029950733 | E40: =+Tabla22[[#This Row],[Global 2026]] -> 30256382 | F40: 46059 | G40: =+H40+I40 -> 2791498 | H40: 2519546.1 | I40: 271951.88 | J40: 1675481 | K40: 2349247 | L40: 23913.793 | M40: =13643+8748 -> 22391 | N40: 91347 | O40: 29006 | P40: 4838 | Q40: 4581 | R40: 53316 | S40: 74959 | T40: 166819 | U40: 291618 | V40: 60494 | W40: 85249 | X40: 49141 | Y40: 20982 | Z40: 4184 | AA40: 3548 | AB40: 0 | AC40: 3560 | AD40: 0 | AE40: 0 | AF40: =+AE40+AC40+AA40+Y40+W40+U40+S40+Q40+O40+M40+K40 -> 2885141 | AG40: =+AF40/G40 -> 1.0335458 | AH40: =+AF40-G40 -> 93642.984 | AI40: =+AF40/C40-1 -> 0.35482283 | AJ40: =+C40/B40 -> 0.066513666 | AK40: =+AF40/E40 -> 0.095356444 | AL40: =+E40/B40-1 -> -0.054974898 | AO40: =+F40 -> 46059 | AP40: =Tabla2[[#This Row],[Web + APP 2025]]+Tabla2[[#This Row],[Afiliados 2025]]+Tabla2[[#This Row],[TMK 2025]]+Tabla2[[#This Row],[WA 2025]]+Tabla2[[#This Row],[Ent. en Tienda 2025]] -> 1848895.8 | AQ40: =Tabla2[[#This Row],[Meli Drop 2025]]+Tabla2[[#This Row],[Meli Full 2025]]+Tabla2[[#This Row],[Amazon Drop 2025]]+Tabla2[[#This Row],[Amazon Full 2025]]+Tabla2[[#This Row],[TikTok 2025]]+Tabla2[[#This Row],[Shein 2025]] -> 280638 | AR40: =Tabla2[[#This Row],[Web + APP 2026]]+Tabla2[[#This Row],[Afiliados 2026]]+Tabla2[[#This Row],[TMK 2026]]+Tabla2[[#This Row],[WA 2026]]+Tabla2[[#This Row],[Ent. en Tienda 2026]] -> 2480184 | AS40: =Tabla2[[#This Row],[Meli Drop 2026]]+Tabla2[[#This Row],[Meli Full 2026]]+Tabla2[[#This Row],[Amazon Drop 2026]]+Tabla2[[#This Row],[Amazon Full 2026]]+Tabla2[[#This Row],[TikTok 2026]]+Tabla2[[#This Row],[Shein 2026]] -> 404957 | AT40: =+AR40/AP40-1 -> 0.34144066 | AU40: =+AS40/AQ40-1 -> 0.44298705 | AV40: =+H40 -> 2519546.1 | AW40: =+I40 -> 271951.88 | AX40: =+AR40/AV40 -> 0.98437729 | AY40: =+AS40/AW40 -> 1.4890759 | AZ40: =+(AR40+AS40)/(AV40+AW40) -> 1.0335458 | BA40: 0.019425134 | BB40: 0.031617374 | BC40: =+AR40-AV40 -> -39362.138 | BD40: =+AS40-AW40 -> 133005.12
A41: 45696 | B41: 42648094 | C41: =+J41+L41+N41+P41+R41+T41+V41+X41+Z41+AB41+AD41 -> 1975582.5 | D41: =+Tabla22[[#This Row],[Share diario]] -> 0.027589279 | E41: =+Tabla22[[#This Row],[Global 2026]] -> 41295456 | F41: 46060 | G41: =+H41+I41 -> 2583432.1 | H41: 2211064.8 | I41: 372367.31 | J41: 1541898 | K41: 2093587 | L41: 17559.483 | M41: =14334+12342 -> 26676 | N41: 13396 | O41: 31006 | P41: 921 | Q41: 2429 | R41: 40059 | S41: 69984 | T41: 260206 | U41: 282237 | V41: 70792 | W41: 81965 | X41: 28263 | Y41: 25885 | Z41: 2488 | AA41: 5353 | AB41: 0 | AC41: -930 | AD41: 0 | AE41: 0 | AF41: =+AE41+AC41+AA41+Y41+W41+U41+S41+Q41+O41+M41+K41 -> 2618192 | AG41: =+AF41/G41 -> 1.0134549 | AH41: =+AF41-G41 -> 34759.872 | AI41: =+AF41/C41-1 -> 0.32527597 | AJ41: =+C41/B41 -> 0.046322879 | AK41: =+AF41/E41 -> 0.063401455 | AL41: =+E41/B41-1 -> -0.031716259 | AO41: =+F41 -> 46060 | AP41: =Tabla2[[#This Row],[Web + APP 2025]]+Tabla2[[#This Row],[Afiliados 2025]]+Tabla2[[#This Row],[TMK 2025]]+Tabla2[[#This Row],[WA 2025]]+Tabla2[[#This Row],[Ent. en Tienda 2025]] -> 1613833.5 | AQ41: =Tabla2[[#This Row],[Meli Drop 2025]]+Tabla2[[#This Row],[Meli Full 2025]]+Tabla2[[#This Row],[Amazon Drop 2025]]+Tabla2[[#This Row],[Amazon Full 2025]]+Tabla2[[#This Row],[TikTok 2025]]+Tabla2[[#This Row],[Shein 2025]] -> 361749 | AR41: =Tabla2[[#This Row],[Web + APP 2026]]+Tabla2[[#This Row],[Afiliados 2026]]+Tabla2[[#This Row],[TMK 2026]]+Tabla2[[#This Row],[WA 2026]]+Tabla2[[#This Row],[Ent. en Tienda 2026]] -> 2223682 | AS41: =Tabla2[[#This Row],[Meli Drop 2026]]+Tabla2[[#This Row],[Meli Full 2026]]+Tabla2[[#This Row],[Amazon Drop 2026]]+Tabla2[[#This Row],[Amazon Full 2026]]+Tabla2[[#This Row],[TikTok 2026]]+Tabla2[[#This Row],[Shein 2026]] -> 394510 | AT41: =+AR41/AP41-1 -> 0.37788813 | AU41: =+AS41/AQ41-1 -> 0.090562794 | AV41: =+H41 -> 2211064.8 | AW41: =+I41 -> 372367.31 | AX41: =+AR41/AV41 -> 1.0057064 | AY41: =+AS41/AW41 -> 1.0594646 | AZ41: =+(AR41+AS41)/(AV41+AW41) -> 1.0134549 | BA41: 0.026597665 | BB41: 0.027746293 | BC41: =+AR41-AV41 -> 12617.18 | BD41: =+AS41-AW41 -> 22142.691
A42: 45697 | B42: 41791699 | C42: =+J42+L42+N42+P42+R42+T42+V42+X42+Z42+AB42+AD42 -> 2325398.2 | D42: =+Tabla22[[#This Row],[Share diario]] -> 0.025594755 | E42: =+Tabla22[[#This Row],[Global 2026]] -> 41339084 | F42: 46061 | G42: =+H42+I42 -> 2409947.8 | H42: 1929957.6 | I42: 479990.24 | J42: 1896294 | K42: 2397497 | L42: 21667.241 | M42: =13709+11462 -> 25171 | N42: 30139 | O42: 5807 | P42: 3695 | Q42: 4467 | R42: 40975 | S42: 69643 | T42: 191313 | U42: 234501 | V42: 87339 | W42: 58072 | X42: 48851 | Y42: 17667 | Z42: 5125 | AA42: 2741 | AB42: 0 | AC42: 0 | AD42: 0 | AE42: 0 | AF42: =+AE42+AC42+AA42+Y42+W42+U42+S42+Q42+O42+M42+K42 -> 2815566 | AG42: =+AF42/G42 -> 1.1683099 | AH42: =+AF42-G42 -> 405618.18 | AI42: =+AF42/C42-1 -> 0.21078874 | AJ42: =+C42/B42 -> 0.055642587 | AK42: =+AF42/E42 -> 0.068109056 | AL42: =+E42/B42-1 -> -0.010830261 | AO42: =+F42 -> 46061 | AP42: =Tabla2[[#This Row],[Web + APP 2025]]+Tabla2[[#This Row],[Afiliados 2025]]+Tabla2[[#This Row],[TMK 2025]]+Tabla2[[#This Row],[WA 2025]]+Tabla2[[#This Row],[Ent. en Tienda 2025]] -> 1992770.2 | AQ42: =Tabla2[[#This Row],[Meli Drop 2025]]+Tabla2[[#This Row],[Meli Full 2025]]+Tabla2[[#This Row],[Amazon Drop 2025]]+Tabla2[[#This Row],[Amazon Full 2025]]+Tabla2[[#This Row],[TikTok 2025]]+Tabla2[[#This Row],[Shein 2025]] -> 332628 | AR42: =Tabla2[[#This Row],[Web + APP 2026]]+Tabla2[[#This Row],[Afiliados 2026]]+Tabla2[[#This Row],[TMK 2026]]+Tabla2[[#This Row],[WA 2026]]+Tabla2[[#This Row],[Ent. en Tienda 2026]] -> 2502585 | AS42: =Tabla2[[#This Row],[Meli Drop 2026]]+Tabla2[[#This Row],[Meli Full 2026]]+Tabla2[[#This Row],[Amazon Drop 2026]]+Tabla2[[#This Row],[Amazon Full 2026]]+Tabla2[[#This Row],[TikTok 2026]]+Tabla2[[#This Row],[Shein 2026]] -> 312981 | AT42: =+AR42/AP42-1 -> 0.25583218 | AU42: =+AS42/AQ42-1 -> -0.059065984 | AV42: =+H42 -> 1929957.6 | AW42: =+I42 -> 479990.24 | AX42: =+AR42/AV42 -> 1.2967047 | AY42: =+AS42/AW42 -> 0.65205701 | AZ42: =+(AR42+AS42)/(AV42+AW42) -> 1.1683099 | BA42: 0.034285017 | BB42: 0.024218723 | BC42: =+AR42-AV42 -> 572627.43 | BD42: =+AS42-AW42 -> -167009.24
A43: 45698 | B43: 26406954 | C43: =+J43+L43+N43+P43+R43+T43+V43+X43+Z43+AB43+AD43 -> 4228681.7 | D43: =+Tabla22[[#This Row],[Share diario]] -> 0.03012681 | E43: =+Tabla22[[#This Row],[Global 2026]] -> 22422064 | F43: 46062 | G43: =+H43+I43 -> 2824472.7 | H43: 2383122 | I43: 441350.75 | J43: 3630208 | K43: 2252123 | L43: 20464.655 | M43: =6100+3966 -> 10066 | N43: 83992 | O43: 16050 | P43: 8959 | Q43: 1868 | R43: 63382 | S43: 58213 | T43: 281151 | U43: 451605 | V43: 78555 | W43: 67176 | X43: 59569 | Y43: 11686 | Z43: 2401 | AA43: 3093 | AB43: 0 | AC43: 586 | AD43: 0 | AE43: 0 | AF43: =+AE43+AC43+AA43+Y43+W43+U43+S43+Q43+O43+M43+K43 -> 2872466 | AG43: =+AF43/G43 -> 1.0169919 | AH43: =+AF43-G43 -> 47993.281 | AI43: =+AF43/C43-1 -> -0.32071832 | AJ43: =+C43/B43 -> 0.16013515 | AK43: =+AF43/E43 -> 0.1281089 | AL43: =+E43/B43-1 -> -0.15090305 | AO43: =+F43 -> 46062 | AP43: =Tabla2[[#This Row],[Web + APP 2025]]+Tabla2[[#This Row],[Afiliados 2025]]+Tabla2[[#This Row],[TMK 2025]]+Tabla2[[#This Row],[WA 2025]]+Tabla2[[#This Row],[Ent. en Tienda 2025]] -> 3807005.7 | AQ43: =Tabla2[[#This Row],[Meli Drop 2025]]+Tabla2[[#This Row],[Meli Full 2025]]+Tabla2[[#This Row],[Amazon Drop 2025]]+Tabla2[[#This Row],[Amazon Full 2025]]+Tabla2[[#This Row],[TikTok 2025]]+Tabla2[[#This Row],[Shein 2025]] -> 421676 | AR43: =Tabla2[[#This Row],[Web + APP 2026]]+Tabla2[[#This Row],[Afiliados 2026]]+Tabla2[[#This Row],[TMK 2026]]+Tabla2[[#This Row],[WA 2026]]+Tabla2[[#This Row],[Ent. en Tienda 2026]] -> 2338320 | AS43: =Tabla2[[#This Row],[Meli Drop 2026]]+Tabla2[[#This Row],[Meli Full 2026]]+Tabla2[[#This Row],[Amazon Drop 2026]]+Tabla2[[#This Row],[Amazon Full 2026]]+Tabla2[[#This Row],[TikTok 2026]]+Tabla2[[#This Row],[Shein 2026]] -> 534146 | AT43: =+AR43/AP43-1 -> -0.38578499 | AU43: =+AS43/AQ43-1 -> 0.26672137 | AV43: =+H43 -> 2383122 | AW43: =+I43 -> 441350.75 | AX43: =+AR43/AV43 -> 0.98120031 | AY43: =+AS43/AW43 -> 1.2102528 | AZ43: =+(AR43+AS43)/(AV43+AW43) -> 1.0169919 | BA43: 0.031525054 | BB43: 0.02990541 | BC43: =+AR43-AV43 -> -44801.964 | BD43: =+AS43-AW43 -> 92795.245
A44: 45699 | B44: 28764494 | C44: =+J44+L44+N44+P44+R44+T44+V44+X44+Z44+AB44+AD44 -> 3584756.2 | D44: =+Tabla22[[#This Row],[Share diario]] -> 0.054784891 | E44: =+Tabla22[[#This Row],[Global 2026]] -> 27571599 | F44: 46063 | G44: =+H44+I44 -> 5112242 | H44: 4552737 | I44: 559504.98 | J44: 2855454 | K44: 4002151 | L44: 16592.241 | M44: =10914+11047 -> 21961 | N44: 62364 | O44: 55589 | P44: 4603 | Q44: 3319 | R44: 42383 | S44: 62975 | T44: 448251 | U44: 557077 | V44: 107546 | W44: 78209 | X44: 43052 | Y44: 21078 | Z44: 4511 | AA44: 953 | AB44: 0 | AC44: 844 | AD44: 0 | AE44: 0 | AF44: =+AE44+AC44+AA44+Y44+W44+U44+S44+Q44+O44+M44+K44 -> 4804156 | AG44: =+AF44/G44 -> 0.93973564 | AH44: =+AF44-G44 -> -308085.97 | AI44: =+AF44/C44-1 -> 0.34016253 | AJ44: =+C44/B44 -> 0.12462435 | AK44: =+AF44/E44 -> 0.17424292 | AL44: =+E44/B44-1 -> -0.041471093 | AO44: =+F44 -> 46063 | AP44: =Tabla2[[#This Row],[Web + APP 2025]]+Tabla2[[#This Row],[Afiliados 2025]]+Tabla2[[#This Row],[TMK 2025]]+Tabla2[[#This Row],[WA 2025]]+Tabla2[[#This Row],[Ent. en Tienda 2025]] -> 2981396.2 | AQ44: =Tabla2[[#This Row],[Meli Drop 2025]]+Tabla2[[#This Row],[Meli Full 2025]]+Tabla2[[#This Row],[Amazon Drop 2025]]+Tabla2[[#This Row],[Amazon Full 2025]]+Tabla2[[#This Row],[TikTok 2025]]+Tabla2[[#This Row],[Shein 2025]] -> 603360 | AR44: =Tabla2[[#This Row],[Web + APP 2026]]+Tabla2[[#This Row],[Afiliados 2026]]+Tabla2[[#This Row],[TMK 2026]]+Tabla2[[#This Row],[WA 2026]]+Tabla2[[#This Row],[Ent. en Tienda 2026]] -> 4145995 | AS44: =Tabla2[[#This Row],[Meli Drop 2026]]+Tabla2[[#This Row],[Meli Full 2026]]+Tabla2[[#This Row],[Amazon Drop 2026]]+Tabla2[[#This Row],[Amazon Full 2026]]+Tabla2[[#This Row],[TikTok 2026]]+Tabla2[[#This Row],[Shein 2026]] -> 658161 | AT44: =+AR44/AP44-1 -> 0.39062193 | AU44: =+AS44/AQ44-1 -> 0.090826372 | AV44: =+H44 -> 4552737 | AW44: =+I44 -> 559504.98 | AX44: =+AR44/AV44 -> 0.9106599 | AY44: =+AS44/AW44 -> 1.1763273 | AZ44: =+(AR44+AS44)/(AV44+AW44) -> 0.93973564 | BA44: 0.039964641 | BB44: 0.057131556 | BC44: =+AR44-AV44 -> -406741.99 | BD44: =+AS44-AW44 -> 98656.025
A45: 45700 | B45: 34103254 | C45: =+J45+L45+N45+P45+R45+T45+V45+X45+Z45+AB45+AD45 -> 3527108.8 | D45: =+Tabla22[[#This Row],[Share diario]] -> 0.046442484 | E45: =+Tabla22[[#This Row],[Global 2026]] -> 29524043 | F45: 46064 | G45: =+H45+I45 -> 4365978.1 | H45: 3565403.9 | I45: 800574.19 | J45: 2929364 | K45: 3104553 | L45: 19632.759 | M45: =12075+10720 -> 22795 | N45: 23666 | O45: 17436 | P45: 8628 | Q45: 696 | R45: 92989 | S45: 83559 | T45: 286849 | U45: 555761 | V45: 127459 | W45: 71762 | X45: 36103 | Y45: 24671 | Z45: 2418 | AA45: 4503 | AB45: 0 | AC45: -435 | AD45: 0 | AE45: 0 | AF45: =+AE45+AC45+AA45+Y45+W45+U45+S45+Q45+O45+M45+K45 -> 3885301 | AG45: =+AF45/G45 -> 0.88990391 | AH45: =+AF45-G45 -> -480677.13 | AI45: =+AF45/C45-1 -> 0.10155407 | AJ45: =+C45/B45 -> 0.10342441 | AK45: =+AF45/E45 -> 0.13159786 | AL45: =+E45/B45-1 -> -0.1342749 | AO45: =+F45 -> 46064 | AP45: =Tabla2[[#This Row],[Web + APP 2025]]+Tabla2[[#This Row],[Afiliados 2025]]+Tabla2[[#This Row],[TMK 2025]]+Tabla2[[#This Row],[WA 2025]]+Tabla2[[#This Row],[Ent. en Tienda 2025]] -> 3074279.8 | AQ45: =Tabla2[[#This Row],[Meli Drop 2025]]+Tabla2[[#This Row],[Meli Full 2025]]+Tabla2[[#This Row],[Amazon Drop 2025]]+Tabla2[[#This Row],[Amazon Full 2025]]+Tabla2[[#This Row],[TikTok 2025]]+Tabla2[[#This Row],[Shein 2025]] -> 452829 | AR45: =Tabla2[[#This Row],[Web + APP 2026]]+Tabla2[[#This Row],[Afiliados 2026]]+Tabla2[[#This Row],[TMK 2026]]+Tabla2[[#This Row],[WA 2026]]+Tabla2[[#This Row],[Ent. en Tienda 2026]] -> 3229039 | AS45: =Tabla2[[#This Row],[Meli Drop 2026]]+Tabla2[[#This Row],[Meli Full 2026]]+Tabla2[[#This Row],[Amazon Drop 2026]]+Tabla2[[#This Row],[Amazon Full 2026]]+Tabla2[[#This Row],[TikTok 2026]]+Tabla2[[#This Row],[Shein 2026]] -> 656262 | AT45: =+AR45/AP45-1 -> 0.050339999 | AU45: =+AS45/AQ45-1 -> 0.44924905 | AV45: =+H45 -> 3565403.9 | AW45: =+I45 -> 800574.19 | AX45: =+AR45/AV45 -> 0.90565867 | AY45: =+AS45/AW45 -> 0.81973914 | AZ45: =+(AR45+AS45)/(AV45+AW45) -> 0.88990391 | BA45: 0.057183871 | BB45: 0.044741674 | BC45: =+AR45-AV45 -> -336364.94 | BD45: =+AS45-AW45 -> -144312.19
A46: 45701 | B46: 39504620 | C46: =+J46+L46+N46+P46+R46+T46+V46+X46+Z46+AB46+AD46 -> 2181176.4 | D46: =+Tabla22[[#This Row],[Share diario]] -> 0.045695629 | E46: =+Tabla22[[#This Row],[Global 2026]] -> 33200957 | F46: 46065 | G46: =+H46+I46 -> 4277322.5 | H46: 3676481.8 | I46: 600840.64 | J46: 1665220 | K46: 2317644 | L46: 18078.448 | M46: =13963+11447 -> 25410 | N46: 39150 | O46: 26530 | P46: 4561 | Q46: 5396 | R46: 81122 | S46: 99852 | T46: 288539 | U46: 459284 | V46: 74526 | W46: 89138 | X46: 6407 | Y46: 11692 | Z46: 3573 | AA46: 1959 | AB46: 0 | AC46: 3313 | AD46: 0 | AE46: 0 | AF46: =+AE46+AC46+AA46+Y46+W46+U46+S46+Q46+O46+M46+K46 -> 3040218 | AG46: =+AF46/G46 -> 0.71077596 | AH46: =+AF46-G46 -> -1237104.5 | AI46: =+AF46/C46-1 -> 0.39384322 | AJ46: =+C46/B46 -> 0.055213199 | AK46: =+AF46/E46 -> 0.091570192 | AL46: =+E46/B46-1 -> -0.15956774 | AO46: =+F46 -> 46065 | AP46: =Tabla2[[#This Row],[Web + APP 2025]]+Tabla2[[#This Row],[Afiliados 2025]]+Tabla2[[#This Row],[TMK 2025]]+Tabla2[[#This Row],[WA 2025]]+Tabla2[[#This Row],[Ent. en Tienda 2025]] -> 1808131.4 | AQ46: =Tabla2[[#This Row],[Meli Drop 2025]]+Tabla2[[#This Row],[Meli Full 2025]]+Tabla2[[#This Row],[Amazon Drop 2025]]+Tabla2[[#This Row],[Amazon Full 2025]]+Tabla2[[#This Row],[TikTok 2025]]+Tabla2[[#This Row],[Shein 2025]] -> 373045 | AR46: =Tabla2[[#This Row],[Web + APP 2026]]+Tabla2[[#This Row],[Afiliados 2026]]+Tabla2[[#This Row],[TMK 2026]]+Tabla2[[#This Row],[WA 2026]]+Tabla2[[#This Row],[Ent. en Tienda 2026]] -> 2474832 | AS46: =Tabla2[[#This Row],[Meli Drop 2026]]+Tabla2[[#This Row],[Meli Full 2026]]+Tabla2[[#This Row],[Amazon Drop 2026]]+Tabla2[[#This Row],[Amazon Full 2026]]+Tabla2[[#This Row],[TikTok 2026]]+Tabla2[[#This Row],[Shein 2026]] -> 565386 | AT46: =+AR46/AP46-1 -> 0.3687235 | AU46: =+AS46/AQ46-1 -> 0.51559731 | AV46: =+H46 -> 3676481.8 | AW46: =+I46 -> 600840.64 | AX46: =+AR46/AV46 -> 0.67315224 | AY46: =+AS46/AW46 -> 0.94099161 | AZ46: =+(AR46+AS46)/(AV46+AW46) -> 0.71077596 | BA46: 0.042917189 | BB46: 0.046135572 | BC46: =+AR46-AV46 -> -1201649.8 | BD46: =+AS46-AW46 -> -35454.642
A47: 45702 | B47: 32593735 | C47: =+J47+L47+N47+P47+R47+T47+V47+X47+Z47+AB47+AD47 -> 1866043.4 | D47: =+Tabla22[[#This Row],[Share diario]] -> 0.028258338 | E47: =+Tabla22[[#This Row],[Global 2026]] -> 35824613 | F47: 46066 | G47: =+H47+I47 -> 2657293.8 | H47: 2162315.4 | I47: 494978.45 | J47: 1401802 | K47: 1758784 | L47: 14241.379 | M47: =8886+9726 -> 18612 | N47: 55802 | O47: 25664 | P47: 2882 | Q47: 3330 | R47: 95242 | S47: 68260 | T47: 211719 | U47: 399606 | V47: 60511 | W47: 59102 | X47: 20710 | Y47: 14235 | Z47: 3134 | AA47: 7832 | AB47: 0 | AC47: 2440 | AD47: 0 | AE47: 0 | AF47: =+AE47+AC47+AA47+Y47+W47+U47+S47+Q47+O47+M47+K47 -> 2357865 | AG47: =+AF47/G47 -> 0.88731813 | AH47: =+AF47-G47 -> -299428.84 | AI47: =+AF47/C47-1 -> 0.26356387 | AJ47: =+C47/B47 -> 0.057251597 | AK47: =+AF47/E47 -> 0.065816901 | AL47: =+E47/B47-1 -> 0.099125737 | AO47: =+F47 -> 46066 | AP47: =Tabla2[[#This Row],[Web + APP 2025]]+Tabla2[[#This Row],[Afiliados 2025]]+Tabla2[[#This Row],[TMK 2025]]+Tabla2[[#This Row],[WA 2025]]+Tabla2[[#This Row],[Ent. en Tienda 2025]] -> 1569969.4 | AQ47: =Tabla2[[#This Row],[Meli Drop 2025]]+Tabla2[[#This Row],[Meli Full 2025]]+Tabla2[[#This Row],[Amazon Drop 2025]]+Tabla2[[#This Row],[Amazon Full 2025]]+Tabla2[[#This Row],[TikTok 2025]]+Tabla2[[#This Row],[Shein 2025]] -> 296074 | AR47: =Tabla2[[#This Row],[Web + APP 2026]]+Tabla2[[#This Row],[Afiliados 2026]]+Tabla2[[#This Row],[TMK 2026]]+Tabla2[[#This Row],[WA 2026]]+Tabla2[[#This Row],[Ent. en Tienda 2026]] -> 1874650 | AS47: =Tabla2[[#This Row],[Meli Drop 2026]]+Tabla2[[#This Row],[Meli Full 2026]]+Tabla2[[#This Row],[Amazon Drop 2026]]+Tabla2[[#This Row],[Amazon Full 2026]]+Tabla2[[#This Row],[TikTok 2026]]+Tabla2[[#This Row],[Shein 2026]] -> 483215 | AT47: =+AR47/AP47-1 -> 0.19406787 | AU47: =+AS47/AQ47-1 -> 0.63207509 | AV47: =+H47 -> 2162315.4 | AW47: =+I47 -> 494978.45 | AX47: =+AR47/AV47 -> 0.86696418 | AY47: =+AS47/AW47 -> 0.97623442 | AZ47: =+(AR47+AS47)/(AV47+AW47) -> 0.88731813 | BA47: 0.035355604 | BB47: 0.027134544 | BC47: =+AR47-AV47 -> -287665.39 | BD47: =+AS47-AW47 -> -11763.451
A48: 45703 | B48: 42356911 | C48: =+J48+L48+N48+P48+R48+T48+V48+X48+Z48+AB48+AD48 -> 1856484.5 | D48: =+Tabla22[[#This Row],[Share diario]] -> 0.024175616 | E48: =+Tabla22[[#This Row],[Global 2026]] -> 40028256 | F48: 46067 | G48: =+H48+I48 -> 2270349.9 | H48: 1877501.2 | I48: 392848.72 | J48: 1480367 | K48: 1400645 | L48: 20915.517 | M48: =11423+8165 -> 19588 | N48: 13567 | O48: -861 | P48: 1142 | Q48: 1446 | R48: 55048 | S48: 76825 | T48: 234704 | U48: 365354 | V48: 34552 | W48: 48474 | X48: 16189 | Y48: 16510 | Z48: 0 | AA48: 7433 | AB48: 0 | AC48: 0 | AD48: 0 | AE48: 0 | AF48: =+AE48+AC48+AA48+Y48+W48+U48+S48+Q48+O48+M48+K48 -> 1935414 | AG48: =+AF48/G48 -> 0.85247388 | AH48: =+AF48-G48 -> -334935.91 | AI48: =+AF48/C48-1 -> 0.042515562 | AJ48: =+C48/B48 -> 0.043829554 | AK48: =+AF48/E48 -> 0.048351195 | AL48: =+E48/B48-1 -> -0.054976979 | AO48: =+F48 -> 46067 | AP48: =Tabla2[[#This Row],[Web + APP 2025]]+Tabla2[[#This Row],[Afiliados 2025]]+Tabla2[[#This Row],[TMK 2025]]+Tabla2[[#This Row],[WA 2025]]+Tabla2[[#This Row],[Ent. en Tienda 2025]] -> 1571039.5 | AQ48: =Tabla2[[#This Row],[Meli Drop 2025]]+Tabla2[[#This Row],[Meli Full 2025]]+Tabla2[[#This Row],[Amazon Drop 2025]]+Tabla2[[#This Row],[Amazon Full 2025]]+Tabla2[[#This Row],[TikTok 2025]]+Tabla2[[#This Row],[Shein 2025]] -> 285445 | AR48: =Tabla2[[#This Row],[Web + APP 2026]]+Tabla2[[#This Row],[Afiliados 2026]]+Tabla2[[#This Row],[TMK 2026]]+Tabla2[[#This Row],[WA 2026]]+Tabla2[[#This Row],[Ent. en Tienda 2026]] -> 1497643 | AS48: =Tabla2[[#This Row],[Meli Drop 2026]]+Tabla2[[#This Row],[Meli Full 2026]]+Tabla2[[#This Row],[Amazon Drop 2026]]+Tabla2[[#This Row],[Amazon Full 2026]]+Tabla2[[#This Row],[TikTok 2026]]+Tabla2[[#This Row],[Shein 2026]] -> 437771 | AT48: =+AR48/AP48-1 -> -0.046718441 | AU48: =+AS48/AQ48-1 -> 0.53364396 | AV48: =+H48 -> 1877501.2 | AW48: =+I48 -> 392848.72 | AX48: =+AR48/AV48 -> 0.79767885 | AY48: =+AS48/AW48 -> 1.1143501 | AZ48: =+(AR48+AS48)/(AV48+AW48) -> 0.85247388 | BA48: 0.028060623 | BB48: 0.023560457 | BC48: =+AR48-AV48 -> -379858.2 | BD48: =+AS48-AW48 -> 44922.282
A49: 45704 | B49: 44382937 | C49: =+J49+L49+N49+P49+R49+T49+V49+X49+Z49+AB49+AD49 -> 2548266.7 | D49: =+Tabla22[[#This Row],[Share diario]] -> 0.024051776 | E49: =+Tabla22[[#This Row],[Global 2026]] -> 41384863 | F49: 46068 | G49: =+H49+I49 -> 2257526.5 | H49: 1878781 | I49: 378745.52 | J49: 1932100 | K49: 2149329 | L49: 24901.724 | M49: =17478+10892 -> 28370 | N49: 13663 | O49: 178 | P49: 2471 | Q49: 0 | R49: 72548 | S49: 68941 | T49: 370770 | U49: 492948 | V49: 101714 | W49: 50253 | X49: 26966 | Y49: 25710 | Z49: 3133 | AA49: 9189 | AB49: 0 | AC49: 0 | AD49: 0 | AE49: 0 | AF49: =+AE49+AC49+AA49+Y49+W49+U49+S49+Q49+O49+M49+K49 -> 2824918 | AG49: =+AF49/G49 -> 1.2513333 | AH49: =+AF49-G49 -> 567391.52 | AI49: =+AF49/C49-1 -> 0.10856449 | AJ49: =+C49/B49 -> 0.05741546 | AK49: =+AF49/E49 -> 0.068259692 | AL49: =+E49/B49-1 -> -0.067550149 | AO49: =+F49 -> 46068 | AP49: =Tabla2[[#This Row],[Web + APP 2025]]+Tabla2[[#This Row],[Afiliados 2025]]+Tabla2[[#This Row],[TMK 2025]]+Tabla2[[#This Row],[WA 2025]]+Tabla2[[#This Row],[Ent. en Tienda 2025]] -> 2045683.7 | AQ49: =Tabla2[[#This Row],[Meli Drop 2025]]+Tabla2[[#This Row],[Meli Full 2025]]+Tabla2[[#This Row],[Amazon Drop 2025]]+Tabla2[[#This Row],[Amazon Full 2025]]+Tabla2[[#This Row],[TikTok 2025]]+Tabla2[[#This Row],[Shein 2025]] -> 502583 | AR49: =Tabla2[[#This Row],[Web + APP 2026]]+Tabla2[[#This Row],[Afiliados 2026]]+Tabla2[[#This Row],[TMK 2026]]+Tabla2[[#This Row],[WA 2026]]+Tabla2[[#This Row],[Ent. en Tienda 2026]] -> 2246818 | AS49: =Tabla2[[#This Row],[Meli Drop 2026]]+Tabla2[[#This Row],[Meli Full 2026]]+Tabla2[[#This Row],[Amazon Drop 2026]]+Tabla2[[#This Row],[Amazon Full 2026]]+Tabla2[[#This Row],[TikTok 2026]]+Tabla2[[#This Row],[Shein 2026]] -> 578100 | AT49: =+AR49/AP49-1 -> 0.098321296 | AU49: =+AS49/AQ49-1 -> 0.15025777 | AV49: =+H49 -> 1878781 | AW49: =+I49 -> 378745.52 | AX49: =+AR49/AV49 -> 1.1958914 | AY49: =+AS49/AW49 -> 1.5263547 | AZ49: =+(AR49+AS49)/(AV49+AW49) -> 1.2513333 | BA49: 0.027053252 | BB49: 0.023576516 | BC49: =+AR49-AV49 -> 368037.04 | BD49: =+AS49-AW49 -> 199354.48
A50: 45705 | B50: 24063181 | C50: =+J50+L50+N50+P50+R50+T50+V50+X50+Z50+AB50+AD50 -> 3727592.2 | D50: =+Tabla22[[#This Row],[Share diario]] -> 0.033014194 | E50: =+Tabla22[[#This Row],[Global 2026]] -> 23766868 | F50: 46069 | G50: =+H50+I50 -> 3113257.6 | H50: 2446400.3 | I50: 666857.23 | J50: 3064112 | K50: 3080170 | L50: 18136.207 | M50: =12628+12367 -> 24995 | N50: 41372 | O50: 27259 | P50: 9059 | Q50: 2265 | R50: 59366 | S50: 98172 | T50: 381579 | U50: 460199 | V50: 106292 | W50: 48934 | X50: 40654 | Y50: 24099 | Z50: 7022 | AA50: 5432 | AB50: 0 | AC50: 430 | AD50: 0 | AE50: 0 | AF50: =+AE50+AC50+AA50+Y50+W50+U50+S50+Q50+O50+M50+K50 -> 3771955 | AG50: =+AF50/G50 -> 1.2115782 | AH50: =+AF50-G50 -> 658697.42 | AI50: =+AF50/C50-1 -> 0.011901193 | AJ50: =+C50/B50 -> 0.15490854 | AK50: =+AF50/E50 -> 0.15870644 | AL50: =+E50/B50-1 -> -0.012313958 | AO50: =+F50 -> 46069 | AP50: =Tabla2[[#This Row],[Web + APP 2025]]+Tabla2[[#This Row],[Afiliados 2025]]+Tabla2[[#This Row],[TMK 2025]]+Tabla2[[#This Row],[WA 2025]]+Tabla2[[#This Row],[Ent. en Tienda 2025]] -> 3192045.2 | AQ50: =Tabla2[[#This Row],[Meli Drop 2025]]+Tabla2[[#This Row],[Meli Full 2025]]+Tabla2[[#This Row],[Amazon Drop 2025]]+Tabla2[[#This Row],[Amazon Full 2025]]+Tabla2[[#This Row],[TikTok 2025]]+Tabla2[[#This Row],[Shein 2025]] -> 535547 | AR50: =Tabla2[[#This Row],[Web + APP 2026]]+Tabla2[[#This Row],[Afiliados 2026]]+Tabla2[[#This Row],[TMK 2026]]+Tabla2[[#This Row],[WA 2026]]+Tabla2[[#This Row],[Ent. en Tienda 2026]] -> 3232861 | AS50: =Tabla2[[#This Row],[Meli Drop 2026]]+Tabla2[[#This Row],[Meli Full 2026]]+Tabla2[[#This Row],[Amazon Drop 2026]]+Tabla2[[#This Row],[Amazon Full 2026]]+Tabla2[[#This Row],[TikTok 2026]]+Tabla2[[#This Row],[Shein 2026]] -> 539094 | AT50: =+AR50/AP50-1 -> 0.012786722 | AU50: =+AS50/AQ50-1 -> 0.0066231349 | AV50: =+H50 -> 2446400.3 | AW50: =+I50 -> 666857.23 | AX50: =+AR50/AV50 -> 1.3214767 | AY50: =+AS50/AW50 -> 0.80840992 | AZ50: =+(AR50+AS50)/(AV50+AW50) -> 1.2115782 | BA50: 0.047632659 | BB50: 0.03069948 | BC50: =+AR50-AV50 -> 786460.65 | BD50: =+AS50-AW50 -> -127763.23
A51: 45706 | B51: 28049331 | C51: =+J51+L51+N51+P51+R51+T51+V51+X51+Z51+AB51+AD51 -> 3637685 | D51: =+Tabla22[[#This Row],[Share diario]] -> 0.048293002 | E51: =+Tabla22[[#This Row],[Global 2026]] -> 26877030 | F51: 46070 | G51: =+H51+I51 -> 4527911.5 | H51: 3817315.7 | I51: 710595.84 | J51: 3088415 | K51: 3594147 | L51: 23043.966 | M51: =15370+11491 -> 26861 | N51: 65981 | O51: 48038 | P51: 7052 | Q51: 4918 | R51: 29733 | S51: 78213 | T51: 361184 | U51: 470863 | V51: 44740 | W51: 44216 | X51: 15384 | Y51: 21475 | Z51: 2152 | AA51: 6664 | AB51: 0 | AC51: 0 | AD51: 0 | AE51: 947 | AF51: =+AE51+AC51+AA51+Y51+W51+U51+S51+Q51+O51+M51+K51 -> 4296342 | AG51: =+AF51/G51 -> 0.94885733 | AH51: =+AF51-G51 -> -231569.5 | AI51: =+AF51/C51-1 -> 0.18106489 | AJ51: =+C51/B51 -> 0.12968883 | AK51: =+AF51/E51 -> 0.15985181 | AL51: =+E51/B51-1 -> -0.041794259 | AO51: =+F51 -> 46070 | AP51: =Tabla2[[#This Row],[Web + APP 2025]]+Tabla2[[#This Row],[Afiliados 2025]]+Tabla2[[#This Row],[TMK 2025]]+Tabla2[[#This Row],[WA 2025]]+Tabla2[[#This Row],[Ent. en Tienda 2025]] -> 3214225 | AQ51: =Tabla2[[#This Row],[Meli Drop 2025]]+Tabla2[[#This Row],[Meli Full 2025]]+Tabla2[[#This Row],[Amazon Drop 2025]]+Tabla2[[#This Row],[Amazon Full 2025]]+Tabla2[[#This Row],[TikTok 2025]]+Tabla2[[#This Row],[Shein 2025]] -> 423460 | AR51: =Tabla2[[#This Row],[Web + APP 2026]]+Tabla2[[#This Row],[Afiliados 2026]]+Tabla2[[#This Row],[TMK 2026]]+Tabla2[[#This Row],[WA 2026]]+Tabla2[[#This Row],[Ent. en Tienda 2026]] -> 3752177 | AS51: =Tabla2[[#This Row],[Meli Drop 2026]]+Tabla2[[#This Row],[Meli Full 2026]]+Tabla2[[#This Row],[Amazon Drop 2026]]+Tabla2[[#This Row],[Amazon Full 2026]]+Tabla2[[#This Row],[TikTok 2026]]+Tabla2[[#This Row],[Shein 2026]] -> 544165 | AT51: =+AR51/AP51-1 -> 0.16736602 | AU51: =+AS51/AQ51-1 -> 0.28504463 | AV51: =+H51 -> 3817315.7 | AW51: =+I51 -> 710595.84 | AX51: =+AR51/AV51 -> 0.982936 | AY51: =+AS51/AW51 -> 0.76578692 | AZ51: =+(AR51+AS51)/(AV51+AW51) -> 0.94885733 | BA51: 0.050756846 | BB51: 0.047902873 | BC51: =+AR51-AV51 -> -65138.657 | BD51: =+AS51-AW51 -> -166430.84
A52: 45707 | B52: 28881637 | C52: =+J52+L52+N52+P52+R52+T52+V52+X52+Z52+AB52+AD52 -> 3611181 | D52: =+Tabla22[[#This Row],[Share diario]] -> 0.047128205 | E52: =+Tabla22[[#This Row],[Global 2026]] -> 29417270 | F52: 46071 | G52: =+H52+I52 -> 4405712.2 | H52: 3843840.1 | I52: 561872.09 | J52: 3113676 | K52: 3559563 | L52: 21506.034 | M52: =13096+10747 -> 23843 | N52: 65670 | O52: 14662 | P52: 2633 | Q52: 1851 | R52: 66784 | S52: 91613 | T52: 295101 | U52: 453814 | V52: 30136 | W52: 39979 | X52: 13695 | Y52: 30090 | Z52: 1980 | AA52: 3873 | AB52: 0 | AC52: 3359 | AD52: 0 | AE52: 0 | AF52: =+AE52+AC52+AA52+Y52+W52+U52+S52+Q52+O52+M52+K52 -> 4222647 | AG52: =+AF52/G52 -> 0.95844822 | AH52: =+AF52-G52 -> -183065.17 | AI52: =+AF52/C52-1 -> 0.16932576 | AJ52: =+C52/B52 -> 0.12503381 | AK52: =+AF52/E52 -> 0.14354313 | AL52: =+E52/B52-1 -> 0.018545798 | AO52: =+F52 -> 46071 | AP52: =Tabla2[[#This Row],[Web + APP 2025]]+Tabla2[[#This Row],[Afiliados 2025]]+Tabla2[[#This Row],[TMK 2025]]+Tabla2[[#This Row],[WA 2025]]+Tabla2[[#This Row],[Ent. en Tienda 2025]] -> 3270269 | AQ52: =Tabla2[[#This Row],[Meli Drop 2025]]+Tabla2[[#This Row],[Meli Full 2025]]+Tabla2[[#This Row],[Amazon Drop 2025]]+Tabla2[[#This Row],[Amazon Full 2025]]+Tabla2[[#This Row],[TikTok 2025]]+Tabla2[[#This Row],[Shein 2025]] -> 340912 | AR52: =Tabla2[[#This Row],[Web + APP 2026]]+Tabla2[[#This Row],[Afiliados 2026]]+Tabla2[[#This Row],[TMK 2026]]+Tabla2[[#This Row],[WA 2026]]+Tabla2[[#This Row],[Ent. en Tienda 2026]] -> 3691532 | AS52: =Tabla2[[#This Row],[Meli Drop 2026]]+Tabla2[[#This Row],[Meli Full 2026]]+Tabla2[[#This Row],[Amazon Drop 2026]]+Tabla2[[#This Row],[Amazon Full 2026]]+Tabla2[[#This Row],[TikTok 2026]]+Tabla2[[#This Row],[Shein 2026]] -> 531115 | AT52: =+AR52/AP52-1 -> 0.128816 | AU52: =+AS52/AQ52-1 -> 0.55792404 | AV52: =+H52 -> 3843840.1 | AW52: =+I52 -> 561872.09 | AX52: =+AR52/AV52 -> 0.96037606 | AY52: =+AS52/AW52 -> 0.94525962 | AZ52: =+(AR52+AS52)/(AV52+AW52) -> 0.95844822 | BA52: 0.040133721 | BB52: 0.048235724 | BC52: =+AR52-AV52 -> -152308.07 | BD52: =+AS52-AW52 -> -30757.093
A53: 45708 | B53: 35987596 | C53: =+J53+L53+N53+P53+R53+T53+V53+X53+Z53+AB53+AD53 -> 2980934.2 | D53: =+Tabla22[[#This Row],[Share diario]] -> 0.046784832 | E53: =+Tabla22[[#This Row],[Global 2026]] -> 35456665 | F53: 46072 | G53: =+H53+I53 -> 4363204.7 | H53: 3910862.3 | I53: 452342.46 | J53: 2421357 | K53: 3329797 | L53: 22405.172 | M53: =15937+12034 -> 27971 | N53: 55891 | O53: 23965 | P53: 2576 | Q53: 344 | R53: 61430 | S53: 65256 | T53: 357973 | U53: 368888 | V53: 24350 | W53: 35313 | X53: 28074 | Y53: 25716 | Z53: 6878 | AA53: 7482 | AB53: 0 | AC53: 1990 | AD53: 0 | AE53: 689 | AF53: =+AE53+AC53+AA53+Y53+W53+U53+S53+Q53+O53+M53+K53 -> 3887411 | AG53: =+AF53/G53 -> 0.89095315 | AH53: =+AF53-G53 -> -475793.74 | AI53: =+AF53/C53-1 -> 0.30409153 | AJ53: =+C53/B53 -> 0.082832267 | AK53: =+AF53/E53 -> 0.10963837 | AL53: =+E53/B53-1 -> -0.014753167 | AO53: =+F53 -> 46072 | AP53: =Tabla2[[#This Row],[Web + APP 2025]]+Tabla2[[#This Row],[Afiliados 2025]]+Tabla2[[#This Row],[TMK 2025]]+Tabla2[[#This Row],[WA 2025]]+Tabla2[[#This Row],[Ent. en Tienda 2025]] -> 2563659.2 | AQ53: =Tabla2[[#This Row],[Meli Drop 2025]]+Tabla2[[#This Row],[Meli Full 2025]]+Tabla2[[#This Row],[Amazon Drop 2025]]+Tabla2[[#This Row],[Amazon Full 2025]]+Tabla2[[#This Row],[TikTok 2025]]+Tabla2[[#This Row],[Shein 2025]] -> 417275 | AR53: =Tabla2[[#This Row],[Web + APP 2026]]+Tabla2[[#This Row],[Afiliados 2026]]+Tabla2[[#This Row],[TMK 2026]]+Tabla2[[#This Row],[WA 2026]]+Tabla2[[#This Row],[Ent. en Tienda 2026]] -> 3447333 | AS53: =Tabla2[[#This Row],[Meli Drop 2026]]+Tabla2[[#This Row],[Meli Full 2026]]+Tabla2[[#This Row],[Amazon Drop 2026]]+Tabla2[[#This Row],[Amazon Full 2026]]+Tabla2[[#This Row],[TikTok 2026]]+Tabla2[[#This Row],[Shein 2026]] -> 440078 | AT53: =+AR53/AP53-1 -> 0.3446924 | AU53: =+AS53/AQ53-1 -> 0.054647415 | AV53: =+H53 -> 3910862.3 | AW53: =+I53 -> 452342.46 | AX53: =+AR53/AV53 -> 0.88147645 | AY53: =+AS53/AW53 -> 0.97288678 | AZ53: =+(AR53+AS53)/(AV53+AW53) -> 0.89095315 | BA53: 0.032310176 | BB53: 0.049076774 | BC53: =+AR53-AV53 -> -463529.28 | BD53: =+AS53-AW53 -> -12264.462
A54: 45709 | B54: 36080831 | C54: =+J54+L54+N54+P54+R54+T54+V54+X54+Z54+AB54+AD54 -> 2474773.4 | D54: =+Tabla22[[#This Row],[Share diario]] -> 0.038619638 | E54: =+Tabla22[[#This Row],[Global 2026]] -> 36977163 | F54: 46073 | G54: =+H54+I54 -> 3619504.3 | H54: 3065838.9 | I54: 553665.46 | J54: 1897795 | K54: 2545784 | L54: 20191.379 | M54: =11741+8386 -> 20127 | N54: 54966 | O54: 11485 | P54: 2375 | Q54: 1656 | R54: 91325 | S54: 148228 | T54: 346747 | U54: 360812 | V54: 33465 | W54: 21316 | X54: 19690 | Y54: 16275 | Z54: 8219 | AA54: 3147 | AB54: 0 | AC54: 1306 | AD54: 0 | AE54: 0 | AF54: =+AE54+AC54+AA54+Y54+W54+U54+S54+Q54+O54+M54+K54 -> 3130136 | AG54: =+AF54/G54 -> 0.86479686 | AH54: =+AF54-G54 -> -489368.34 | AI54: =+AF54/C54-1 -> 0.26481723 | AJ54: =+C54/B54 -> 0.0685897 | AK54: =+AF54/E54 -> 0.084650518 | AL54: =+E54/B54-1 -> 0.024842332 | AO54: =+F54 -> 46073 | AP54: =Tabla2[[#This Row],[Web + APP 2025]]+Tabla2[[#This Row],[Afiliados 2025]]+Tabla2[[#This Row],[TMK 2025]]+Tabla2[[#This Row],[WA 2025]]+Tabla2[[#This Row],[Ent. en Tienda 2025]] -> 2066652.4 | AQ54: =Tabla2[[#This Row],[Meli Drop 2025]]+Tabla2[[#This Row],[Meli Full 2025]]+Tabla2[[#This Row],[Amazon Drop 2025]]+Tabla2[[#This Row],[Amazon Full 2025]]+Tabla2[[#This Row],[TikTok 2025]]+Tabla2[[#This Row],[Shein 2025]] -> 408121 | AR54: =Tabla2[[#This Row],[Web + APP 2026]]+Tabla2[[#This Row],[Afiliados 2026]]+Tabla2[[#This Row],[TMK 2026]]+Tabla2[[#This Row],[WA 2026]]+Tabla2[[#This Row],[Ent. en Tienda 2026]] -> 2727280 | AS54: =Tabla2[[#This Row],[Meli Drop 2026]]+Tabla2[[#This Row],[Meli Full 2026]]+Tabla2[[#This Row],[Amazon Drop 2026]]+Tabla2[[#This Row],[Amazon Full 2026]]+Tabla2[[#This Row],[TikTok 2026]]+Tabla2[[#This Row],[Shein 2026]] -> 402856 | AT54: =+AR54/AP54-1 -> 0.31966074 | AU54: =+AS54/AQ54-1 -> -0.012900586 | AV54: =+H54 -> 3065838.9 | AW54: =+I54 -> 553665.46 | AX54: =+AR54/AV54 -> 0.88957056 | AY54: =+AS54/AW54 -> 0.72761627 | AZ54: =+(AR54+AS54)/(AV54+AW54) -> 0.86479686 | BA54: 0.039547533 | BB54: 0.038472713 | BC54: =+AR54-AV54 -> -338558.88 | BD54: =+AS54-AW54 -> -150809.46
A55: 45710 | B55: 47042220 | C55: =+J55+L55+N55+P55+R55+T55+V55+X55+Z55+AB55+AD55 -> 2208107.7 | D55: =+Tabla22[[#This Row],[Share diario]] -> 0.032062047 | E55: =+Tabla22[[#This Row],[Global 2026]] -> 49550104 | F55: 46074 | G55: =+H55+I55 -> 3012995.8 | H55: 2471476.4 | I55: 541519.39 | J55: 1719612 | K55: 2157328 | L55: 22776.724 | M55: =16471+12358 -> 28829 | N55: 25877 | O55: 12510 | P55: 3459 | Q55: 215 | R55: 44179 | S55: 61838 | T55: 327055 | U55: 366612 | V55: 34049 | W55: 23690 | X55: 21382 | Y55: 14858 | Z55: 9718 | AA55: 4463 | AB55: 0 | AC55: 1379 | AD55: 0 | AE55: 0 | AF55: =+AE55+AC55+AA55+Y55+W55+U55+S55+Q55+O55+M55+K55 -> 2671722 | AG55: =+AF55/G55 -> 0.88673273 | AH55: =+AF55-G55 -> -341273.82 | AI55: =+AF55/C55-1 -> 0.20995999 | AJ55: =+C55/B55 -> 0.04693885 | AK55: =+AF55/E55 -> 0.053919604 | AL55: =+E55/B55-1 -> 0.053311345 | AO55: =+F55 -> 46074 | AP55: =Tabla2[[#This Row],[Web + APP 2025]]+Tabla2[[#This Row],[Afiliados 2025]]+Tabla2[[#This Row],[TMK 2025]]+Tabla2[[#This Row],[WA 2025]]+Tabla2[[#This Row],[Ent. en Tienda 2025]] -> 1815903.7 | AQ55: =Tabla2[[#This Row],[Meli Drop 2025]]+Tabla2[[#This Row],[Meli Full 2025]]+Tabla2[[#This Row],[Amazon Drop 2025]]+Tabla2[[#This Row],[Amazon Full 2025]]+Tabla2[[#This Row],[TikTok 2025]]+Tabla2[[#This Row],[Shein 2025]] -> 392204 | AR55: =Tabla2[[#This Row],[Web + APP 2026]]+Tabla2[[#This Row],[Afiliados 2026]]+Tabla2[[#This Row],[TMK 2026]]+Tabla2[[#This Row],[WA 2026]]+Tabla2[[#This Row],[Ent. en Tienda 2026]] -> 2260720 | AS55: =Tabla2[[#This Row],[Meli Drop 2026]]+Tabla2[[#This Row],[Meli Full 2026]]+Tabla2[[#This Row],[Amazon Drop 2026]]+Tabla2[[#This Row],[Amazon Full 2026]]+Tabla2[[#This Row],[TikTok 2026]]+Tabla2[[#This Row],[Shein 2026]] -> 411002 | AT55: =+AR55/AP55-1 -> 0.24495587 | AU55: =+AS55/AQ55-1 -> 0.047929139 | AV55: =+H55 -> 2471476.4 | AW55: =+I55 -> 541519.39 | AX55: =+AR55/AV55 -> 0.91472448 | AY55: =+AS55/AW55 -> 0.75897929 | AZ55: =+(AR55+AS55)/(AV55+AW55) -> 0.88673273 | BA55: 0.038679956 | BB55: 0.031014155 | BC55: =+AR55-AV55 -> -210756.43 | BD55: =+AS55-AW55 -> -130517.39
A56: 45711 | B56: 46157405 | C56: =+J56+L56+N56+P56+R56+T56+V56+X56+Z56+AB56+AD56 -> 2545543.6 | D56: =+Tabla22[[#This Row],[Share diario]] -> 0.028607247 | E56: =+Tabla22[[#This Row],[Global 2026]] -> 40534030 | F56: 46075 | G56: =+H56+I56 -> 2692009.9 | H56: 2171610.1 | I56: 520399.76 | J56: 1980647 | K56: 2371363 | L56: 20783.621 | M56: =18154+11801 -> 29955 | N56: 20320 | O56: -835 | P56: 1308 | Q56: 361 | R56: 92867 | S56: 73803 | T56: 375118 | U56: 303085 | V56: 29980 | W56: 29461 | X56: 15301 | Y56: 21582 | Z56: 9219 | AA56: 4347 | AB56: 0 | AC56: 413 | AD56: 0 | AE56: 0 | AF56: =+AE56+AC56+AA56+Y56+W56+U56+S56+Q56+O56+M56+K56 -> 2833535 | AG56: =+AF56/G56 -> 1.0525723 | AH56: =+AF56-G56 -> 141525.11 | AI56: =+AF56/C56-1 -> 0.11313551 | AJ56: =+C56/B56 -> 0.055149193 | AK56: =+AF56/E56 -> 0.06990509 | AL56: =+E56/B56-1 -> -0.1218304 | AO56: =+F56 -> 46075 | AP56: =Tabla2[[#This Row],[Web + APP 2025]]+Tabla2[[#This Row],[Afiliados 2025]]+Tabla2[[#This Row],[TMK 2025]]+Tabla2[[#This Row],[WA 2025]]+Tabla2[[#This Row],[Ent. en Tienda 2025]] -> 2115925.6 | AQ56: =Tabla2[[#This Row],[Meli Drop 2025]]+Tabla2[[#This Row],[Meli Full 2025]]+Tabla2[[#This Row],[Amazon Drop 2025]]+Tabla2[[#This Row],[Amazon Full 2025]]+Tabla2[[#This Row],[TikTok 2025]]+Tabla2[[#This Row],[Shein 2025]] -> 429618 | AR56: =Tabla2[[#This Row],[Web + APP 2026]]+Tabla2[[#This Row],[Afiliados 2026]]+Tabla2[[#This Row],[TMK 2026]]+Tabla2[[#This Row],[WA 2026]]+Tabla2[[#This Row],[Ent. en Tienda 2026]] -> 2474647 | AS56: =Tabla2[[#This Row],[Meli Drop 2026]]+Tabla2[[#This Row],[Meli Full 2026]]+Tabla2[[#This Row],[Amazon Drop 2026]]+Tabla2[[#This Row],[Amazon Full 2026]]+Tabla2[[#This Row],[TikTok 2026]]+Tabla2[[#This Row],[Shein 2026]] -> 358888 | AT56: =+AR56/AP56-1 -> 0.16953402 | AU56: =+AS56/AQ56-1 -> -0.16463463 | AV56: =+H56 -> 2171610.1 | AW56: =+I56 -> 520399.76 | AX56: =+AR56/AV56 -> 1.1395448 | AY56: =+AS56/AW56 -> 0.68963906 | AZ56: =+(AR56+AS56)/(AV56+AW56) -> 1.0525723 | BA56: 0.037171411 | BB56: 0.027251182 | BC56: =+AR56-AV56 -> 303036.87 | BD56: =+AS56-AW56 -> -161511.76
A57: 45712 | B57: 26433260 | C57: =+J57+L57+N57+P57+R57+T57+V57+X57+Z57+AB57+AD57 -> 3325119.5 | D57: =+Tabla22[[#This Row],[Share diario]] -> 0.032978914 | E57: =+Tabla22[[#This Row],[Global 2026]] -> 22062756 | F57: 46076 | G57: =+H57+I57 -> 3100444.4 | H57: 2530401.5 | I57: 570042.9 | J57: 2773046 | K57: 3389716 | L57: 19384.483 | M57: =12794+10935 -> 23729 | N57: 44133 | O57: 28866 | P57: 1728 | Q57: 2677 | R57: 54932 | S57: 76508 | T57: 362431 | U57: 327888 | V57: 32310 | W57: 34023 | X57: 32251 | Y57: 20904 | Z57: 4904 | AA57: 3447 | AB57: 0 | AC57: 430 | AD57: 0 | AE57: 0 | AF57: =+AE57+AC57+AA57+Y57+W57+U57+S57+Q57+O57+M57+K57 -> 3908188 | AG57: =+AF57/G57 -> 1.2605251 | AH57: =+AF57-G57 -> 807743.6 | AI57: =+AF57/C57-1 -> 0.17535265 | AJ57: =+C57/B57 -> 0.12579302 | AK57: =+AF57/E57 -> 0.17713961 | AL57: =+E57/B57-1 -> -0.16534109 | AO57: =+F57 -> 46076 | AP57: =Tabla2[[#This Row],[Web + APP 2025]]+Tabla2[[#This Row],[Afiliados 2025]]+Tabla2[[#This Row],[TMK 2025]]+Tabla2[[#This Row],[WA 2025]]+Tabla2[[#This Row],[Ent. en Tienda 2025]] -> 2893223.5 | AQ57: =Tabla2[[#This Row],[Meli Drop 2025]]+Tabla2[[#This Row],[Meli Full 2025]]+Tabla2[[#This Row],[Amazon Drop 2025]]+Tabla2[[#This Row],[Amazon Full 2025]]+Tabla2[[#This Row],[TikTok 2025]]+Tabla2[[#This Row],[Shein 2025]] -> 431896 | AR57: =Tabla2[[#This Row],[Web + APP 2026]]+Tabla2[[#This Row],[Afiliados 2026]]+Tabla2[[#This Row],[TMK 2026]]+Tabla2[[#This Row],[WA 2026]]+Tabla2[[#This Row],[Ent. en Tienda 2026]] -> 3521496 | AS57: =Tabla2[[#This Row],[Meli Drop 2026]]+Tabla2[[#This Row],[Meli Full 2026]]+Tabla2[[#This Row],[Amazon Drop 2026]]+Tabla2[[#This Row],[Amazon Full 2026]]+Tabla2[[#This Row],[TikTok 2026]]+Tabla2[[#This Row],[Shein 2026]] -> 386692 | AT57: =+AR57/AP57-1 -> 0.21715312 | AU57: =+AS57/AQ57-1 -> -0.10466409 | AV57: =+H57 -> 2530401.5 | AW57: =+I57 -> 570042.9 | AX57: =+AR57/AV57 -> 1.3916748 | AY57: =+AS57/AW57 -> 0.67835597 | AZ57: =+(AR57+AS57)/(AV57+AW57) -> 1.2605251 | BA57: 0.04071735 | BB57: 0.031753597 | BC57: =+AR57-AV57 -> 991094.49 | BD57: =+AS57-AW57 -> -183350.9
A58: 45713 | B58: 29392120 | C58: =+J58+L58+N58+P58+R58+T58+V58+X58+Z58+AB58+AD58 -> 3789269.2 | D58: =+Tabla22[[#This Row],[Share diario]] -> 0.043078747 | E58: =+Tabla22[[#This Row],[Global 2026]] -> 27778475 | F58: 46077 | G58: =+H58+I58 -> 4033025 | H58: 3459959.6 | I58: 573065.48 | J58: 3237704 | K58: 3790804 | L58: 19955.172 | M58: =11627+12049 -> 23676 | N58: 86781 | O58: 53511 | P58: 8087 | Q58: 3950 | R58: 28472 | S58: 71433 | T58: 347028 | U58: 328991 | V58: 43531 | W58: 44374 | X58: 10995 | Y58: 15412 | Z58: 6716 | AA58: 2538 | AB58: 0 | AC58: -680 | AD58: 0 | AE58: 0 | AF58: =+AE58+AC58+AA58+Y58+W58+U58+S58+Q58+O58+M58+K58 -> 4334009 | AG58: =+AF58/G58 -> 1.0746298 | AH58: =+AF58-G58 -> 300983.97 | AI58: =+AF58/C58-1 -> 0.14375855 | AJ58: =+C58/B58 -> 0.12892126 | AK58: =+AF58/E58 -> 0.15602041 | AL58: =+E58/B58-1 -> -0.054900599 | AO58: =+F58 -> 46077 | AP58: =Tabla2[[#This Row],[Web + APP 2025]]+Tabla2[[#This Row],[Afiliados 2025]]+Tabla2[[#This Row],[TMK 2025]]+Tabla2[[#This Row],[WA 2025]]+Tabla2[[#This Row],[Ent. en Tienda 2025]] -> 3380999.2 | AQ58: =Tabla2[[#This Row],[Meli Drop 2025]]+Tabla2[[#This Row],[Meli Full 2025]]+Tabla2[[#This Row],[Amazon Drop 2025]]+Tabla2[[#This Row],[Amazon Full 2025]]+Tabla2[[#This Row],[TikTok 2025]]+Tabla2[[#This Row],[Shein 2025]] -> 408270 | AR58: =Tabla2[[#This Row],[Web + APP 2026]]+Tabla2[[#This Row],[Afiliados 2026]]+Tabla2[[#This Row],[TMK 2026]]+Tabla2[[#This Row],[WA 2026]]+Tabla2[[#This Row],[Ent. en Tienda 2026]] -> 3943374 | AS58: =Tabla2[[#This Row],[Meli Drop 2026]]+Tabla2[[#This Row],[Meli Full 2026]]+Tabla2[[#This Row],[Amazon Drop 2026]]+Tabla2[[#This Row],[Amazon Full 2026]]+Tabla2[[#This Row],[TikTok 2026]]+Tabla2[[#This Row],[Shein 2026]] -> 390635 | AT58: =+AR58/AP58-1 -> 0.16633391 | AU58: =+AS58/AQ58-1 -> -0.043194455 | AV58: =+H58 -> 3459959.6 | AW58: =+I58 -> 573065.48 | AX58: =+AR58/AV58 -> 1.1397168 | AY58: =+AS58/AW58 -> 0.68165857 | AZ58: =+(AR58+AS58)/(AV58+AW58) -> 1.0746298 | BA58: 0.040933249 | BB58: 0.043418469 | BC58: =+AR58-AV58 -> 483414.45 | BD58: =+AS58-AW58 -> -182430.48
A59: 45714 | B59: 32989145 | C59: =+J59+L59+N59+P59+R59+T59+V59+X59+Z59+AB59+AD59 -> 3432841.1 | D59: =+Tabla22[[#This Row],[Share diario]] -> 0.049092061 | E59: =+Tabla22[[#This Row],[Global 2026]] -> 31602573 | F59: 46078 | G59: =+H59+I59 -> 4584999.8 | H59: 4043282.7 | I59: 541717.09 | J59: 2904631 | K59: 3614722 | L59: 19587.069 | M59: =16122+15095 -> 31217 | N59: 64657 | O59: 80631 | P59: 3724 | Q59: -491 | R59: 45659 | S59: 33888 | T59: 329946 | U59: 578952 | V59: 38488 | W59: 54562 | X59: 17323 | Y59: 28200 | Z59: 8826 | AA59: 5951 | AB59: 0 | AC59: 7009 | AD59: 0 | AE59: 775 | AF59: =+AE59+AC59+AA59+Y59+W59+U59+S59+Q59+O59+M59+K59 -> 4435416 | AG59: =+AF59/G59 -> 0.9673754 | AH59: =+AF59-G59 -> -149583.76 | AI59: =+AF59/C59-1 -> 0.29205399 | AJ59: =+C59/B59 -> 0.10405972 | AK59: =+AF59/E59 -> 0.14034984 | AL59: =+E59/B59-1 -> -0.042031159 | AO59: =+F59 -> 46078 | AP59: =Tabla2[[#This Row],[Web + APP 2025]]+Tabla2[[#This Row],[Afiliados 2025]]+Tabla2[[#This Row],[TMK 2025]]+Tabla2[[#This Row],[WA 2025]]+Tabla2[[#This Row],[Ent. en Tienda 2025]] -> 3038258.1 | AQ59: =Tabla2[[#This Row],[Meli Drop 2025]]+Tabla2[[#This Row],[Meli Full 2025]]+Tabla2[[#This Row],[Amazon Drop 2025]]+Tabla2[[#This Row],[Amazon Full 2025]]+Tabla2[[#This Row],[TikTok 2025]]+Tabla2[[#This Row],[Shein 2025]] -> 394583 | AR59: =Tabla2[[#This Row],[Web + APP 2026]]+Tabla2[[#This Row],[Afiliados 2026]]+Tabla2[[#This Row],[TMK 2026]]+Tabla2[[#This Row],[WA 2026]]+Tabla2[[#This Row],[Ent. en Tienda 2026]] -> 3759967 | AS59: =Tabla2[[#This Row],[Meli Drop 2026]]+Tabla2[[#This Row],[Meli Full 2026]]+Tabla2[[#This Row],[Amazon Drop 2026]]+Tabla2[[#This Row],[Amazon Full 2026]]+Tabla2[[#This Row],[TikTok 2026]]+Tabla2[[#This Row],[Shein 2026]] -> 675449 | AT59: =+AR59/AP59-1 -> 0.23754037 | AU59: =+AS59/AQ59-1 -> 0.71180461 | AV59: =+H59 -> 4043282.7 | AW59: =+I59 -> 541717.09 | AX59: =+AR59/AV59 -> 0.92992929 | AY59: =+AS59/AW59 -> 1.2468667 | AZ59: =+(AR59+AS59)/(AV59+AW59) -> 0.9673754 | BA59: 0.038694078 | BB59: 0.050738496 | BC59: =+AR59-AV59 -> -283315.67 | BD59: =+AS59-AW59 -> 133731.91
A60: 45715 | B60: 36962992 | C60: =+J60+L60+N60+P60+R60+T60+V60+X60+Z60+AB60+AD60 -> 3033501.7 | D60: =+Tabla22[[#This Row],[Share diario]] -> 0.04447434 | E60: =+Tabla22[[#This Row],[Global 2026]] -> 36200123 | F60: 46079 | G60: =+H60+I60 -> 4156960.4 | H60: 3633404.1 | I60: 523556.36 | J60: 2452213 | K60: 2872787 | L60: 20014.655 | M60: =12579+13284 -> 25863 | N60: 22443 | O60: 7979 | P60: 8872 | Q60: 0 | R60: 97686 | S60: 126103 | T60: 371645 | U60: 530958 | V60: 41902 | W60: 91753 | X60: 12405 | Y60: 15632 | Z60: 6321 | AA60: 4939 | AB60: 0 | AC60: 5544 | AD60: 0 | AE60: 0 | AF60: =+AE60+AC60+AA60+Y60+W60+U60+S60+Q60+O60+M60+K60 -> 3681558 | AG60: =+AF60/G60 -> 0.88563701 | AH60: =+AF60-G60 -> -475402.45 | AI60: =+AF60/C60-1 -> 0.21363309 | AJ60: =+C60/B60 -> 0.082068618 | AK60: =+AF60/E60 -> 0.10170015 | AL60: =+E60/B60-1 -> -0.020638724 | AO60: =+F60 -> 46079 | AP60: =Tabla2[[#This Row],[Web + APP 2025]]+Tabla2[[#This Row],[Afiliados 2025]]+Tabla2[[#This Row],[TMK 2025]]+Tabla2[[#This Row],[WA 2025]]+Tabla2[[#This Row],[Ent. en Tienda 2025]] -> 2601228.7 | AQ60: =Tabla2[[#This Row],[Meli Drop 2025]]+Tabla2[[#This Row],[Meli Full 2025]]+Tabla2[[#This Row],[Amazon Drop 2025]]+Tabla2[[#This Row],[Amazon Full 2025]]+Tabla2[[#This Row],[TikTok 2025]]+Tabla2[[#This Row],[Shein 2025]] -> 432273 | AR60: =Tabla2[[#This Row],[Web + APP 2026]]+Tabla2[[#This Row],[Afiliados 2026]]+Tabla2[[#This Row],[TMK 2026]]+Tabla2[[#This Row],[WA 2026]]+Tabla2[[#This Row],[Ent. en Tienda 2026]] -> 3032732 | AS60: =Tabla2[[#This Row],[Meli Drop 2026]]+Tabla2[[#This Row],[Meli Full 2026]]+Tabla2[[#This Row],[Amazon Drop 2026]]+Tabla2[[#This Row],[Amazon Full 2026]]+Tabla2[[#This Row],[TikTok 2026]]+Tabla2[[#This Row],[Shein 2026]] -> 648826 | AT60: =+AR60/AP60-1 -> 0.16588443 | AU60: =+AS60/AQ60-1 -> 0.50096351 | AV60: =+H60 -> 3633404.1 | AW60: =+I60 -> 523556.36 | AX60: =+AR60/AV60 -> 0.83468063 | AY60: =+AS60/AW60 -> 1.2392668 | AZ60: =+(AR60+AS60)/(AV60+AW60) -> 0.88563701 | BA60: 0.037396883 | BB60: 0.045594997 | BC60: =+AR60-AV60 -> -600672.09 | BD60: =+AS60-AW60 -> 125269.64
A61: 45716 | B61: 42693027 | C61: =+J61+L61+N61+P61+R61+T61+V61+X61+Z61+AB61+AD61 -> 2409436.8 | D61: =+Tabla22[[#This Row],[Share diario]] -> 0.039300678 | E61: =+Tabla22[[#This Row],[Global 2026]] -> 42656916 | F61: 46080 | G61: =+H61+I61 -> 3684333.3 | H61: 3110767.6 | I61: 573565.71 | J61: 1747242 | K61: 2328816 | L61: 17482.759 | M61: =11774+8876 -> 20650 | N61: 73006 | O61: 23531 | P61: 3125 | Q61: 6440 | R61: 104847 | S61: 122038 | T61: 394351 | U61: 450008 | V61: 40984 | W61: 106960 | X61: 18424 | Y61: 15315 | Z61: 9975 | AA61: 3641 | AB61: 0 | AC61: 2547 | AD61: 0 | AE61: 775 | AF61: =+AE61+AC61+AA61+Y61+W61+U61+S61+Q61+O61+M61+K61 -> 3080721 | AG61: =+AF61/G61 -> 0.83616783 | AH61: =+AF61-G61 -> -603612.33 | AI61: =+AF61/C61-1 -> 0.27860629 | AJ61: =+C61/B61 -> 0.056436307 | AK61: =+AF61/E61 -> 0.072220903 | AL61: =+E61/B61-1 -> -0.00084582899 | AO61: =+F61 -> 46080 | AP61: =Tabla2[[#This Row],[Web + APP 2025]]+Tabla2[[#This Row],[Afiliados 2025]]+Tabla2[[#This Row],[TMK 2025]]+Tabla2[[#This Row],[WA 2025]]+Tabla2[[#This Row],[Ent. en Tienda 2025]] -> 1945702.8 | AQ61: =Tabla2[[#This Row],[Meli Drop 2025]]+Tabla2[[#This Row],[Meli Full 2025]]+Tabla2[[#This Row],[Amazon Drop 2025]]+Tabla2[[#This Row],[Amazon Full 2025]]+Tabla2[[#This Row],[TikTok 2025]]+Tabla2[[#This Row],[Shein 2025]] -> 463734 | AR61: =Tabla2[[#This Row],[Web + APP 2026]]+Tabla2[[#This Row],[Afiliados 2026]]+Tabla2[[#This Row],[TMK 2026]]+Tabla2[[#This Row],[WA 2026]]+Tabla2[[#This Row],[Ent. en Tienda 2026]] -> 2501475 | AS61: =Tabla2[[#This Row],[Meli Drop 2026]]+Tabla2[[#This Row],[Meli Full 2026]]+Tabla2[[#This Row],[Amazon Drop 2026]]+Tabla2[[#This Row],[Amazon Full 2026]]+Tabla2[[#This Row],[TikTok 2026]]+Tabla2[[#This Row],[Shein 2026]] -> 579246 | AT61: =+AR61/AP61-1 -> 0.28564088 | AU61: =+AS61/AQ61-1 -> 0.24909107 | AV61: =+H61 -> 3110767.6 | AW61: =+I61 -> 573565.71 | AX61: =+AR61/AV61 -> 0.80413432 | AY61: =+AS61/AW61 -> 1.0099035 | AZ61: =+(AR61+AS61)/(AV61+AW61) -> 0.83616783 | BA61: 0.040968979 | BB61: 0.039036517 | BC61: =+AR61-AV61 -> -609292.62 | BD61: =+AS61-AW61 -> 5680.2905
A62: 45717 | B62: 50836467 | C62: =+J62+L62+N62+P62+R62+T62+V62+X62+Z62+AB62+AD62 -> 2062135.5 | D62: =+Tabla22[[#This Row],[Share diario]] -> 0.031215575 | E62: =+Tabla22[[#This Row],[Global 2026]] -> 51597186 | F62: 46081 | G62: =+H62+I62 -> 2942144.8 | H62: 2326834.7 | I62: 615310.05 | J62: 1522696 | K62: 2298757 | L62: 23759.483 | M62: =17672+10634 -> 28306 | N62: 41023 | O62: 7846 | P62: 2722 | Q62: 0 | R62: 37541 | S62: 67232 | T62: 384483 | U62: 415460 | V62: 29795 | W62: 103810 | X62: 13746 | Y62: 16109 | Z62: 6370 | AA62: 3746 | AB62: 0 | AC62: -5 | AD62: 0 | AE62: 1895 | AF62: =+AE62+AC62+AA62+Y62+W62+U62+S62+Q62+O62+M62+K62 -> 2943156 | AG62: =+AF62/G62 -> 1.0003437 | AH62: =+AF62-G62 -> 1011.2346 | AI62: =+AF62/C62-1 -> 0.42723697 | AJ62: =+C62/B62 -> 0.040564099 | AK62: =+AF62/E62 -> 0.057041018 | AL62: =+E62/B62-1 -> 0.014964041 | AO62: =+F62 -> 46081 | AP62: =Tabla2[[#This Row],[Web + APP 2025]]+Tabla2[[#This Row],[Afiliados 2025]]+Tabla2[[#This Row],[TMK 2025]]+Tabla2[[#This Row],[WA 2025]]+Tabla2[[#This Row],[Ent. en Tienda 2025]] -> 1627741.5 | AQ62: =Tabla2[[#This Row],[Meli Drop 2025]]+Tabla2[[#This Row],[Meli Full 2025]]+Tabla2[[#This Row],[Amazon Drop 2025]]+Tabla2[[#This Row],[Amazon Full 2025]]+Tabla2[[#This Row],[TikTok 2025]]+Tabla2[[#This Row],[Shein 2025]] -> 434394 | AR62: =Tabla2[[#This Row],[Web + APP 2026]]+Tabla2[[#This Row],[Afiliados 2026]]+Tabla2[[#This Row],[TMK 2026]]+Tabla2[[#This Row],[WA 2026]]+Tabla2[[#This Row],[Ent. en Tienda 2026]] -> 2402141 | AS62: =Tabla2[[#This Row],[Meli Drop 2026]]+Tabla2[[#This Row],[Meli Full 2026]]+Tabla2[[#This Row],[Amazon Drop 2026]]+Tabla2[[#This Row],[Amazon Full 2026]]+Tabla2[[#This Row],[TikTok 2026]]+Tabla2[[#This Row],[Shein 2026]] -> 541015 | AT62: =+AR62/AP62-1 -> 0.47575093 | AU62: =+AS62/AQ62-1 -> 0.24544768 | AV62: =+H62 -> 2326834.7 | AW62: =+I62 -> 615310.05 | AX62: =+AR62/AV62 -> 1.0323643 | AY62: =+AS62/AW62 -> 0.87925592 | AZ62: =+(AR62+AS62)/(AV62+AW62) -> 1.0003437 | BA62: 0.043950718 | BB62: 0.02919907 | BC62: =+AR62-AV62 -> 75306.283 | BD62: =+AS62-AW62 -> -74295.049
A63: 45718 | B63: 48002488 | C63: =+J63+L63+N63+P63+R63+T63+V63+X63+Z63+AB63+AD63 -> 2666615.9 | D63: =+Tabla22[[#This Row],[Share diario]] -> 0.022488732 | E63: =+Tabla22[[#This Row],[Global 2026]] -> 52843119 | F63: 46082 | G63: =+H63+I63 -> 2805782.4 | H63: 2136915.4 | I63: 668867 | J63: 2021359 | K63: 2769749 | L63: 23281.897 | M63: =19644+14270 -> 33914 | N63: 3956 | O63: 26512 | P63: 7228 | Q63: 0 | R63: 118573 | S63: 96454 | T63: 444525 | U63: 447295 | V63: 31189 | W63: 95383 | X63: 12849 | Y63: 21210 | Z63: 3655 | AA63: 3536 | AB63: 0 | AC63: 430 | AD63: 0 | AE63: 0 | AF63: =+AE63+AC63+AA63+Y63+W63+U63+S63+Q63+O63+M63+K63 -> 3494483 | AG63: =+AF63/G63 -> 1.2454576 | AH63: =+AF63-G63 -> 688700.62 | AI63: =+AF63/C63-1 -> 0.31045607 | AJ63: =+C63/B63 -> 0.055551618 | AK63: =+AF63/E63 -> 0.066129386 | AL63: =+E63/B63-1 -> 0.10084125 | AO63: =+F63 -> 46082 | AP63: =Tabla2[[#This Row],[Web + APP 2025]]+Tabla2[[#This Row],[Afiliados 2025]]+Tabla2[[#This Row],[TMK 2025]]+Tabla2[[#This Row],[WA 2025]]+Tabla2[[#This Row],[Ent. en Tienda 2025]] -> 2174397.9 | AQ63: =Tabla2[[#This Row],[Meli Drop 2025]]+Tabla2[[#This Row],[Meli Full 2025]]+Tabla2[[#This Row],[Amazon Drop 2025]]+Tabla2[[#This Row],[Amazon Full 2025]]+Tabla2[[#This Row],[TikTok 2025]]+Tabla2[[#This Row],[Shein 2025]] -> 492218 | AR63: =Tabla2[[#This Row],[Web + APP 2026]]+Tabla2[[#This Row],[Afiliados 2026]]+Tabla2[[#This Row],[TMK 2026]]+Tabla2[[#This Row],[WA 2026]]+Tabla2[[#This Row],[Ent. en Tienda 2026]] -> 2926629 | AS63: =Tabla2[[#This Row],[Meli Drop 2026]]+Tabla2[[#This Row],[Meli Full 2026]]+Tabla2[[#This Row],[Amazon Drop 2026]]+Tabla2[[#This Row],[Amazon Full 2026]]+Tabla2[[#This Row],[TikTok 2026]]+Tabla2[[#This Row],[Shein 2026]] -> 567854 | AT63: =+AR63/AP63-1 -> 0.34594915 | AU63: =+AS63/AQ63-1 -> 0.15366362 | AV63: =+H63 -> 2136915.4 | AW63: =+I63 -> 668867 | AX63: =+AR63/AV63 -> 1.3695577 | AY63: =+AS63/AW63 -> 0.84897894 | AZ63: =+(AR63+AS63)/(AV63+AW63) -> 1.2454576 | BA63: =+AQ63/(SUM($AQ$63:$AQ$93)) -> 0.028973199 | BB63: =+AP63/(SUM($AP$63:$AP$93)) -> 0.028392939 | BC63: =+AR63-AV63 -> 789713.62 | BD63: =+AS63-AW63 -> -101013 | BE63: Promedio Diario 1 -26 Mar | BF63: =+AVERAGE(AQ63:AQ88) -> 539849.81
A64: 45719 | B64: 28870398 | C64: =+J64+L64+N64+P64+R64+T64+V64+X64+Z64+AB64+AD64 -> 3575627.5 | D64: =+Tabla22[[#This Row],[Share diario]] -> 0.029080927 | E64: =+Tabla22[[#This Row],[Global 2026]] -> 29862876 | F64: 46083 | G64: =+H64+I64 -> 3622374.4 | H64: 2854571.4 | I64: 767803 | J64: 2894647 | K64: 3687641 | L64: 17015.517 | M64: 26936 | N64: 70126 | O64: 15825 | P64: 2478 | Q64: 7457 | R64: 47499 | S64: 107185 | T64: 481304 | U64: 452113 | V64: 33324 | W64: 85564 | X64: 22831 | Y64: 6520 | Z64: 6403 | AA64: 4483 | AB64: 0 | AC64: 515 | AD64: 0 | AE64: 0 | AF64: =+AE64+AC64+AA64+Y64+W64+U64+S64+Q64+O64+M64+K64 -> 4394239 | AG64: =+AF64/G64 -> 1.2130825 | AH64: =+AF64-G64 -> 771864.58 | AI64: =+AF64/C64-1 -> 0.22894205 | AJ64: =+C64/B64 -> 0.12385099 | AK64: =+AF64/E64 -> 0.14714721 | AL64: =+E64/B64-1 -> 0.034377011 | AO64: =+F64 -> 46083 | AP64: =Tabla2[[#This Row],[Web + APP 2025]]+Tabla2[[#This Row],[Afiliados 2025]]+Tabla2[[#This Row],[TMK 2025]]+Tabla2[[#This Row],[WA 2025]]+Tabla2[[#This Row],[Ent. en Tienda 2025]] -> 3031765.5 | AQ64: =Tabla2[[#This Row],[Meli Drop 2025]]+Tabla2[[#This Row],[Meli Full 2025]]+Tabla2[[#This Row],[Amazon Drop 2025]]+Tabla2[[#This Row],[Amazon Full 2025]]+Tabla2[[#This Row],[TikTok 2025]]+Tabla2[[#This Row],[Shein 2025]] -> 543862 | AR64: =Tabla2[[#This Row],[Web + APP 2026]]+Tabla2[[#This Row],[Afiliados 2026]]+Tabla2[[#This Row],[TMK 2026]]+Tabla2[[#This Row],[WA 2026]]+Tabla2[[#This Row],[Ent. en Tienda 2026]] -> 3845044 | AS64: =Tabla2[[#This Row],[Meli Drop 2026]]+Tabla2[[#This Row],[Meli Full 2026]]+Tabla2[[#This Row],[Amazon Drop 2026]]+Tabla2[[#This Row],[Amazon Full 2026]]+Tabla2[[#This Row],[TikTok 2026]]+Tabla2[[#This Row],[Shein 2026]] -> 549195 | AT64: =+AR64/AP64-1 -> 0.26825244 | AU64: =+AS64/AQ64-1 -> 0.0098057963 | AV64: =+H64 -> 2854571.4 | AW64: =+I64 -> 767803 | AX64: =+AR64/AV64 -> 1.3469777 | AY64: =+AS64/AW64 -> 0.71528113 | AZ64: =+(AR64+AS64)/(AV64+AW64) -> 1.2130825 | BA64: =+AQ64/(SUM($AQ$63:$AQ$93)) -> 0.032013096 | BB64: =+AP64/(SUM($AP$63:$AP$93)) -> 0.039588307 | BC64: =+AR64-AV64 -> 990472.58 | BD64: =+AS64-AW64 -> -218608 | BE64: Promedio Diario 27 - 31 Mar | BF64: =+AVERAGE(AQ89:AQ93) -> 590528
A65: 45720 | B65: 30118136 | C65: =+J65+L65+N65+P65+R65+T65+V65+X65+Z65+AB65+AD65 -> 3876973.2 | D65: =+Tabla22[[#This Row],[Share diario]] -> 0.038994203 | E65: =+Tabla22[[#This Row],[Global 2026]] -> 33171704 | F65: 46084 | G65: =+H65+I65 -> 4645559.3 | H65: 3980132.3 | I65: 665427 | J65: 3324837 | K65: 4158362 | L65: 20705.172 | M65: =15135+6897 -> 22032 | N65: 55930 | O65: 47632 | P65: 5121 | Q65: 2071 | R65: 33120 | S65: 74989 | T65: 340219 | U65: 653421 | V65: 73972 | W65: 126548 | X65: 16003 | Y65: 5908 | Z65: 7066 | AA65: 4036 | AB65: 0 | AC65: 2049 | AD65: 0 | AE65: 775 | AF65: =+AE65+AC65+AA65+Y65+W65+U65+S65+Q65+O65+M65+K65 -> 5097823 | AG65: =+AF65/G65 -> 1.097354 | AH65: =+AF65-G65 -> 452263.75 | AI65: =+AF65/C65-1 -> 0.31489767 | AJ65: =+C65/B65 -> 0.12872554 | AK65: =+AF65/E65 -> 0.15367987 | AL65: =+E65/B65-1 -> 0.10138635 | AO65: =+F65 -> 46084 | AP65: =Tabla2[[#This Row],[Web + APP 2025]]+Tabla2[[#This Row],[Afiliados 2025]]+Tabla2[[#This Row],[TMK 2025]]+Tabla2[[#This Row],[WA 2025]]+Tabla2[[#This Row],[Ent. en Tienda 2025]] -> 3439713.2 | AQ65: =Tabla2[[#This Row],[Meli Drop 2025]]+Tabla2[[#This Row],[Meli Full 2025]]+Tabla2[[#This Row],[Amazon Drop 2025]]+Tabla2[[#This Row],[Amazon Full 2025]]+Tabla2[[#This Row],[TikTok 2025]]+Tabla2[[#This Row],[Shein 2025]] -> 437260 | AR65: =Tabla2[[#This Row],[Web + APP 2026]]+Tabla2[[#This Row],[Afiliados 2026]]+Tabla2[[#This Row],[TMK 2026]]+Tabla2[[#This Row],[WA 2026]]+Tabla2[[#This Row],[Ent. en Tienda 2026]] -> 4305086 | AS65: =Tabla2[[#This Row],[Meli Drop 2026]]+Tabla2[[#This Row],[Meli Full 2026]]+Tabla2[[#This Row],[Amazon Drop 2026]]+Tabla2[[#This Row],[Amazon Full 2026]]+Tabla2[[#This Row],[TikTok 2026]]+Tabla2[[#This Row],[Shein 2026]] -> 792737 | AT65: =+AR65/AP65-1 -> 0.25158285 | AU65: =+AS65/AQ65-1 -> 0.81296483 | AV65: =+H65 -> 3980132.3 | AW65: =+I65 -> 665427 | AX65: =+AR65/AV65 -> 1.081644 | AY65: =+AS65/AW65 -> 1.1913208 | AZ65: =+(AR65+AS65)/(AV65+AW65) -> 1.097354 | BA65: =+AQ65/(SUM($AQ$63:$AQ$93)) -> 0.025738232 | BB65: =+AP65/(SUM($AP$63:$AP$93)) -> 0.044915222 | BC65: =+AR65-AV65 -> 324953.75 | BD65: =+AS65-AW65 -> 127310
A66: 45721 | B66: 32149498 | C66: =+J66+L66+N66+P66+R66+T66+V66+X66+Z66+AB66+AD66 -> 3691707.2 | D66: =+Tabla22[[#This Row],[Share diario]] -> 0.042280545 | E66: =+Tabla22[[#This Row],[Global 2026]] -> 34892813 | F66: 46085 | G66: =+H66+I66 -> 5143890 | H66: 4515690 | I66: 628200 | J66: 3006578 | K66: 4047073 | L66: 20405.172 | M66: 21637 | N66: 61036 | O66: 50390 | P66: 128 | Q66: 7095 | R66: 94925 | S66: 81778 | T66: 365903 | U66: 480522 | V66: 115450 | W66: 55623 | X66: 19487 | Y66: 12102 | Z66: 7795 | AA66: 6133 | AB66: 0 | AC66: 1534 | AD66: 0 | AE66: 0 | AF66: =+AE66+AC66+AA66+Y66+W66+U66+S66+Q66+O66+M66+K66 -> 4763887 | AG66: =+AF66/G66 -> 0.92612536 | AH66: =+AF66-G66 -> -380003.04 | AI66: =+AF66/C66-1 -> 0.29042927 | AJ66: =+C66/B66 -> 0.11482939 | AK66: =+AF66/E66 -> 0.13652918 | AL66: =+E66/B66-1 -> 0.085329948 | AO66: =+F66 -> 46085 | AP66: =Tabla2[[#This Row],[Web + APP 2025]]+Tabla2[[#This Row],[Afiliados 2025]]+Tabla2[[#This Row],[TMK 2025]]+Tabla2[[#This Row],[WA 2025]]+Tabla2[[#This Row],[Ent. en Tienda 2025]] -> 3183072.2 | AQ66: =Tabla2[[#This Row],[Meli Drop 2025]]+Tabla2[[#This Row],[Meli Full 2025]]+Tabla2[[#This Row],[Amazon Drop 2025]]+Tabla2[[#This Row],[Amazon Full 2025]]+Tabla2[[#This Row],[TikTok 2025]]+Tabla2[[#This Row],[Shein 2025]] -> 508635 | AR66: =Tabla2[[#This Row],[Web + APP 2026]]+Tabla2[[#This Row],[Afiliados 2026]]+Tabla2[[#This Row],[TMK 2026]]+Tabla2[[#This Row],[WA 2026]]+Tabla2[[#This Row],[Ent. en Tienda 2026]] -> 4207973 | AS66: =Tabla2[[#This Row],[Meli Drop 2026]]+Tabla2[[#This Row],[Meli Full 2026]]+Tabla2[[#This Row],[Amazon Drop 2026]]+Tabla2[[#This Row],[Amazon Full 2026]]+Tabla2[[#This Row],[TikTok 2026]]+Tabla2[[#This Row],[Shein 2026]] -> 555914 | AT66: =+AR66/AP66-1 -> 0.32198479 | AU66: =+AS66/AQ66-1 -> 0.092952707 | AV66: =+H66 -> 4515690 | AW66: =+I66 -> 628200 | AX66: =+AR66/AV66 -> 0.93185603 | AY66: =+AS66/AW66 -> 0.88493155 | AZ66: =+(AR66+AS66)/(AV66+AW66) -> 0.92612536 | BA66: =+AQ66/(SUM($AQ$63:$AQ$93)) -> 0.029939545 | BB66: =+AP66/(SUM($AP$63:$AP$93)) -> 0.041564045 | BC66: =+AR66-AV66 -> -307717.04 | BD66: =+AS66-AW66 -> -72286 | BE66: Total 1-27 marzo | BF66: =+BF63*26 -> 14036095
A67: 45722 | B67: 37519228 | C67: =+J67+L67+N67+P67+R67+T67+V67+X67+Z67+AB67+AD67 -> 2779470.1 | D67: =+Tabla22[[#This Row],[Share diario]] -> 0.040260116 | E67: =+Tabla22[[#This Row],[Global 2026]] -> 38712693 | F67: 46086 | G67: =+H67+I67 -> 4846185.2 | H67: 4178769.2 | I67: 667416 | J67: 2158066 | K67: 3273154 | L67: 20349.138 | M67: =15908+12659 -> 28567 | N67: 52546 | O67: 21743 | P67: 1600 | Q67: 154 | R67: 74876 | S67: 89264 | T67: 330846 | U67: 393807 | V67: 120380 | W67: 40051 | X67: 14076 | Y67: 5342 | Z67: 6731 | AA67: 5065 | AB67: 0 | AC67: 560 | AD67: 0 | AE67: 0 | AF67: =+AE67+AC67+AA67+Y67+W67+U67+S67+Q67+O67+M67+K67 -> 3857707 | AG67: =+AF67/G67 -> 0.79602964 | AH67: =+AF67-G67 -> -988478.15 | AI67: =+AF67/C67-1 -> 0.38792892 | AJ67: =+C67/B67 -> 0.074081219 | AK67: =+AF67/E67 -> 0.099649668 | AL67: =+E67/B67-1 -> 0.031809423 | AO67: =+F67 -> 46086 | AP67: =Tabla2[[#This Row],[Web + APP 2025]]+Tabla2[[#This Row],[Afiliados 2025]]+Tabla2[[#This Row],[TMK 2025]]+Tabla2[[#This Row],[WA 2025]]+Tabla2[[#This Row],[Ent. en Tienda 2025]] -> 2307437.1 | AQ67: =Tabla2[[#This Row],[Meli Drop 2025]]+Tabla2[[#This Row],[Meli Full 2025]]+Tabla2[[#This Row],[Amazon Drop 2025]]+Tabla2[[#This Row],[Amazon Full 2025]]+Tabla2[[#This Row],[TikTok 2025]]+Tabla2[[#This Row],[Shein 2025]] -> 472033 | AR67: =Tabla2[[#This Row],[Web + APP 2026]]+Tabla2[[#This Row],[Afiliados 2026]]+Tabla2[[#This Row],[TMK 2026]]+Tabla2[[#This Row],[WA 2026]]+Tabla2[[#This Row],[Ent. en Tienda 2026]] -> 3412882 | AS67: =Tabla2[[#This Row],[Meli Drop 2026]]+Tabla2[[#This Row],[Meli Full 2026]]+Tabla2[[#This Row],[Amazon Drop 2026]]+Tabla2[[#This Row],[Amazon Full 2026]]+Tabla2[[#This Row],[TikTok 2026]]+Tabla2[[#This Row],[Shein 2026]] -> 444825 | AT67: =+AR67/AP67-1 -> 0.47907908 | AU67: =+AS67/AQ67-1 -> -0.057640038 | AV67: =+H67 -> 4178769.2 | AW67: =+I67 -> 667416 | AX67: =+AR67/AV67 -> 0.81671944 | AY67: =+AS67/AW67 -> 0.66648837 | AZ67: =+(AR67+AS67)/(AV67+AW67) -> 0.79602964 | BA67: =+AQ67/(SUM($AQ$63:$AQ$93)) -> 0.027785059 | BB67: =+AP67/(SUM($AP$63:$AP$93)) -> 0.030130144 | BC67: =+AR67-AV67 -> -765887.15 | BD67: =+AS67-AW67 -> -222591 | BE67: Total 25-31 marzo | BF67: =+BF64*5 -> 2952640
A68: 45723 | B68: 39523265 | C68: =+J68+L68+N68+P68+R68+T68+V68+X68+Z68+AB68+AD68 -> 2664201.1 | D68: =+Tabla22[[#This Row],[Share diario]] -> 0.030311665 | E68: =+Tabla22[[#This Row],[Global 2026]] -> 39872258 | F68: 46087 | G68: =+H68+I68 -> 3647918.7 | H68: 3029226.7 | I68: 618692 | J68: 2008601 | K68: 2313818 | L68: 17718.103 | M68: 23488 | N68: 60599 | O68: 32023 | P68: 1392 | Q68: 1687 | R68: 69932 | S68: 118330 | T68: 369062 | U68: 299324 | V68: 123391 | W68: 33674 | X68: 10054 | Y68: 6895 | Z68: 3452 | AA68: 6866 | AB68: 0 | AC68: 387 | AD68: 0 | AE68: 0 | AF68: =+AE68+AC68+AA68+Y68+W68+U68+S68+Q68+O68+M68+K68 -> 2836492 | AG68: =+AF68/G68 -> 0.77756448 | AH68: =+AF68-G68 -> -811426.67 | AI68: =+AF68/C68-1 -> 0.064668878 | AJ68: =+C68/B68 -> 0.067408426 | AK68: =+AF68/E68 -> 0.071139488 | AL68: =+E68/B68-1 -> 0.008830065 | AO68: =+F68 -> 46087 | AP68: =Tabla2[[#This Row],[Web + APP 2025]]+Tabla2[[#This Row],[Afiliados 2025]]+Tabla2[[#This Row],[TMK 2025]]+Tabla2[[#This Row],[WA 2025]]+Tabla2[[#This Row],[Ent. en Tienda 2025]] -> 2158242.1 | AQ68: =Tabla2[[#This Row],[Meli Drop 2025]]+Tabla2[[#This Row],[Meli Full 2025]]+Tabla2[[#This Row],[Amazon Drop 2025]]+Tabla2[[#This Row],[Amazon Full 2025]]+Tabla2[[#This Row],[TikTok 2025]]+Tabla2[[#This Row],[Shein 2025]] -> 505959 | AR68: =Tabla2[[#This Row],[Web + APP 2026]]+Tabla2[[#This Row],[Afiliados 2026]]+Tabla2[[#This Row],[TMK 2026]]+Tabla2[[#This Row],[WA 2026]]+Tabla2[[#This Row],[Ent. en Tienda 2026]] -> 2489346 | AS68: =Tabla2[[#This Row],[Meli Drop 2026]]+Tabla2[[#This Row],[Meli Full 2026]]+Tabla2[[#This Row],[Amazon Drop 2026]]+Tabla2[[#This Row],[Amazon Full 2026]]+Tabla2[[#This Row],[TikTok 2026]]+Tabla2[[#This Row],[Shein 2026]] -> 347146 | AT68: =+AR68/AP68-1 -> 0.1534137 | AU68: =+AS68/AQ68-1 -> -0.31388512 | AV68: =+H68 -> 3029226.7 | AW68: =+I68 -> 618692 | AX68: =+AR68/AV68 -> 0.82177607 | AY68: =+AS68/AW68 -> 0.56109664 | AZ68: =+(AR68+AS68)/(AV68+AW68) -> 0.77756448 | BA68: =+AQ68/(SUM($AQ$63:$AQ$93)) -> 0.029782029 | BB68: =+AP68/(SUM($AP$63:$AP$93)) -> 0.028181979 | BC68: =+AR68-AV68 -> -539880.67 | BD68: =+AS68-AW68 -> -271546
A69: 45724 | B69: 48982826 | C69: =+J69+L69+N69+P69+R69+T69+V69+X69+Z69+AB69+AD69 -> 2136044.4 | D69: =+Tabla22[[#This Row],[Share diario]] -> 0.029054592 | E69: =+Tabla22[[#This Row],[Global 2026]] -> 52578844 | F69: 46088 | G69: =+H69+I69 -> 3375221.9 | H69: 2833361.9 | I69: 541860 | J69: 1587947 | K69: 2036782 | L69: 16966.379 | M69: 29622 | N69: 27670 | O69: 12659 | P69: 257 | Q69: 1118 | R69: 58244 | S69: 33500 | T69: 305214 | U69: 318037 | V69: 118323 | W69: 29312 | X69: 13685 | Y69: 16246 | Z69: 7738 | AA69: 7308 | AB69: 0 | AC69: 430 | AD69: 0 | AE69: 0 | AF69: =+AE69+AC69+AA69+Y69+W69+U69+S69+Q69+O69+M69+K69 -> 2485014 | AG69: =+AF69/G69 -> 0.73625203 | AH69: =+AF69-G69 -> -890207.93 | AI69: =+AF69/C69-1 -> 0.1633719 | AJ69: =+C69/B69 -> 0.043608027 | AK69: =+AF69/E69 -> 0.047262621 | AL69: =+E69/B69-1 -> 0.073413853 | AO69: =+F69 -> 46088 | AP69: =Tabla2[[#This Row],[Web + APP 2025]]+Tabla2[[#This Row],[Afiliados 2025]]+Tabla2[[#This Row],[TMK 2025]]+Tabla2[[#This Row],[WA 2025]]+Tabla2[[#This Row],[Ent. en Tienda 2025]] -> 1691084.4 | AQ69: =Tabla2[[#This Row],[Meli Drop 2025]]+Tabla2[[#This Row],[Meli Full 2025]]+Tabla2[[#This Row],[Amazon Drop 2025]]+Tabla2[[#This Row],[Amazon Full 2025]]+Tabla2[[#This Row],[TikTok 2025]]+Tabla2[[#This Row],[Shein 2025]] -> 444960 | AR69: =Tabla2[[#This Row],[Web + APP 2026]]+Tabla2[[#This Row],[Afiliados 2026]]+Tabla2[[#This Row],[TMK 2026]]+Tabla2[[#This Row],[WA 2026]]+Tabla2[[#This Row],[Ent. en Tienda 2026]] -> 2113681 | AS69: =Tabla2[[#This Row],[Meli Drop 2026]]+Tabla2[[#This Row],[Meli Full 2026]]+Tabla2[[#This Row],[Amazon Drop 2026]]+Tabla2[[#This Row],[Amazon Full 2026]]+Tabla2[[#This Row],[TikTok 2026]]+Tabla2[[#This Row],[Shein 2026]] -> 371333 | AT69: =+AR69/AP69-1 -> 0.24989683 | AU69: =+AS69/AQ69-1 -> -0.16546881 | AV69: =+H69 -> 2833361.9 | AW69: =+I69 -> 541860 | AX69: =+AR69/AV69 -> 0.74599753 | AY69: =+AS69/AW69 -> 0.68529325 | AZ69: =+(AR69+AS69)/(AV69+AW69) -> 0.73625203 | BA69: =+AQ69/(SUM($AQ$63:$AQ$93)) -> 0.026191473 | BB69: =+AP69/(SUM($AP$63:$AP$93)) -> 0.022081908 | BC69: =+AR69-AV69 -> -719680.93 | BD69: =+AS69-AW69 -> -170527 | BE69: Total | BF69: =+BF67+BF66 -> 16988735
